Workbook

Sheet DAILY_STATUS
A1: DAILY STATUS BOARD
A2: Change day (B3). Mark sick/swap in ROSTER first → this updates automatically.
A3: SELECT DAY → | B3: 1 | C3: (1-28)
A4: Day of Week | B4: =CHOOSE(MOD(B3-1,7)+1,"Mon","Tue","Wed","Thu","Fri","Sat","Sun") -> Mon
A6: TODAY'S ASSIGNMENTS
A7: Staff | B7: Team | C7: Skill | D7: Shift | E7: Status | G7: Action Needed
A8: =ROSTER!A4 -> Alice Johnson | B8: =ROSTER!B4 -> Day A | C8: =ROSTER!D4 -> 1 | D8: =IF(OR($B$3<1,$B$3>28),"—",INDEX(ROSTER!E4:AF4,1,$B$3)) -> EL | E8: =IF(D8="SICK","🔴 SICK",IF(D8="AL","🟡 AL",IF(D8="OFF","⬜ OFF",IF(D8="AVL","🔵 FLOAT",IF(OR(D8="AG-E",D8="AG-L",D8="AG-N"),"🟠 AGENCY",IF(OR(D8="OC-E",D8="OC-L",D8="OC-EL",D8="OC-N"),"🟣 ON-CALL","🟢 WORKING")))))) -> 🟢 WORKING | G8: =IF(D8="SICK","⚡ FIND COVER — check Available list below",IF(D8="AVL","Ready to deploy if gap arises",IF(OR(D8="AG-E",D8="AG-L",D8="AG-N"),"Confirm agency arrival. Handover pack ready?","")))
A9: =ROSTER!A5 -> Bob Smith | B9: =ROSTER!B5 -> Day A | C9: =ROSTER!D5 -> 0.5 | D9: =IF(OR($B$3<1,$B$3>28),"—",INDEX(ROSTER!E5:AF5,1,$B$3)) -> EL | E9: =IF(D9="SICK","🔴 SICK",IF(D9="AL","🟡 AL",IF(D9="OFF","⬜ OFF",IF(D9="AVL","🔵 FLOAT",IF(OR(D9="AG-E",D9="AG-L",D9="AG-N"),"🟠 AGENCY",IF(OR(D9="OC-E",D9="OC-L",D9="OC-EL",D9="OC-N"),"🟣 ON-CALL","🟢 WORKING")))))) -> 🟢 WORKING | G9: =IF(D9="SICK","⚡ FIND COVER — check Available list below",IF(D9="AVL","Ready to deploy if gap arises",IF(OR(D9="AG-E",D9="AG-L",D9="AG-N"),"Confirm agency arrival. Handover pack ready?","")))
A10: =ROSTER!A6 -> Carol Davis | B10: =ROSTER!B6 -> Day A | C10: =ROSTER!D6 -> 1 | D10: =IF(OR($B$3<1,$B$3>28),"—",INDEX(ROSTER!E6:AF6,1,$B$3)) -> EL | E10: =IF(D10="SICK","🔴 SICK",IF(D10="AL","🟡 AL",IF(D10="OFF","⬜ OFF",IF(D10="AVL","🔵 FLOAT",IF(OR(D10="AG-E",D10="AG-L",D10="AG-N"),"🟠 AGENCY",IF(OR(D10="OC-E",D10="OC-L",D10="OC-EL",D10="OC-N"),"🟣 ON-CALL","🟢 WORKING")))))) -> 🟢 WORKING | G10: =IF(D10="SICK","⚡ FIND COVER — check Available list below",IF(D10="AVL","Ready to deploy if gap arises",IF(OR(D10="AG-E",D10="AG-L",D10="AG-N"),"Confirm agency arrival. Handover pack ready?","")))
A11: =ROSTER!A7 -> David Wilson | B11: =ROSTER!B7 -> Day A | C11: =ROSTER!D7 -> 0.5 | D11: =IF(OR($B$3<1,$B$3>28),"—",INDEX(ROSTER!E7:AF7,1,$B$3)) -> EL | E11: =IF(D11="SICK","🔴 SICK",IF(D11="AL","🟡 AL",IF(D11="OFF","⬜ OFF",IF(D11="AVL","🔵 FLOAT",IF(OR(D11="AG-E",D11="AG-L",D11="AG-N"),"🟠 AGENCY",IF(OR(D11="OC-E",D11="OC-L",D11="OC-EL",D11="OC-N"),"🟣 ON-CALL","🟢 WORKING")))))) -> 🟢 WORKING | G11: =IF(D11="SICK","⚡ FIND COVER — check Available list below",IF(D11="AVL","Ready to deploy if gap arises",IF(OR(D11="AG-E",D11="AG-L",D11="AG-N"),"Confirm agency arrival. Handover pack ready?","")))
A12: =ROSTER!A8 -> Emma Brown | B12: =ROSTER!B8 -> Day A | C12: =ROSTER!D8 -> 1.5 | D12: =IF(OR($B$3<1,$B$3>28),"—",INDEX(ROSTER!E8:AF8,1,$B$3)) -> EL | E12: =IF(D12="SICK","🔴 SICK",IF(D12="AL","🟡 AL",IF(D12="OFF","⬜ OFF",IF(D12="AVL","🔵 FLOAT",IF(OR(D12="AG-E",D12="AG-L",D12="AG-N"),"🟠 AGENCY",IF(OR(D12="OC-E",D12="OC-L",D12="OC-EL",D12="OC-N"),"🟣 ON-CALL","🟢 WORKING")))))) -> 🟢 WORKING | G12: =IF(D12="SICK","⚡ FIND COVER — check Available list below",IF(D12="AVL","Ready to deploy if gap arises",IF(OR(D12="AG-E",D12="AG-L",D12="AG-N"),"Confirm agency arrival. Handover pack ready?","")))
A13: =ROSTER!A9 -> Fiona Hart | B13: =ROSTER!B9 -> Day A | C13: =ROSTER!D9 -> 0.5 | D13: =IF(OR($B$3<1,$B$3>28),"—",INDEX(ROSTER!E9:AF9,1,$B$3)) -> EL | E13: =IF(D13="SICK","🔴 SICK",IF(D13="AL","🟡 AL",IF(D13="OFF","⬜ OFF",IF(D13="AVL","🔵 FLOAT",IF(OR(D13="AG-E",D13="AG-L",D13="AG-N"),"🟠 AGENCY",IF(OR(D13="OC-E",D13="OC-L",D13="OC-EL",D13="OC-N"),"🟣 ON-CALL","🟢 WORKING")))))) -> 🟢 WORKING | G13: =IF(D13="SICK","⚡ FIND COVER — check Available list below",IF(D13="AVL","Ready to deploy if gap arises",IF(OR(D13="AG-E",D13="AG-L",D13="AG-N"),"Confirm agency arrival. Handover pack ready?","")))
A14: =ROSTER!A10 -> George King | B14: =ROSTER!B10 -> Day A | C14: =ROSTER!D10 -> 1 | D14: =IF(OR($B$3<1,$B$3>28),"—",INDEX(ROSTER!E10:AF10,1,$B$3)) -> EL | E14: =IF(D14="SICK","🔴 SICK",IF(D14="AL","🟡 AL",IF(D14="OFF","⬜ OFF",IF(D14="AVL","🔵 FLOAT",IF(OR(D14="AG-E",D14="AG-L",D14="AG-N"),"🟠 AGENCY",IF(OR(D14="OC-E",D14="OC-L",D14="OC-EL",D14="OC-N"),"🟣 ON-CALL","🟢 WORKING")))))) -> 🟢 WORKING | G14: =IF(D14="SICK","⚡ FIND COVER — check Available list below",IF(D14="AVL","Ready to deploy if gap arises",IF(OR(D14="AG-E",D14="AG-L",D14="AG-N"),"Confirm agency arrival. Handover pack ready?","")))
A15: =ROSTER!A11 -> Hannah Lee | B15: =ROSTER!B11 -> Day B | C15: =ROSTER!D11 -> 1 | D15: =IF(OR($B$3<1,$B$3>28),"—",INDEX(ROSTER!E11:AF11,1,$B$3)) -> OFF | E15: =IF(D15="SICK","🔴 SICK",IF(D15="AL","🟡 AL",IF(D15="OFF","⬜ OFF",IF(D15="AVL","🔵 FLOAT",IF(OR(D15="AG-E",D15="AG-L",D15="AG-N"),"🟠 AGENCY",IF(OR(D15="OC-E",D15="OC-L",D15="OC-EL",D15="OC-N"),"🟣 ON-CALL","🟢 WORKING")))))) -> ⬜ OFF | G15: =IF(D15="SICK","⚡ FIND COVER — check Available list below",IF(D15="AVL","Ready to deploy if gap arises",IF(OR(D15="AG-E",D15="AG-L",D15="AG-N"),"Confirm agency arrival. Handover pack ready?","")))
A16: =ROSTER!A12 -> Ian Clark | B16: =ROSTER!B12 -> Day B | C16: =ROSTER!D12 -> 0.5 | D16: =IF(OR($B$3<1,$B$3>28),"—",INDEX(ROSTER!E12:AF12,1,$B$3)) -> OFF | E16: =IF(D16="SICK","🔴 SICK",IF(D16="AL","🟡 AL",IF(D16="OFF","⬜ OFF",IF(D16="AVL","🔵 FLOAT",IF(OR(D16="AG-E",D16="AG-L",D16="AG-N"),"🟠 AGENCY",IF(OR(D16="OC-E",D16="OC-L",D16="OC-EL",D16="OC-N"),"🟣 ON-CALL","🟢 WORKING")))))) -> ⬜ OFF | G16: =IF(D16="SICK","⚡ FIND COVER — check Available list below",IF(D16="AVL","Ready to deploy if gap arises",IF(OR(D16="AG-E",D16="AG-L",D16="AG-N"),"Confirm agency arrival. Handover pack ready?","")))
A17: =ROSTER!A13 -> Julia Martin | B17: =ROSTER!B13 -> Day B | C17: =ROSTER!D13 -> 1 | D17: =IF(OR($B$3<1,$B$3>28),"—",INDEX(ROSTER!E13:AF13,1,$B$3)) -> OFF | E17: =IF(D17="SICK","🔴 SICK",IF(D17="AL","🟡 AL",IF(D17="OFF","⬜ OFF",IF(D17="AVL","🔵 FLOAT",IF(OR(D17="AG-E",D17="AG-L",D17="AG-N"),"🟠 AGENCY",IF(OR(D17="OC-E",D17="OC-L",D17="OC-EL",D17="OC-N"),"🟣 ON-CALL","🟢 WORKING")))))) -> ⬜ OFF | G17: =IF(D17="SICK","⚡ FIND COVER — check Available list below",IF(D17="AVL","Ready to deploy if gap arises",IF(OR(D17="AG-E",D17="AG-L",D17="AG-N"),"Confirm agency arrival. Handover pack ready?","")))
A18: =ROSTER!A14 -> Kevin White | B18: =ROSTER!B14 -> Day B | C18: =ROSTER!D14 -> 0.5 | D18: =IF(OR($B$3<1,$B$3>28),"—",INDEX(ROSTER!E14:AF14,1,$B$3)) -> OFF | E18: =IF(D18="SICK","🔴 SICK",IF(D18="AL","🟡 AL",IF(D18="OFF","⬜ OFF",IF(D18="AVL","🔵 FLOAT",IF(OR(D18="AG-E",D18="AG-L",D18="AG-N"),"🟠 AGENCY",IF(OR(D18="OC-E",D18="OC-L",D18="OC-EL",D18="OC-N"),"🟣 ON-CALL","🟢 WORKING")))))) -> ⬜ OFF | G18: =IF(D18="SICK","⚡ FIND COVER — check Available list below",IF(D18="AVL","Ready to deploy if gap arises",IF(OR(D18="AG-E",D18="AG-L",D18="AG-N"),"Confirm agency arrival. Handover pack ready?","")))
A19: =ROSTER!A15 -> Laura Adams | B19: =ROSTER!B15 -> Day B | C19: =ROSTER!D15 -> 1.5 | D19: =IF(OR($B$3<1,$B$3>28),"—",INDEX(ROSTER!E15:AF15,1,$B$3)) -> OFF | E19: =IF(D19="SICK","🔴 SICK",IF(D19="AL","🟡 AL",IF(D19="OFF","⬜ OFF",IF(D19="AVL","🔵 FLOAT",IF(OR(D19="AG-E",D19="AG-L",D19="AG-N"),"🟠 AGENCY",IF(OR(D19="OC-E",D19="OC-L",D19="OC-EL",D19="OC-N"),"🟣 ON-CALL","🟢 WORKING")))))) -> ⬜ OFF | G19: =IF(D19="SICK","⚡ FIND COVER — check Available list below",IF(D19="AVL","Ready to deploy if gap arises",IF(OR(D19="AG-E",D19="AG-L",D19="AG-N"),"Confirm agency arrival. Handover pack ready?","")))
... A32: =ROSTER!A28 -> Yasmin Reed | B32: =ROSTER!B28 -> Day B | C32: =ROSTER!D28 -> 1 | D32: =IF(OR($B$3<1,$B$3>28),"—",INDEX(ROSTER!E28:AF28,1,$B$3)) -> OFF | E32: =IF(D32="SICK","🔴 SICK",IF(D32="AL","🟡 AL",IF(D32="OFF","⬜ OFF",IF(D32="AVL","🔵 FLOAT",IF(OR(D32="AG-E",D32="AG-L",D32="AG-N"),"🟠 AGENCY",IF(OR(D32="OC-E",D32="OC-L",D32="OC-EL",D32="OC-N"),"🟣 ON-CALL","🟢 WORKING")))))) -> ⬜ OFF | G32: =IF(D32="SICK","⚡ FIND COVER — check Available list below",IF(D32="AVL","Ready to deploy if gap arises",IF(OR(D32="AG-E",D32="AG-L",D32="AG-N"),"Confirm agency arrival. Handover pack ready?","")))
A33: =ROSTER!A29 -> 0 | C33: =ROSTER!D29 -> 0 | D33: =IF(OR($B$3<1,$B$3>28),"—",INDEX(ROSTER!E29:AF29,1,$B$3)) -> 0
A34: =ROSTER!A30 -> 0 | C34: =ROSTER!D30 -> 0 | D34: =IF(OR($B$3<1,$B$3>28),"—",INDEX(ROSTER!E30:AF30,1,$B$3)) -> 0
A35: =ROSTER!A31 -> 0 | C35: =ROSTER!D31 -> 0 | D35: =IF(OR($B$3<1,$B$3>28),"—",INDEX(ROSTER!E31:AF31,1,$B$3)) -> 0
A36: =ROSTER!A32 -> 0 | C36: =ROSTER!D32 -> 0 | D36: =IF(OR($B$3<1,$B$3>28),"—",INDEX(ROSTER!E32:AF32,1,$B$3)) -> 0
A37: =ROSTER!A33 -> 0 | C37: =ROSTER!D33 -> 0 | D37: =IF(OR($B$3<1,$B$3>28),"—",INDEX(ROSTER!E33:AF33,1,$B$3)) -> 0
A38: =ROSTER!A34 -> 0 | C38: =ROSTER!D34 -> 0 | D38: =IF(OR($B$3<1,$B$3>28),"—",INDEX(ROSTER!E34:AF34,1,$B$3)) -> 0
A39: =ROSTER!A35 -> 0 | C39: =ROSTER!D35 -> 0 | D39: =IF(OR($B$3<1,$B$3>28),"—",INDEX(ROSTER!E35:AF35,1,$B$3)) -> 0
A40: =ROSTER!A36 -> 0 | C40: =ROSTER!D36 -> 0 | D40: =IF(OR($B$3<1,$B$3>28),"—",INDEX(ROSTER!E36:AF36,1,$B$3)) -> 0
A41: =ROSTER!A37 -> 0 | C41: =ROSTER!D37 -> 0 | D41: =IF(OR($B$3<1,$B$3>28),"—",INDEX(ROSTER!E37:AF37,1,$B$3)) -> 0
A42: =ROSTER!A38 -> 0 | C42: =ROSTER!D38 -> 0 | D42: =IF(OR($B$3<1,$B$3>28),"—",INDEX(ROSTER!E38:AF38,1,$B$3)) -> 0
A43: =ROSTER!A39 -> 0 | C43: =ROSTER!D39 -> 0 | D43: =IF(OR($B$3<1,$B$3>28),"—",INDEX(ROSTER!E39:AF39,1,$B$3)) -> 0
A44: =ROSTER!A40 -> 0 | C44: =ROSTER!D40 -> 0 | D44: =IF(OR($B$3<1,$B$3>28),"—",INDEX(ROSTER!E40:AF40,1,$B$3)) -> 0
... A54: =ROSTER!A50 -> 0 | C54: =ROSTER!D50 -> 0 | D54: =IF(OR($B$3<1,$B$3>28),"—",INDEX(ROSTER!E50:AF50,1,$B$3)) -> 0
A57: COVERAGE
A58: Metric | B58: Count | C58: Min | D58: Status
A59: Early | B59: =COUNTIF(D8:D54,"EL")+COUNTIF(D8:D54,"E")+COUNTIF(D8:D54,"OC-E")+COUNTIF(D8:D54,"OC-EL")+COUNTIF(D8:D54,"AG-E")+COUNTIF(D8:D54,"BH-D") -> 8 | C59: 3 | D59: =IF(B59>=C59+3,"🟢 STRONG",IF(B59>=C59+1,"🟡 OK",IF(B59>=C59,"🟠 AT MIN","🔴 BELOW MIN"))) -> 🟢 STRONG
A60: Late | B60: =COUNTIF(D8:D54,"EL")+COUNTIF(D8:D54,"L")+COUNTIF(D8:D54,"OC-L")+COUNTIF(D8:D54,"OC-EL")+COUNTIF(D8:D54,"AG-L")+COUNTIF(D8:D54,"BH-D") -> 7 | C60: 3 | D60: =IF(B60>=C60+3,"🟢 STRONG",IF(B60>=C60+1,"🟡 OK",IF(B60>=C60,"🟠 AT MIN","🔴 BELOW MIN"))) -> 🟢 STRONG
A61: Night | B61: =COUNTIF(D8:D54,"N")+COUNTIF(D8:D54,"OC-N")+COUNTIF(D8:D54,"AG-N")+COUNTIF(D8:D54,"BH-N") -> 3 | C61: 3 | D61: =IF(B61>=C61+3,"🟢 STRONG",IF(B61>=C61+1,"🟡 OK",IF(B61>=C61,"🟠 AT MIN","🔴 BELOW MIN"))) -> 🟠 AT MIN
A62: Sick | B62: =COUNTIF(D8:D54,"SICK") -> 0
A63: AL | B63: =COUNTIF(D8:D54,"AL") -> 0
A64: Float Avail | B64: =COUNTIF(D8:D54,"AVL") -> 3
A65: Agency | B65: =COUNTIF(D8:D54,"AG-E")+COUNTIF(D8:D54,"AG-L")+COUNTIF(D8:D54,"AG-N") -> 0
A66: Off Duty | B66: =COUNTIF(D8:D54,"OFF") -> 11
A68: ESCALATION
A69: Current Level | B69: =IF(OR(B59<3,B61<3),"⚫ LVL5 — UNSAFE",IF(B65>0,"🟠 LVL3 — Agency",IF(AND(B64=0,B62>0),"🟡 LVL2 — Floats gone",IF(B62>0,"🟢 LVL1 — Float deployed","⬜ LVL0 — Normal")))) -> ⬜ LVL0 — Normal
A71: SWAP VALIDATOR
A72: Enter roster row numbers (4-50) for both staff + day number
A73: Staff A Row | B73: 4 | C73: =IF(OR(B73<4,B73>50,B74<4,B74>50),"—",INDEX(ROSTER!A$4:A$50,B73-3)) -> Alice Johnson
A74: Staff B Row | B74: 11 | C74: =IF(OR(B73<4,B73>50,B74<4,B74>50),"—",INDEX(ROSTER!A$4:A$50,B74-3)) -> Hannah Lee
A75: Swap Day | B75: 3
A77: A current | B77: =IF(OR(B73<4,B73>50,B74<4,B74>50),"—",INDEX(ROSTER!E$4:AF$50,B73-3,B75)) -> OFF
A78: B current | B78: =IF(OR(B73<4,B73>50,B74<4,B74>50),"—",INDEX(ROSTER!E$4:AF$50,B74-3,B75)) -> EL
A79: Skill A | B79: =IF(OR(B73<4,B73>50,B74<4,B74>50),"—",INDEX(ROSTER!D$4:D$50,B73-3)) -> 1
A80: Skill B | B80: =IF(OR(B73<4,B73>50,B74<4,B74>50),"—",INDEX(ROSTER!D$4:D$50,B74-3)) -> 1
A81: Skill safe? | B81: =IF(B79="—","—",IF(B79=B80,"✅ Equal",IF(B79>B80,"⚠️ Drops "&TEXT(B79-B80,"0.0"),"✅ Improves"))) -> ✅ Equal
A82: A fatigue count | B82: =IF(OR(B73<4,B73>50,B74<4,B74>50),"—",INDEX(FATIGUE_TRACKER!E$4:AF$50,B73-3,B75)) -> 1
A83: Fatigue safe? | B83: =IF(B82="—","—",IF(B82>=CONFIG!$B$33-1,"🔴 BLOCKS — at limit",IF(B82>=CONFIG!$B$33-2,"🟡 Close to limit","✅ OK"))) -> ✅ OK
A84: A weekly hrs | B84: =IF(OR(B73<4,B73>50,B74<4,B74>50),"—",INDEX(ROSTER!AP$4:AP$50,B73-3)) -> 42.875
A85: WTR after swap? | B85: =IF(B84="—","—",IF(B84+12.25>48,"🔴 BREACH 48hr","✅ OK ("&TEXT(B84+12.25,"0.0")&"hrs)")) -> 🔴 BREACH 48hr
A87: VERDICT | B87: =IF(B73=B74,"⚠️ SAME PERSON — not a swap",IF(OR(B73<4,B73>50,B74<4,B74>50),"🔴 INVALID ROW — use 4-50",IF(OR(ISNUMBER(SEARCH("🔴",B83)),ISNUMBER(SEARCH("🔴",B85))),"🔴 REJECT — breach detected",IF(ISNUMBER(SEARCH("⚠️",B81)),"🟡 APPROVE WITH CAUTION — skill drops","🟢 APPROVE — swap is safe")))) -> 🔴 REJECT — breach detected
A90: AVAILABLE COVER
A91: Staff who are AVL (float) or OFF (OT candidates) today
A92: Name | B92: Team | C92: Current | D92: Type | E92: Skill | F92: Fatigue
A93: =IF(OR(D8="AVL",D8="OFF"),ROSTER!A4,"") | B93: =IF(A93<>"",ROSTER!B4,"") | C93: =IF(A93<>"",D8,"") | D93: =IF(A93="","",IF(D8="AVL","🔵 FLOAT",IF(OR($B$3<1,$B$3>28),"—",IF(INDEX(FATIGUE_TRACKER!E$4:AF$50,1,$B$3)>=CONFIG!$B$33-1,"⛔ FATIGUED",IF(INDEX(FATIGUE_TRACKER!E$4:AF$50,1,$B$3)>=CONFIG!$B$33-2,"🟡 OT (tired)","🟣 OT"))))) | E93: =IF(A93<>"",ROSTER!D4,"") | F93: =IF(A93="","",IF(OR($B$3<1,$B$3>28),"—",INDEX(FATIGUE_TRACKER!E$4:AF$50,1,$B$3)))
A94: =IF(OR(D9="AVL",D9="OFF"),ROSTER!A5,"") | B94: =IF(A94<>"",ROSTER!B5,"") | C94: =IF(A94<>"",D9,"") | D94: =IF(A94="","",IF(D9="AVL","🔵 FLOAT",IF(OR($B$3<1,$B$3>28),"—",IF(INDEX(FATIGUE_TRACKER!E$4:AF$50,2,$B$3)>=CONFIG!$B$33-1,"⛔ FATIGUED",IF(INDEX(FATIGUE_TRACKER!E$4:AF$50,2,$B$3)>=CONFIG!$B$33-2,"🟡 OT (tired)","🟣 OT"))))) | E94: =IF(A94<>"",ROSTER!D5,"") | F94: =IF(A94="","",IF(OR($B$3<1,$B$3>28),"—",INDEX(FATIGUE_TRACKER!E$4:AF$50,2,$B$3)))
A95: =IF(OR(D10="AVL",D10="OFF"),ROSTER!A6,"") | B95: =IF(A95<>"",ROSTER!B6,"") | C95: =IF(A95<>"",D10,"") | D95: =IF(A95="","",IF(D10="AVL","🔵 FLOAT",IF(OR($B$3<1,$B$3>28),"—",IF(INDEX(FATIGUE_TRACKER!E$4:AF$50,3,$B$3)>=CONFIG!$B$33-1,"⛔ FATIGUED",IF(INDEX(FATIGUE_TRACKER!E$4:AF$50,3,$B$3)>=CONFIG!$B$33-2,"🟡 OT (tired)","🟣 OT"))))) | E95: =IF(A95<>"",ROSTER!D6,"") | F95: =IF(A95="","",IF(OR($B$3<1,$B$3>28),"—",INDEX(FATIGUE_TRACKER!E$4:AF$50,3,$B$3)))
A96: =IF(OR(D11="AVL",D11="OFF"),ROSTER!A7,"") | B96: =IF(A96<>"",ROSTER!B7,"") | C96: =IF(A96<>"",D11,"") | D96: =IF(A96="","",IF(D11="AVL","🔵 FLOAT",IF(OR($B$3<1,$B$3>28),"—",IF(INDEX(FATIGUE_TRACKER!E$4:AF$50,4,$B$3)>=CONFIG!$B$33-1,"⛔ FATIGUED",IF(INDEX(FATIGUE_TRACKER!E$4:AF$50,4,$B$3)>=CONFIG!$B$33-2,"🟡 OT (tired)","🟣 OT"))))) | E96: =IF(A96<>"",ROSTER!D7,"") | F96: =IF(A96="","",IF(OR($B$3<1,$B$3>28),"—",INDEX(FATIGUE_TRACKER!E$4:AF$50,4,$B$3)))
A97: =IF(OR(D12="AVL",D12="OFF"),ROSTER!A8,"") | B97: =IF(A97<>"",ROSTER!B8,"") | C97: =IF(A97<>"",D12,"") | D97: =IF(A97="","",IF(D12="AVL","🔵 FLOAT",IF(OR($B$3<1,$B$3>28),"—",IF(INDEX(FATIGUE_TRACKER!E$4:AF$50,5,$B$3)>=CONFIG!$B$33-1,"⛔ FATIGUED",IF(INDEX(FATIGUE_TRACKER!E$4:AF$50,5,$B$3)>=CONFIG!$B$33-2,"🟡 OT (tired)","🟣 OT"))))) | E97: =IF(A97<>"",ROSTER!D8,"") | F97: =IF(A97="","",IF(OR($B$3<1,$B$3>28),"—",INDEX(FATIGUE_TRACKER!E$4:AF$50,5,$B$3)))
A98: =IF(OR(D13="AVL",D13="OFF"),ROSTER!A9,"") | B98: =IF(A98<>"",ROSTER!B9,"") | C98: =IF(A98<>"",D13,"") | D98: =IF(A98="","",IF(D13="AVL","🔵 FLOAT",IF(OR($B$3<1,$B$3>28),"—",IF(INDEX(FATIGUE_TRACKER!E$4:AF$50,6,$B$3)>=CONFIG!$B$33-1,"⛔ FATIGUED",IF(INDEX(FATIGUE_TRACKER!E$4:AF$50,6,$B$3)>=CONFIG!$B$33-2,"🟡 OT (tired)","🟣 OT"))))) | E98: =IF(A98<>"",ROSTER!D9,"") | F98: =IF(A98="","",IF(OR($B$3<1,$B$3>28),"—",INDEX(FATIGUE_TRACKER!E$4:AF$50,6,$B$3)))
A99: =IF(OR(D14="AVL",D14="OFF"),ROSTER!A10,"") | B99: =IF(A99<>"",ROSTER!B10,"") | C99: =IF(A99<>"",D14,"") | D99: =IF(A99="","",IF(D14="AVL","🔵 FLOAT",IF(OR($B$3<1,$B$3>28),"—",IF(INDEX(FATIGUE_TRACKER!E$4:AF$50,7,$B$3)>=CONFIG!$B$33-1,"⛔ FATIGUED",IF(INDEX(FATIGUE_TRACKER!E$4:AF$50,7,$B$3)>=CONFIG!$B$33-2,"🟡 OT (tired)","🟣 OT"))))) | E99: =IF(A99<>"",ROSTER!D10,"") | F99: =IF(A99="","",IF(OR($B$3<1,$B$3>28),"—",INDEX(FATIGUE_TRACKER!E$4:AF$50,7,$B$3)))
A100: =IF(OR(D15="AVL",D15="OFF"),ROSTER!A11,"") -> Hannah Lee | B100: =IF(A100<>"",ROSTER!B11,"") -> Day B | C100: =IF(A100<>"",D15,"") -> OFF | D100: =IF(A100="","",IF(D15="AVL","🔵 FLOAT",IF(OR($B$3<1,$B$3>28),"—",IF(INDEX(FATIGUE_TRACKER!E$4:AF$50,8,$B$3)>=CONFIG!$B$33-1,"⛔ FATIGUED",IF(INDEX(FATIGUE_TRACKER!E$4:AF$50,8,$B$3)>=CONFIG!$B$33-2,"🟡 OT (tired)","🟣 OT"))))) -> 🟣 OT | E100: =IF(A100<>"",ROSTER!D11,"") -> 1 | F100: =IF(A100="","",IF(OR($B$3<1,$B$3>28),"—",INDEX(FATIGUE_TRACKER!E$4:AF$50,8,$B$3))) -> 1
A101: =IF(OR(D16="AVL",D16="OFF"),ROSTER!A12,"") -> Ian Clark | B101: =IF(A101<>"",ROSTER!B12,"") -> Day B | C101: =IF(A101<>"",D16,"") -> OFF | D101: =IF(A101="","",IF(D16="AVL","🔵 FLOAT",IF(OR($B$3<1,$B$3>28),"—",IF(INDEX(FATIGUE_TRACKER!E$4:AF$50,9,$B$3)>=CONFIG!$B$33-1,"⛔ FATIGUED",IF(INDEX(FATIGUE_TRACKER!E$4:AF$50,9,$B$3)>=CONFIG!$B$33-2,"🟡 OT (tired)","🟣 OT"))))) -> 🟣 OT | E101: =IF(A101<>"",ROSTER!D12,"") -> 0.5 | F101: =IF(A101="","",IF(OR($B$3<1,$B$3>28),"—",INDEX(FATIGUE_TRACKER!E$4:AF$50,9,$B$3))) -> 1
A102: =IF(OR(D17="AVL",D17="OFF"),ROSTER!A13,"") -> Julia Martin | B102: =IF(A102<>"",ROSTER!B13,"") -> Day B | C102: =IF(A102<>"",D17,"") -> OFF | D102: =IF(A102="","",IF(D17="AVL","🔵 FLOAT",IF(OR($B$3<1,$B$3>28),"—",IF(INDEX(FATIGUE_TRACKER!E$4:AF$50,10,$B$3)>=CONFIG!$B$33-1,"⛔ FATIGUED",IF(INDEX(FATIGUE_TRACKER!E$4:AF$50,10,$B$3)>=CONFIG!$B$33-2,"🟡 OT (tired)","🟣 OT"))))) -> 🟣 OT | E102: =IF(A102<>"",ROSTER!D13,"") -> 1 | F102: =IF(A102="","",IF(OR($B$3<1,$B$3>28),"—",INDEX(FATIGUE_TRACKER!E$4:AF$50,10,$B$3))) -> 1
A103: =IF(OR(D18="AVL",D18="OFF"),ROSTER!A14,"") -> Kevin White | B103: =IF(A103<>"",ROSTER!B14,"") -> Day B | C103: =IF(A103<>"",D18,"") -> OFF | D103: =IF(A103="","",IF(D18="AVL","🔵 FLOAT",IF(OR($B$3<1,$B$3>28),"—",IF(INDEX(FATIGUE_TRACKER!E$4:AF$50,11,$B$3)>=CONFIG!$B$33-1,"⛔ FATIGUED",IF(INDEX(FATIGUE_TRACKER!E$4:AF$50,11,$B$3)>=CONFIG!$B$33-2,"🟡 OT (tired)","🟣 OT"))))) -> 🟣 OT | E103: =IF(A103<>"",ROSTER!D14,"") -> 0.5 | F103: =IF(A103="","",IF(OR($B$3<1,$B$3>28),"—",INDEX(FATIGUE_TRACKER!E$4:AF$50,11,$B$3))) -> 1
A104: =IF(OR(D19="AVL",D19="OFF"),ROSTER!A15,"") -> Laura Adams | B104: =IF(A104<>"",ROSTER!B15,"") -> Day B | C104: =IF(A104<>"",D19,"") -> OFF | D104: =IF(A104="","",IF(D19="AVL","🔵 FLOAT",IF(OR($B$3<1,$B$3>28),"—",IF(INDEX(FATIGUE_TRACKER!E$4:AF$50,12,$B$3)>=CONFIG!$B$33-1,"⛔ FATIGUED",IF(INDEX(FATIGUE_TRACKER!E$4:AF$50,12,$B$3)>=CONFIG!$B$33-2,"🟡 OT (tired)","🟣 OT"))))) -> 🟣 OT | E104: =IF(A104<>"",ROSTER!D15,"") -> 1.5 | F104: =IF(A104="","",IF(OR($B$3<1,$B$3>28),"—",INDEX(FATIGUE_TRACKER!E$4:AF$50,12,$B$3))) -> 1
A105: =IF(OR(D20="AVL",D20="OFF"),ROSTER!A16,"") -> Mike Taylor | B105: =IF(A105<>"",ROSTER!B16,"") -> Day B | C105: =IF(A105<>"",D20,"") -> OFF | D105: =IF(A105="","",IF(D20="AVL","🔵 FLOAT",IF(OR($B$3<1,$B$3>28),"—",IF(INDEX(FATIGUE_TRACKER!E$4:AF$50,13,$B$3)>=CONFIG!$B$33-1,"⛔ FATIGUED",IF(INDEX(FATIGUE_TRACKER!E$4:AF$50,13,$B$3)>=CONFIG!$B$33-2,"🟡 OT (tired)","🟣 OT"))))) -> 🟣 OT | E105: =IF(A105<>"",ROSTER!D16,"") -> 0.5 | F105: =IF(A105="","",IF(OR($B$3<1,$B$3>28),"—",INDEX(FATIGUE_TRACKER!E$4:AF$50,13,$B$3))) -> 1
A106: =IF(OR(D21="AVL",D21="OFF"),ROSTER!A17,"") -> Nina Patel | B106: =IF(A106<>"",ROSTER!B17,"") -> Day B | C106: =IF(A106<>"",D21,"") -> OFF | D106: =IF(A106="","",IF(D21="AVL","🔵 FLOAT",IF(OR($B$3<1,$B$3>28),"—",IF(INDEX(FATIGUE_TRACKER!E$4:AF$50,14,$B$3)>=CONFIG!$B$33-1,"⛔ FATIGUED",IF(INDEX(FATIGUE_TRACKER!E$4:AF$50,14,$B$3)>=CONFIG!$B$33-2,"🟡 OT (tired)","🟣 OT"))))) -> 🟣 OT | E106: =IF(A106<>"",ROSTER!D17,"") -> 1 | F106: =IF(A106="","",IF(OR($B$3<1,$B$3>28),"—",INDEX(FATIGUE_TRACKER!E$4:AF$50,14,$B$3))) -> 1
A107: =IF(OR(D22="AVL",D22="OFF"),ROSTER!A18,"") | B107: =IF(A107<>"",ROSTER!B18,"") | C107: =IF(A107<>"",D22,"") | D107: =IF(A107="","",IF(D22="AVL","🔵 FLOAT",IF(OR($B$3<1,$B$3>28),"—",IF(INDEX(FATIGUE_TRACKER!E$4:AF$50,15,$B$3)>=CONFIG!$B$33-1,"⛔ FATIGUED",IF(INDEX(FATIGUE_TRACKER!E$4:AF$50,15,$B$3)>=CONFIG!$B$33-2,"🟡 OT (tired)","🟣 OT"))))) | E107: =IF(A107<>"",ROSTER!D18,"") | F107: =IF(A107="","",IF(OR($B$3<1,$B$3>28),"—",INDEX(FATIGUE_TRACKER!E$4:AF$50,15,$B$3)))
A108: =IF(OR(D23="AVL",D23="OFF"),ROSTER!A19,"") | B108: =IF(A108<>"",ROSTER!B19,"") | C108: =IF(A108<>"",D23,"") | D108: =IF(A108="","",IF(D23="AVL","🔵 FLOAT",IF(OR($B$3<1,$B$3>28),"—",IF(INDEX(FATIGUE_TRACKER!E$4:AF$50,16,$B$3)>=CONFIG!$B$33-1,"⛔ FATIGUED",IF(INDEX(FATIGUE_TRACKER!E$4:AF$50,16,$B$3)>=CONFIG!$B$33-2,"🟡 OT (tired)","🟣 OT"))))) | E108: =IF(A108<>"",ROSTER!D19,"") | F108: =IF(A108="","",IF(OR($B$3<1,$B$3>28),"—",INDEX(FATIGUE_TRACKER!E$4:AF$50,16,$B$3)))
A109: =IF(OR(D24="AVL",D24="OFF"),ROSTER!A20,"") | B109: =IF(A109<>"",ROSTER!B20,"") | C109: =IF(A109<>"",D24,"") | D109: =IF(A109="","",IF(D24="AVL","🔵 FLOAT",IF(OR($B$3<1,$B$3>28),"—",IF(INDEX(FATIGUE_TRACKER!E$4:AF$50,17,$B$3)>=CONFIG!$B$33-1,"⛔ FATIGUED",IF(INDEX(FATIGUE_TRACKER!E$4:AF$50,17,$B$3)>=CONFIG!$B$33-2,"🟡 OT (tired)","🟣 OT"))))) | E109: =IF(A109<>"",ROSTER!D20,"") | F109: =IF(A109="","",IF(OR($B$3<1,$B$3>28),"—",INDEX(FATIGUE_TRACKER!E$4:AF$50,17,$B$3)))
A110: =IF(OR(D25="AVL",D25="OFF"),ROSTER!A21,"") -> Rachel Green | B110: =IF(A110<>"",ROSTER!B21,"") -> Night B | C110: =IF(A110<>"",D25,"") -> OFF | D110: =IF(A110="","",IF(D25="AVL","🔵 FLOAT",IF(OR($B$3<1,$B$3>28),"—",IF(INDEX(FATIGUE_TRACKER!E$4:AF$50,18,$B$3)>=CONFIG!$B$33-1,"⛔ FATIGUED",IF(INDEX(FATIGUE_TRACKER!E$4:AF$50,18,$B$3)>=CONFIG!$B$33-2,"🟡 OT (tired)","🟣 OT"))))) -> 🟣 OT | E110: =IF(A110<>"",ROSTER!D21,"") -> 1 | F110: =IF(A110="","",IF(OR($B$3<1,$B$3>28),"—",INDEX(FATIGUE_TRACKER!E$4:AF$50,18,$B$3))) -> 1
A111: =IF(OR(D26="AVL",D26="OFF"),ROSTER!A22,"") -> Steve Black | B111: =IF(A111<>"",ROSTER!B22,"") -> Night B | C111: =IF(A111<>"",D26,"") -> OFF | D111: =IF(A111="","",IF(D26="AVL","🔵 FLOAT",IF(OR($B$3<1,$B$3>28),"—",IF(INDEX(FATIGUE_TRACKER!E$4:AF$50,19,$B$3)>=CONFIG!$B$33-1,"⛔ FATIGUED",IF(INDEX(FATIGUE_TRACKER!E$4:AF$50,19,$B$3)>=CONFIG!$B$33-2,"🟡 OT (tired)","🟣 OT"))))) -> 🟣 OT | E111: =IF(A111<>"",ROSTER!D22,"") -> 0.5 | F111: =IF(A111="","",IF(OR($B$3<1,$B$3>28),"—",INDEX(FATIGUE_TRACKER!E$4:AF$50,19,$B$3))) -> 1
A112: =IF(OR(D27="AVL",D27="OFF"),ROSTER!A23,"") -> Tina Hall | B112: =IF(A112<>"",ROSTER!B23,"") -> Night B | C112: =IF(A112<>"",D27,"") -> OFF | D112: =IF(A112="","",IF(D27="AVL","🔵 FLOAT",IF(OR($B$3<1,$B$3>28),"—",IF(INDEX(FATIGUE_TRACKER!E$4:AF$50,20,$B$3)>=CONFIG!$B$33-1,"⛔ FATIGUED",IF(INDEX(FATIGUE_TRACKER!E$4:AF$50,20,$B$3)>=CONFIG!$B$33-2,"🟡 OT (tired)","🟣 OT"))))) -> 🟣 OT | E112: =IF(A112<>"",ROSTER!D23,"") -> 0.5 | F112: =IF(A112="","",IF(OR($B$3<1,$B$3>28),"—",INDEX(FATIGUE_TRACKER!E$4:AF$50,20,$B$3))) -> 1
A113: =IF(OR(D28="AVL",D28="OFF"),ROSTER!A24,"") -> Uma Shah | B113: =IF(A113<>"",ROSTER!B24,"") -> Float | C113: =IF(A113<>"",D28,"") -> AVL | D113: =IF(A113="","",IF(D28="AVL","🔵 FLOAT",IF(OR($B$3<1,$B$3>28),"—",IF(INDEX(FATIGUE_TRACKER!E$4:AF$50,21,$B$3)>=CONFIG!$B$33-1,"⛔ FATIGUED",IF(INDEX(FATIGUE_TRACKER!E$4:AF$50,21,$B$3)>=CONFIG!$B$33-2,"🟡 OT (tired)","🟣 OT"))))) -> 🔵 FLOAT | E113: =IF(A113<>"",ROSTER!D24,"") -> 1 | F113: =IF(A113="","",IF(OR($B$3<1,$B$3>28),"—",INDEX(FATIGUE_TRACKER!E$4:AF$50,21,$B$3))) -> 0
A114: =IF(OR(D29="AVL",D29="OFF"),ROSTER!A25,"") -> Victor Chen | B114: =IF(A114<>"",ROSTER!B25,"") -> Float | C114: =IF(A114<>"",D29,"") -> AVL | D114: =IF(A114="","",IF(D29="AVL","🔵 FLOAT",IF(OR($B$3<1,$B$3>28),"—",IF(INDEX(FATIGUE_TRACKER!E$4:AF$50,22,$B$3)>=CONFIG!$B$33-1,"⛔ FATIGUED",IF(INDEX(FATIGUE_TRACKER!E$4:AF$50,22,$B$3)>=CONFIG!$B$33-2,"🟡 OT (tired)","🟣 OT"))))) -> 🔵 FLOAT | E114: =IF(A114<>"",ROSTER!D25,"") -> 0.5 | F114: =IF(A114="","",IF(OR($B$3<1,$B$3>28),"—",INDEX(FATIGUE_TRACKER!E$4:AF$50,22,$B$3))) -> 0
A115: =IF(OR(D30="AVL",D30="OFF"),ROSTER!A26,"") -> Wendy Jones | B115: =IF(A115<>"",ROSTER!B26,"") -> Float | C115: =IF(A115<>"",D30,"") -> AVL | D115: =IF(A115="","",IF(D30="AVL","🔵 FLOAT",IF(OR($B$3<1,$B$3>28),"—",IF(INDEX(FATIGUE_TRACKER!E$4:AF$50,23,$B$3)>=CONFIG!$B$33-1,"⛔ FATIGUED",IF(INDEX(FATIGUE_TRACKER!E$4:AF$50,23,$B$3)>=CONFIG!$B$33-2,"🟡 OT (tired)","🟣 OT"))))) -> 🔵 FLOAT | E115: =IF(A115<>"",ROSTER!D26,"") -> 0.5 | F115: =IF(A115="","",IF(OR($B$3<1,$B$3>28),"—",INDEX(FATIGUE_TRACKER!E$4:AF$50,23,$B$3))) -> 0
A116: =IF(OR(D31="AVL",D31="OFF"),ROSTER!A27,"") | B116: =IF(A116<>"",ROSTER!B27,"") | C116: =IF(A116<>"",D31,"") | D116: =IF(A116="","",IF(D31="AVL","🔵 FLOAT",IF(OR($B$3<1,$B$3>28),"—",IF(INDEX(FATIGUE_TRACKER!E$4:AF$50,24,$B$3)>=CONFIG!$B$33-1,"⛔ FATIGUED",IF(INDEX(FATIGUE_TRACKER!E$4:AF$50,24,$B$3)>=CONFIG!$B$33-2,"🟡 OT (tired)","🟣 OT"))))) | E116: =IF(A116<>"",ROSTER!D27,"") | F116: =IF(A116="","",IF(OR($B$3<1,$B$3>28),"—",INDEX(FATIGUE_TRACKER!E$4:AF$50,24,$B$3)))
A117: =IF(OR(D32="AVL",D32="OFF"),ROSTER!A28,"") -> Yasmin Reed | B117: =IF(A117<>"",ROSTER!B28,"") -> Day B | C117: =IF(A117<>"",D32,"") -> OFF | D117: =IF(A117="","",IF(D32="AVL","🔵 FLOAT",IF(OR($B$3<1,$B$3>28),"—",IF(INDEX(FATIGUE_TRACKER!E$4:AF$50,25,$B$3)>=CONFIG!$B$33-1,"⛔ FATIGUED",IF(INDEX(FATIGUE_TRACKER!E$4:AF$50,25,$B$3)>=CONFIG!$B$33-2,"🟡 OT (tired)","🟣 OT"))))) -> 🟣 OT | E117: =IF(A117<>"",ROSTER!D28,"") -> 1 | F117: =IF(A117="","",IF(OR($B$3<1,$B$3>28),"—",INDEX(FATIGUE_TRACKER!E$4:AF$50,25,$B$3))) -> 1
A118: =IF(OR(D33="AVL",D33="OFF"),ROSTER!A29,"") | B118: =IF(A118<>"",ROSTER!B29,"") | C118: =IF(A118<>"",D33,"") | D118: =IF(A118="","",IF(D33="AVL","🔵 FLOAT",IF(OR($B$3<1,$B$3>28),"—",IF(INDEX(FATIGUE_TRACKER!E$4:AF$50,26,$B$3)>=CONFIG!$B$33-1,"⛔ FATIGUED",IF(INDEX(FATIGUE_TRACKER!E$4:AF$50,26,$B$3)>=CONFIG!$B$33-2,"🟡 OT (tired)","🟣 OT"))))) | E118: =IF(A118<>"",ROSTER!D29,"") | F118: =IF(A118="","",IF(OR($B$3<1,$B$3>28),"—",INDEX(FATIGUE_TRACKER!E$4:AF$50,26,$B$3)))
A119: =IF(OR(D34="AVL",D34="OFF"),ROSTER!A30,"") | B119: =IF(A119<>"",ROSTER!B30,"") | C119: =IF(A119<>"",D34,"") | D119: =IF(A119="","",IF(D34="AVL","🔵 FLOAT",IF(OR($B$3<1,$B$3>28),"—",IF(INDEX(FATIGUE_TRACKER!E$4:AF$50,27,$B$3)>=CONFIG!$B$33-1,"⛔ FATIGUED",IF(INDEX(FATIGUE_TRACKER!E$4:AF$50,27,$B$3)>=CONFIG!$B$33-2,"🟡 OT (tired)","🟣 OT"))))) | E119: =IF(A119<>"",ROSTER!D30,"") | F119: =IF(A119="","",IF(OR($B$3<1,$B$3>28),"—",INDEX(FATIGUE_TRACKER!E$4:AF$50,27,$B$3)))
A120: =IF(OR(D35="AVL",D35="OFF"),ROSTER!A31,"") | B120: =IF(A120<>"",ROSTER!B31,"") | C120: =IF(A120<>"",D35,"") | D120: =IF(A120="","",IF(D35="AVL","🔵 FLOAT",IF(OR($B$3<1,$B$3>28),"—",IF(INDEX(FATIGUE_TRACKER!E$4:AF$50,28,$B$3)>=CONFIG!$B$33-1,"⛔ FATIGUED",IF(INDEX(FATIGUE_TRACKER!E$4:AF$50,28,$B$3)>=CONFIG!$B$33-2,"🟡 OT (tired)","🟣 OT"))))) | E120: =IF(A120<>"",ROSTER!D31,"") | F120: =IF(A120="","",IF(OR($B$3<1,$B$3>28),"—",INDEX(FATIGUE_TRACKER!E$4:AF$50,28,$B$3)))
A121: =IF(OR(D36="AVL",D36="OFF"),ROSTER!A32,"") | B121: =IF(A121<>"",ROSTER!B32,"") | C121: =IF(A121<>"",D36,"") | D121: =IF(A121="","",IF(D36="AVL","🔵 FLOAT",IF(OR($B$3<1,$B$3>28),"—",IF(INDEX(FATIGUE_TRACKER!E$4:AF$50,29,$B$3)>=CONFIG!$B$33-1,"⛔ FATIGUED",IF(INDEX(FATIGUE_TRACKER!E$4:AF$50,29,$B$3)>=CONFIG!$B$33-2,"🟡 OT (tired)","🟣 OT"))))) | E121: =IF(A121<>"",ROSTER!D32,"") | F121: =IF(A121="","",IF(OR($B$3<1,$B$3>28),"—",INDEX(FATIGUE_TRACKER!E$4:AF$50,29,$B$3)))
A122: =IF(OR(D37="AVL",D37="OFF"),ROSTER!A33,"") | B122: =IF(A122<>"",ROSTER!B33,"") | C122: =IF(A122<>"",D37,"") | D122: =IF(A122="","",IF(D37="AVL","🔵 FLOAT",IF(OR($B$3<1,$B$3>28),"—",IF(INDEX(FATIGUE_TRACKER!E$4:AF$50,30,$B$3)>=CONFIG!$B$33-1,"⛔ FATIGUED",IF(INDEX(FATIGUE_TRACKER!E$4:AF$50,30,$B$3)>=CONFIG!$B$33-2,"🟡 OT (tired)","🟣 OT"))))) | E122: =IF(A122<>"",ROSTER!D33,"") | F122: =IF(A122="","",IF(OR($B$3<1,$B$3>28),"—",INDEX(FATIGUE_TRACKER!E$4:AF$50,30,$B$3)))
A123: =IF(OR(D38="AVL",D38="OFF"),ROSTER!A34,"") | B123: =IF(A123<>"",ROSTER!B34,"") | C123: =IF(A123<>"",D38,"") | D123: =IF(A123="","",IF(D38="AVL","🔵 FLOAT",IF(OR($B$3<1,$B$3>28),"—",IF(INDEX(FATIGUE_TRACKER!E$4:AF$50,31,$B$3)>=CONFIG!$B$33-1,"⛔ FATIGUED",IF(INDEX(FATIGUE_TRACKER!E$4:AF$50,31,$B$3)>=CONFIG!$B$33-2,"🟡 OT (tired)","🟣 OT"))))) | E123: =IF(A123<>"",ROSTER!D34,"") | F123: =IF(A123="","",IF(OR($B$3<1,$B$3>28),"—",INDEX(FATIGUE_TRACKER!E$4:AF$50,31,$B$3)))
A124: =IF(OR(D39="AVL",D39="OFF"),ROSTER!A35,"") | B124: =IF(A124<>"",ROSTER!B35,"") | C124: =IF(A124<>"",D39,"") | D124: =IF(A124="","",IF(D39="AVL","🔵 FLOAT",IF(OR($B$3<1,$B$3>28),"—",IF(INDEX(FATIGUE_TRACKER!E$4:AF$50,32,$B$3)>=CONFIG!$B$33-1,"⛔ FATIGUED",IF(INDEX(FATIGUE_TRACKER!E$4:AF$50,32,$B$3)>=CONFIG!$B$33-2,"🟡 OT (tired)","🟣 OT"))))) | E124: =IF(A124<>"",ROSTER!D35,"") | F124: =IF(A124="","",IF(OR($B$3<1,$B$3>28),"—",INDEX(FATIGUE_TRACKER!E$4:AF$50,32,$B$3)))
A125: =IF(OR(D40="AVL",D40="OFF"),ROSTER!A36,"") | B125: =IF(A125<>"",ROSTER!B36,"") | C125: =IF(A125<>"",D40,"") | D125: =IF(A125="","",IF(D40="AVL","🔵 FLOAT",IF(OR($B$3<1,$B$3>28),"—",IF(INDEX(FATIGUE_TRACKER!E$4:AF$50,33,$B$3)>=CONFIG!$B$33-1,"⛔ FATIGUED",IF(INDEX(FATIGUE_TRACKER!E$4:AF$50,33,$B$3)>=CONFIG!$B$33-2,"🟡 OT (tired)","🟣 OT"))))) | E125: =IF(A125<>"",ROSTER!D36,"") | F125: =IF(A125="","",IF(OR($B$3<1,$B$3>28),"—",INDEX(FATIGUE_TRACKER!E$4:AF$50,33,$B$3)))
A126: =IF(OR(D41="AVL",D41="OFF"),ROSTER!A37,"") | B126: =IF(A126<>"",ROSTER!B37,"") | C126: =IF(A126<>"",D41,"") | D126: =IF(A126="","",IF(D41="AVL","🔵 FLOAT",IF(OR($B$3<1,$B$3>28),"—",IF(INDEX(FATIGUE_TRACKER!E$4:AF$50,34,$B$3)>=CONFIG!$B$33-1,"⛔ FATIGUED",IF(INDEX(FATIGUE_TRACKER!E$4:AF$50,34,$B$3)>=CONFIG!$B$33-2,"🟡 OT (tired)","🟣 OT"))))) | E126: =IF(A126<>"",ROSTER!D37,"") | F126: =IF(A126="","",IF(OR($B$3<1,$B$3>28),"—",INDEX(FATIGUE_TRACKER!E$4:AF$50,34,$B$3)))
A127: =IF(OR(D42="AVL",D42="OFF"),ROSTER!A38,"") | B127: =IF(A127<>"",ROSTER!B38,"") | C127: =IF(A127<>"",D42,"") | D127: =IF(A127="","",IF(D42="AVL","🔵 FLOAT",IF(OR($B$3<1,$B$3>28),"—",IF(INDEX(FATIGUE_TRACKER!E$4:AF$50,35,$B$3)>=CONFIG!$B$33-1,"⛔ FATIGUED",IF(INDEX(FATIGUE_TRACKER!E$4:AF$50,35,$B$3)>=CONFIG!$B$33-2,"🟡 OT (tired)","🟣 OT"))))) | E127: =IF(A127<>"",ROSTER!D38,"") | F127: =IF(A127="","",IF(OR($B$3<1,$B$3>28),"—",INDEX(FATIGUE_TRACKER!E$4:AF$50,35,$B$3)))
A128: =IF(OR(D43="AVL",D43="OFF"),ROSTER!A39,"") | B128: =IF(A128<>"",ROSTER!B39,"") | C128: =IF(A128<>"",D43,"") | D128: =IF(A128="","",IF(D43="AVL","🔵 FLOAT",IF(OR($B$3<1,$B$3>28),"—",IF(INDEX(FATIGUE_TRACKER!E$4:AF$50,36,$B$3)>=CONFIG!$B$33-1,"⛔ FATIGUED",IF(INDEX(FATIGUE_TRACKER!E$4:AF$50,36,$B$3)>=CONFIG!$B$33-2,"🟡 OT (tired)","🟣 OT"))))) | E128: =IF(A128<>"",ROSTER!D39,"") | F128: =IF(A128="","",IF(OR($B$3<1,$B$3>28),"—",INDEX(FATIGUE_TRACKER!E$4:AF$50,36,$B$3)))
A129: =IF(OR(D44="AVL",D44="OFF"),ROSTER!A40,"") | B129: =IF(A129<>"",ROSTER!B40,"") | C129: =IF(A129<>"",D44,"") | D129: =IF(A129="","",IF(D44="AVL","🔵 FLOAT",IF(OR($B$3<1,$B$3>28),"—",IF(INDEX(FATIGUE_TRACKER!E$4:AF$50,37,$B$3)>=CONFIG!$B$33-1,"⛔ FATIGUED",IF(INDEX(FATIGUE_TRACKER!E$4:AF$50,37,$B$3)>=CONFIG!$B$33-2,"🟡 OT (tired)","🟣 OT"))))) | E129: =IF(A129<>"",ROSTER!D40,"") | F129: =IF(A129="","",IF(OR($B$3<1,$B$3>28),"—",INDEX(FATIGUE_TRACKER!E$4:AF$50,37,$B$3)))
A130: =IF(OR(D45="AVL",D45="OFF"),ROSTER!A41,"") | B130: =IF(A130<>"",ROSTER!B41,"") | C130: =IF(A130<>"",D45,"") | D130: =IF(A130="","",IF(D45="AVL","🔵 FLOAT",IF(OR($B$3<1,$B$3>28),"—",IF(INDEX(FATIGUE_TRACKER!E$4:AF$50,38,$B$3)>=CONFIG!$B$33-1,"⛔ FATIGUED",IF(INDEX(FATIGUE_TRACKER!E$4:AF$50,38,$B$3)>=CONFIG!$B$33-2,"🟡 OT (tired)","🟣 OT"))))) | E130: =IF(A130<>"",ROSTER!D41,"") | F130: =IF(A130="","",IF(OR($B$3<1,$B$3>28),"—",INDEX(FATIGUE_TRACKER!E$4:AF$50,38,$B$3)))
...

Sheet CONTINGENCY_PLAN
A1: CONTINGENCY & FORTIFICATION PLAN
A3: ESCALATION PROTOCOL
A4: Level | B4: Trigger & Actions | C4: Max Duration
A5: ⬜ LVL 0 | B5: All covered. Float standby. | C5: Indefinite
A6: 🟢 LVL 1 | B6: Float deployed (1-3 gaps). OT alerted. | C6: 7 days
A7: 🟡 LVL 2 | B7: OT activated. Bank staff called. | C7: 7 days WTR
A8: 🟠 LVL 3 | B8: Agency booked. Handover pack ready. | C8: 14 days
A9: 🔴 LVL 4 | B9: Agency unavailable. Manager on floor. Emergency call-in 1.5x. | C9: 48hrs max
A10: ⚫ LVL 5 | B10: Close admissions. Notify CQC. Mutual aid. | C10: Immediate
A13: NIGHT VULNERABILITY COUNTERMEASURES
A14: 1. Night-First Float | B14: Float deploys night BEFORE day. Night=0 buffer; Day=4-5 buffer.
A15: 2. Standing Agency Night | B15: Pre-book 1 agency night/wk Nov-Mar. Cancel 24hrs. £343/wk.
A16: 3. 4th Night Staff | B16: Recruit 1 extra per night team. +£55K/yr. Eliminates #1 vulnerability.
A17: 4. Night Bank Staff | B17: 2 bank workers night-available. Zero-hours. Base+£3. 2hr response.
A18: 5. Mutual Aid Pact | B18: Agreement with 2-3 neighbouring homes to loan night staff at agreed rate.
A21: WEEKLY OT CAP (WTR)
A22: Daily model: OT=4/day. Weekly truth: same 4 people, max 8 shifts/wk.
A24: Scenario | B24: Gaps/d | C24: Gaps/wk | D24: Float/wk | E24: OT/wk | F24: Agency/wk | G24: Ag £/wk
A25: CLEAN | B25: 0 | C25: =B25*7 -> 0 | D25: =MIN(C25,15) -> 0 | E25: =MIN(MAX(C25-D25,0),CONFIG!$B$59) -> 0 | F25: =MAX(C25-D25-E25,0) -> 0 | G25: =(F25*0.7*12.25*CONFIG!$B$29+F25*0.3*12.25*CONFIG!$B$30) -> 0
A26: TYPICAL | B26: 2 | C26: =B26*7 -> 14 | D26: =MIN(C26,15) -> 14 | E26: =MIN(MAX(C26-D26,0),CONFIG!$B$59) -> 0 | F26: =MAX(C26-D26-E26,0) -> 0 | G26: =(F26*0.7*12.25*CONFIG!$B$29+F26*0.3*12.25*CONFIG!$B$30) -> 0
A27: BAD | B27: 4 | C27: =B27*7 -> 28 | D27: =MIN(C27,15) -> 15 | E27: =MIN(MAX(C27-D27,0),CONFIG!$B$59) -> 8 | F27: =MAX(C27-D27-E27,0) -> 5 | G27: =(F27*0.7*12.25*CONFIG!$B$29+F27*0.3*12.25*CONFIG!$B$30) -> 1457.75
A28: CRISIS | B28: 5 | C28: =B28*7 -> 35 | D28: =MIN(C28,15) -> 15 | E28: =MIN(MAX(C28-D28,0),CONFIG!$B$59) -> 8 | F28: =MAX(C28-D28-E28,0) -> 12 | G28: =(F28*0.7*12.25*CONFIG!$B$29+F28*0.3*12.25*CONFIG!$B$30) -> 3498.6
A29: WORST | B29: 6 | C29: =B29*7 -> 42 | D29: =MIN(C29,15) -> 15 | E29: =MIN(MAX(C29-D29,0),CONFIG!$B$59) -> 8 | F29: =MAX(C29-D29-E29,0) -> 19 | G29: =(F29*0.7*12.25*CONFIG!$B$29+F29*0.3*12.25*CONFIG!$B$30) -> 5539.45
A30: PANDEMIC | B30: 8 | C30: =B30*7 -> 56 | D30: =MIN(C30,15) -> 15 | E30: =MIN(MAX(C30-D30,0),CONFIG!$B$59) -> 8 | F30: =MAX(C30-D30-E30,0) -> 33 | G30: =(F30*0.7*12.25*CONFIG!$B$29+F30*0.3*12.25*CONFIG!$B$30) -> 9621.15
A32: BAD WEEK: daily model shows 0 agency. Weekly shows 5 needed.
A35: NOROVIRUS WAVE (14 days)
A37: Day | B37: Sick | C37: Float | D37: OT | E37: Agency | F37: Shortfall | G37: Level | H37: Cost | I37: Actions
A38: 1 | B38: 2 | C38: =MIN(B38,3) -> 2 | D38: =MIN(MAX(B38-C38,0),4) -> 0 | E38: =MAX(B38-C38-D38,0) -> 0 | F38: =MAX(E38-ROUND(E38*CONFIG!$B$60,0),0) -> 0 | G38: =IF(F38>0,"🔴 LVL4-5",IF(E38>0,"🟠 LVL3",IF(D38>0,"🟡 LVL2",IF(C38>0,"🟢 LVL1","⬜ LVL0")))) -> 🟢 LVL1 | H38: =1539+D38*12.25*(CONFIG!$B$28-1)*CONFIG!$B$61+MIN(E38,ROUND(E38*CONFIG!$B$60,0))*0.7*12.25*CONFIG!$B$29+MIN(E38,ROUND(E38*CONFIG!$B$60,0))*0.3*12.25*CONFIG!$B$30+F38*CONFIG!$B$57*12.25 -> 1539 | I38: Index cases
A39: 2 | B39: 4 | C39: =MIN(B39,3) -> 3 | D39: =MIN(MAX(B39-C39,0),4) -> 1 | E39: =MAX(B39-C39-D39,0) -> 0 | F39: =MAX(E39-ROUND(E39*CONFIG!$B$60,0),0) -> 0 | G39: =IF(F39>0,"🔴 LVL4-5",IF(E39>0,"🟠 LVL3",IF(D39>0,"🟡 LVL2",IF(C39>0,"🟢 LVL1","⬜ LVL0")))) -> 🟡 LVL2 | H39: =1539+D39*12.25*(CONFIG!$B$28-1)*CONFIG!$B$61+MIN(E39,ROUND(E39*CONFIG!$B$60,0))*0.7*12.25*CONFIG!$B$29+MIN(E39,ROUND(E39*CONFIG!$B$60,0))*0.3*12.25*CONFIG!$B$30+F39*CONFIG!$B$57*12.25 -> 1688.5725 | I39: Outbreak declared
A40: 3 | B40: 7 | C40: =MIN(B40,3) -> 3 | D40: =MIN(MAX(B40-C40,0),4) -> 4 | E40: =MAX(B40-C40-D40,0) -> 0 | F40: =MAX(E40-ROUND(E40*CONFIG!$B$60,0),0) -> 0 | G40: =IF(F40>0,"🔴 LVL4-5",IF(E40>0,"🟠 LVL3",IF(D40>0,"🟡 LVL2",IF(C40>0,"🟢 LVL1","⬜ LVL0")))) -> 🟡 LVL2 | H40: =1539+D40*12.25*(CONFIG!$B$28-1)*CONFIG!$B$61+MIN(E40,ROUND(E40*CONFIG!$B$60,0))*0.7*12.25*CONFIG!$B$29+MIN(E40,ROUND(E40*CONFIG!$B$60,0))*0.3*12.25*CONFIG!$B$30+F40*CONFIG!$B$57*12.25 -> 2137.29 | I40: IPC active
A41: 4 | B41: 9 | C41: =MIN(B41,3) -> 3 | D41: =MIN(MAX(B41-C41,0),4) -> 4 | E41: =MAX(B41-C41-D41,0) -> 2 | F41: =MAX(E41-ROUND(E41*CONFIG!$B$60,0),0) -> 0 | G41: =IF(F41>0,"🔴 LVL4-5",IF(E41>0,"🟠 LVL3",IF(D41>0,"🟡 LVL2",IF(C41>0,"🟢 LVL1","⬜ LVL0")))) -> 🟠 LVL3 | H41: =1539+D41*12.25*(CONFIG!$B$28-1)*CONFIG!$B$61+MIN(E41,ROUND(E41*CONFIG!$B$60,0))*0.7*12.25*CONFIG!$B$29+MIN(E41,ROUND(E41*CONFIG!$B$60,0))*0.3*12.25*CONFIG!$B$30+F41*CONFIG!$B$57*12.25 -> 2720.39 | I41: PEAK
A42: 5 | B42: 10 | C42: =MIN(B42,3) -> 3 | D42: =MIN(MAX(B42-C42,0),4) -> 4 | E42: =MAX(B42-C42-D42,0) -> 3 | F42: =MAX(E42-ROUND(E42*CONFIG!$B$60,0),0) -> 0 | G42: =IF(F42>0,"🔴 LVL4-5",IF(E42>0,"🟠 LVL3",IF(D42>0,"🟡 LVL2",IF(C42>0,"🟢 LVL1","⬜ LVL0")))) -> 🟠 LVL3 | H42: =1539+D42*12.25*(CONFIG!$B$28-1)*CONFIG!$B$61+MIN(E42,ROUND(E42*CONFIG!$B$60,0))*0.7*12.25*CONFIG!$B$29+MIN(E42,ROUND(E42*CONFIG!$B$60,0))*0.3*12.25*CONFIG!$B$30+F42*CONFIG!$B$57*12.25 -> 3011.94 | I42: PEAK+1 Manager floor
A43: 6 | B43: 8 | C43: =MIN(B43,3) -> 3 | D43: =MIN(MAX(B43-C43,0),4) -> 4 | E43: =MAX(B43-C43-D43,0) -> 1 | F43: =MAX(E43-ROUND(E43*CONFIG!$B$60,0),0) -> 0 | G43: =IF(F43>0,"🔴 LVL4-5",IF(E43>0,"🟠 LVL3",IF(D43>0,"🟡 LVL2",IF(C43>0,"🟢 LVL1","⬜ LVL0")))) -> 🟠 LVL3 | H43: =1539+D43*12.25*(CONFIG!$B$28-1)*CONFIG!$B$61+MIN(E43,ROUND(E43*CONFIG!$B$60,0))*0.7*12.25*CONFIG!$B$29+MIN(E43,ROUND(E43*CONFIG!$B$60,0))*0.3*12.25*CONFIG!$B$30+F43*CONFIG!$B$57*12.25 -> 2428.84 | I43: First recoveries
A44: 7 | B44: 7 | C44: =MIN(B44,3) -> 3 | D44: =MIN(MAX(B44-C44,0),4) -> 4 | E44: =MAX(B44-C44-D44,0) -> 0 | F44: =MAX(E44-ROUND(E44*CONFIG!$B$60,0),0) -> 0 | G44: =IF(F44>0,"🔴 LVL4-5",IF(E44>0,"🟠 LVL3",IF(D44>0,"🟡 LVL2",IF(C44>0,"🟢 LVL1","⬜ LVL0")))) -> 🟡 LVL2 | H44: =1539+D44*12.25*(CONFIG!$B$28-1)*CONFIG!$B$61+MIN(E44,ROUND(E44*CONFIG!$B$60,0))*0.7*12.25*CONFIG!$B$29+MIN(E44,ROUND(E44*CONFIG!$B$60,0))*0.3*12.25*CONFIG!$B$30+F44*CONFIG!$B$57*12.25 -> 2137.29 | I44: Declining
A45: 8 | B45: 5 | C45: =MIN(B45,3) -> 3 | D45: =MIN(MAX(B45-C45,0),4) -> 2 | E45: =MAX(B45-C45-D45,0) -> 0 | F45: =MAX(E45-ROUND(E45*CONFIG!$B$60,0),0) -> 0 | G45: =IF(F45>0,"🔴 LVL4-5",IF(E45>0,"🟠 LVL3",IF(D45>0,"🟡 LVL2",IF(C45>0,"🟢 LVL1","⬜ LVL0")))) -> 🟡 LVL2 | H45: =1539+D45*12.25*(CONFIG!$B$28-1)*CONFIG!$B$61+MIN(E45,ROUND(E45*CONFIG!$B$60,0))*0.7*12.25*CONFIG!$B$29+MIN(E45,ROUND(E45*CONFIG!$B$60,0))*0.3*12.25*CONFIG!$B$30+F45*CONFIG!$B$57*12.25 -> 1838.145 | I45: Recovery
A46: 9 | B46: 4 | C46: =MIN(B46,3) -> 3 | D46: =MIN(MAX(B46-C46,0),4) -> 1 | E46: =MAX(B46-C46-D46,0) -> 0 | F46: =MAX(E46-ROUND(E46*CONFIG!$B$60,0),0) -> 0 | G46: =IF(F46>0,"🔴 LVL4-5",IF(E46>0,"🟠 LVL3",IF(D46>0,"🟡 LVL2",IF(C46>0,"🟢 LVL1","⬜ LVL0")))) -> 🟡 LVL2 | H46: =1539+D46*12.25*(CONFIG!$B$28-1)*CONFIG!$B$61+MIN(E46,ROUND(E46*CONFIG!$B$60,0))*0.7*12.25*CONFIG!$B$29+MIN(E46,ROUND(E46*CONFIG!$B$60,0))*0.3*12.25*CONFIG!$B$30+F46*CONFIG!$B$57*12.25 -> 1688.5725 | I46: Near-normal
A47: 10 | B47: 3 | C47: =MIN(B47,3) -> 3 | D47: =MIN(MAX(B47-C47,0),4) -> 0 | E47: =MAX(B47-C47-D47,0) -> 0 | F47: =MAX(E47-ROUND(E47*CONFIG!$B$60,0),0) -> 0 | G47: =IF(F47>0,"🔴 LVL4-5",IF(E47>0,"🟠 LVL3",IF(D47>0,"🟡 LVL2",IF(C47>0,"🟢 LVL1","⬜ LVL0")))) -> 🟢 LVL1 | H47: =1539+D47*12.25*(CONFIG!$B$28-1)*CONFIG!$B$61+MIN(E47,ROUND(E47*CONFIG!$B$60,0))*0.7*12.25*CONFIG!$B$29+MIN(E47,ROUND(E47*CONFIG!$B$60,0))*0.3*12.25*CONFIG!$B$30+F47*CONFIG!$B$57*12.25 -> 1539 | I47: Monitoring
A48: 11 | B48: 2 | C48: =MIN(B48,3) -> 2 | D48: =MIN(MAX(B48-C48,0),4) -> 0 | E48: =MAX(B48-C48-D48,0) -> 0 | F48: =MAX(E48-ROUND(E48*CONFIG!$B$60,0),0) -> 0 | G48: =IF(F48>0,"🔴 LVL4-5",IF(E48>0,"🟠 LVL3",IF(D48>0,"🟡 LVL2",IF(C48>0,"🟢 LVL1","⬜ LVL0")))) -> 🟢 LVL1 | H48: =1539+D48*12.25*(CONFIG!$B$28-1)*CONFIG!$B$61+MIN(E48,ROUND(E48*CONFIG!$B$60,0))*0.7*12.25*CONFIG!$B$29+MIN(E48,ROUND(E48*CONFIG!$B$60,0))*0.3*12.25*CONFIG!$B$30+F48*CONFIG!$B$57*12.25 -> 1539 | I48: Almost clear
A49: 12 | B49: 1 | C49: =MIN(B49,3) -> 1 | D49: =MIN(MAX(B49-C49,0),4) -> 0 | E49: =MAX(B49-C49-D49,0) -> 0 | F49: =MAX(E49-ROUND(E49*CONFIG!$B$60,0),0) -> 0 | G49: =IF(F49>0,"🔴 LVL4-5",IF(E49>0,"🟠 LVL3",IF(D49>0,"🟡 LVL2",IF(C49>0,"🟢 LVL1","⬜ LVL0")))) -> 🟢 LVL1 | H49: =1539+D49*12.25*(CONFIG!$B$28-1)*CONFIG!$B$61+MIN(E49,ROUND(E49*CONFIG!$B$60,0))*0.7*12.25*CONFIG!$B$29+MIN(E49,ROUND(E49*CONFIG!$B$60,0))*0.3*12.25*CONFIG!$B$30+F49*CONFIG!$B$57*12.25 -> 1539 | I49: Clearing
... A51: 14 | B51: 0 | C51: =MIN(B51,3) -> 0 | D51: =MIN(MAX(B51-C51,0),4) -> 0 | E51: =MAX(B51-C51-D51,0) -> 0 | F51: =MAX(E51-ROUND(E51*CONFIG!$B$60,0),0) -> 0 | G51: =IF(F51>0,"🔴 LVL4-5",IF(E51>0,"🟠 LVL3",IF(D51>0,"🟡 LVL2",IF(C51>0,"🟢 LVL1","⬜ LVL0")))) -> ⬜ LVL0 | H51: =1539+D51*12.25*(CONFIG!$B$28-1)*CONFIG!$B$61+MIN(E51,ROUND(E51*CONFIG!$B$60,0))*0.7*12.25*CONFIG!$B$29+MIN(E51,ROUND(E51*CONFIG!$B$60,0))*0.3*12.25*CONFIG!$B$30+F51*CONFIG!$B$57*12.25 -> 1539 | I51: Normal
A52: OUTBREAK TOTAL | H52: =SUM(H38:H51) -> 26885.04
A53: Normal 14 days | H53: =1539*14 -> 21546
A54: OUTBREAK PREMIUM | H54: =H52-H53 -> 5339.04
A57: WINTER BUDGET (Dec-Feb)
A58: Standing agency nights 17wk | B58: =17*12.25*28 -> 5831
A59: Bank staff recruit ×4 | B59: 2000
A60: Flu vaccines ×25 | B60: 500
A61: IPC stock | B61: 750
A62: Winter OT incentive 12wk | B62: =8*12*12.25*3 -> 3528
A63: Emergency reserve | B63: =H54 -> 5339.04
A64: TOTAL WINTER BUDGET | B64: =SUM(B58:B63) -> 17948.04

Sheet CONFIG
A1: CARE HOME STAFFING SYSTEM v3.0
A2: SELF-ORGANIZING EDITION
A4: SETTING | B4: VALUE | C4: UNIT | D4: NOTES
A5: Roster Start Date | B5: 2025-01-06 | D5: Must be a Monday
A6: Cycle Length | B6: 14 | C6: days | D6: Panama rotation period
A8: SHIFT TIMES & HOURS
A9: Early Shift (E) | B9: 6 | C9: hours | D9: 08:00-14:00
A10: Late Shift (L) | B10: 6 | C10: hours | D10: 14:00-20:00
A11: Full Day (EL) | B11: 12.25 | C11: hours | D11: 07:45-20:00 (incl 15min handover)
A12: Night Shift (N) | B12: 12.25 | C12: hours | D12: 19:45-08:00 (incl 15min handover)
A14: HANDOVER & BREAKS
A15: Evening Handover | B15: 15 | C15: mins | D15: 19:45-20:00 (Day→Night overlap)
A16: Morning Handover | B16: 15 | C16: mins | D16: 07:45-08:00 (Night→Day overlap)
A17: Break Deduction | B17: 0 | C17: hours | D17: Breaks are PAID (care home requirement)
A19: MINIMUM STAFFING
A20: Early Min (Heads) | B20: 3 | C20: people | D20: Minimum on Early
A21: Early Min (Skill) | B21: 2 | C21: points | D21: Senior=1.0, Junior=0.5
A22: Late Min (Heads) | B22: 3 | C22: people | D22: Minimum on Late
A23: Late Min (Skill) | B23: 2 | C23: points | D23: Senior=1.0, Junior=0.5
A24: Night Min (Heads) | B24: 3 | C24: people | D24: Minimum on Night
A25: Night Min (Skill) | B25: 1.5 | C25: points | D25: At least 1 Senior
A27: OVERTIME & AGENCY
A28: OT Premium | B28: 2 | C28: £/hour | D28: Extra for OC/OT shifts
A29: Agency Rate (Day) | B29: 22 | C29: £/hour | D29: External day cover
A30: Agency Rate (Night) | B30: 28 | C30: £/hour | D30: External night cover (12hr)
A32: SAFETY LIMITS
A33: Max Consecutive Days | B33: 5 | C33: days | D33: Fatigue limit
A34: Max AL Same Day | B34: 2 | C34: people | D34: Coverage protection
A35: Float Retainer | B35: 50 | C35: £/week | D35: Standby payment
A37: ANNUAL LEAVE
A38: AL Entitlement | B38: 28 | C38: days/year | D38: Standard UK
A40: WEEKLY HOURS TARGETS
A41: FT Target (EL workers) | B41: 42.875 | C41: hours/week | D41: 3.5 shifts × 12.25hrs
A42: FT Target (E or L only) | B42: 36 | C42: hours/week | D42: 6 shifts avg
A43: Night FT Target | B43: 42.875 | C43: hours/week | D43: 3.5 shifts × 12.25hrs
A45: BANK HOLIDAY
A46: BH Premium | B46: 1.5 | C46: multiplier | D46: Applied to base rate on bank holidays
A48: SICKNESS ASSUMPTIONS
A49: Avg Sickness Rate | B49: 0.06 | C49: % | D49: 6% sector average (5-8% typical)
A50: Avg AL per day | B50: 1 | C50: people | D50: Typical daily AL overlap
A51: AGENCY NIGHT SPLIT
A52: Night Gap % (of total) | B52: 0.3 | C52: 30% of gaps are night shifts
A54: FORTIFICATION PARAMETERS
A55: Night Float Priority | B55: Y
A56: Emergency Call-In Premium | B56: 1.5
A57: Manager Floor Rate | B57: 18
A58: Winter Sick Uplift | B58: 1.8
A59: Weekly OT Cap (shifts) | B59: 8
A60: Agency Availability % | B60: 1
A61: NLW Rate Apr 2025 | B61: 12.21
A62: Senior Differential | B62: 1.5
A63: Team Lead Differential | B63: 2.5
A64: Night Premium | B64: 0.5
A65: Bank Staff Pool Size | B65: 4

Sheet STAFF_DB
A1: STAFF DATABASE - Single Source of Truth
A2: Add/remove staff here. ROSTER updates automatically.
A4: ID | B4: Name | C4: Role | D4: Team | E4: Pref | F4: Skill | G4: Rate | H4: Active | I4: Start Date | J4: Notes | K4: WTR Opt-Out
A5: S001 | B5: Alice Johnson | C5: Senior Carer | D5: Day A | E5: EL | F5: 1 | G5: 12.5 | H5: Y | I5: 2025-01-06 | K5: Y
A6: S002 | B6: Bob Smith | C6: Carer | D6: Day A | E6: EL | F6: 0.5 | G6: 11 | H6: Y | I6: 2025-01-06 | K6: Y
A7: S003 | B7: Carol Davis | C7: Senior Carer | D7: Day A | E7: EL | F7: 1 | G7: 12.5 | H7: Y | I7: 2025-01-06 | K7: Y
A8: S004 | B8: David Wilson | C8: Carer | D8: Day A | E8: EL | F8: 0.5 | G8: 11 | H8: Y | I8: 2025-01-06 | K8: Y
A9: S005 | B9: Emma Brown | C9: Team Lead | D9: Day A | E9: EL | F9: 1.5 | G9: 14 | H9: Y | I9: 2025-01-06 | K9: Y
A10: S006 | B10: Fiona Hart | C10: Carer | D10: Day A | E10: EL | F10: 0.5 | G10: 11 | H10: Y | I10: 2025-01-06 | K10: Y
A11: S007 | B11: George King | C11: Senior Carer | D11: Day A | E11: EL | F11: 1 | G11: 12.5 | H11: Y | I11: 2025-01-06 | K11: Y
A12: S008 | B12: Hannah Lee | C12: Senior Carer | D12: Day B | E12: EL | F12: 1 | G12: 12.5 | H12: Y | I12: 2025-01-06 | K12: Y
A13: S009 | B13: Ian Clark | C13: Carer | D13: Day B | E13: EL | F13: 0.5 | G13: 11 | H13: Y | I13: 2025-01-06 | K13: Y
A14: S010 | B14: Julia Martin | C14: Senior Carer | D14: Day B | E14: EL | F14: 1 | G14: 12.5 | H14: Y | I14: 2025-01-06 | K14: Y
A15: S011 | B15: Kevin White | C15: Carer | D15: Day B | E15: EL | F15: 0.5 | G15: 11 | H15: Y | I15: 2025-01-06 | K15: Y
A16: S012 | B16: Laura Adams | C16: Team Lead | D16: Day B | E16: EL | F16: 1.5 | G16: 14 | H16: Y | I16: 2025-01-06 | K16: Y
... A27: S023 | B27: Wendy Jones | C27: Float Carer | D27: Float | E27: ANY | F27: 0.5 | G27: 11.5 | H27: Y | I27: 2025-01-06 | K27: Y
A28: S024 | B28: Xena Price | C28: Carer (PT) | D28: Day A | E28: E | F28: 0.5 | G28: 10.5 | H28: Y | I28: 45663 | J28: Early only - school run | K28: Y
A29: S025 | B29: Yasmin Reed | C29: Senior (PT) | D29: Day B | E29: L | F29: 1 | G29: 12 | H29: Y | I29: 45663 | J29: Late only - prefers afternoons | K29: Y
A30: TEAM SUMMARY
A31: Day A | B31: =COUNTIFS(D5:D100,"Day A",H5:H100,"Y") -> 8
A32: Day B | B32: =COUNTIFS(D5:D100,"Day B",H5:H100,"Y") -> 8
A33: Night A | B33: =COUNTIFS(D5:D100,"Night A",H5:H100,"Y") -> 3
A34: Night B | B34: =COUNTIFS(D5:D100,"Night B",H5:H100,"Y") -> 3
A35: Float | B35: =COUNTIFS(D5:D100,"Float",H5:H100,"Y") -> 3
A36: TOTAL ACTIVE | B36: =COUNTIF(H5:H100,"Y") -> 25
A37: Part-Time (E/L) | B37: =COUNTIFS(E5:E100,"E",H5:H100,"Y")+COUNTIFS(E5:E100,"L",H5:H100,"Y") -> 2
A38: TOTAL ACTIVE | B38: =COUNTIF(H5:H100,"Y") -> 25

Sheet ROSTER
A1: DYNAMIC ROSTER - Self-Organizing
A2: Gold cells = "Agency Kill" targets (rested staff on short week) | E2: Week 1 | L2: Week 2 | S2: Week 3 | Z2: Week 4
A3: Name | B3: Team | C3: Pref | D3: Skill | E3: 06 Mon | F3: 07 Tue | G3: 08 Wed | H3: 09 Thu | I3: 10 Fri | J3: 11 Sat | K3: 12 Sun | L3: 13 Mon | M3: 14 Tue | N3: 15 Wed | O3: 16 Thu | P3: 17 Fri | Q3: 18 Sat | R3: 19 Sun | S3: 20 Mon | T3: 21 Tue | U3: 22 Wed | V3: 23 Thu | W3: 24 Fri | X3: 25 Sat | Y3: 26 Sun | Z3: 27 Mon | AA3: 28 Tue | AB3: 29 Wed | AC3: 30 Thu | AD3: 31 Fri | AE3: 01 Sat | AF3: 02 Sun | AG3: Rate | AH3: Total Hrs | AI3: Gross Pay | AJ3: OT Hrs | AK3: OT Pay | AL3: Week 1 | AM3: Week 2 | AN3: Status | AO3: BH Prem | AP3: Wk Avg Hrs | AQ3: WTR Check
A4: Alice Johnson | B4: Day A | C4: EL | D4: 1 | E4: EL | F4: EL | G4: OFF | H4: OFF | I4: EL | J4: EL | K4: EL | L4: OFF | M4: OFF | N4: EL | O4: EL | P4: OFF | Q4: OFF | R4: OFF | S4: EL | T4: EL | U4: OFF | V4: OFF | W4: EL | X4: EL | Y4: EL | Z4: OFF | AA4: OFF | AB4: EL | AC4: EL | AD4: OFF | AE4: OFF | AF4: OFF | AG4: 12.5 | AH4: =(COUNTIF(E4:AF4,"E")*CONFIG!$B$9+COUNTIF(E4:AF4,"L")*CONFIG!$B$10+COUNTIF(E4:AF4,"EL")*CONFIG!$B$11+COUNTIF(E4:AF4,"N")*CONFIG!$B$12+COUNTIF(E4:AF4,"OC-E")*CONFIG!$B$9+COUNTIF(E4:AF4,"OC-L")*CONFIG!$B$10+COUNTIF(E4:AF4,"OC-EL")*CONFIG!$B$11+COUNTIF(E4:AF4,"OC-N")*CONFIG!$B$12+COUNTIF(E4:AF4,"ADM")*CONFIG!$B$9+COUNTIF(E4:AF4,"TRN")*CONFIG!$B$9+COUNTIF(E4:AF4,"BH-D")*CONFIG!$B$11+COUNTIF(E4:AF4,"BH-N")*CONFIG!$B$12) -> 171.5 | AI4: =AH4*AG4 -> 2143.75 | AJ4: =(COUNTIF(E4:AF4,"OC-E")*CONFIG!$B$9+COUNTIF(E4:AF4,"OC-L")*CONFIG!$B$10+COUNTIF(E4:AF4,"OC-EL")*CONFIG!$B$11+COUNTIF(E4:AF4,"OC-N")*CONFIG!$B$12+COUNTIF(E4:AF4,"OT")*CONFIG!$B$9) -> 0 | AK4: =AJ4*CONFIG!$B$28 -> 0 | AL4: =(COUNTIF(E4:K4,"E")+COUNTIF(E4:K4,"L")+COUNTIF(E4:K4,"OC-E")+COUNTIF(E4:K4,"OC-L"))*6+(COUNTIF(E4:K4,"EL")+COUNTIF(E4:K4,"OC-EL")+COUNTIF(E4:K4,"BH-D"))*12.25+(COUNTIF(E4:K4,"N")+COUNTIF(E4:K4,"OC-N")+COUNTIF(E4:K4,"BH-N"))*12.25 -> 61.25 | AM4: =(COUNTIF(L4:R4,"E")+COUNTIF(L4:R4,"L")+COUNTIF(L4:R4,"OC-E")+COUNTIF(L4:R4,"OC-L"))*6+(COUNTIF(L4:R4,"EL")+COUNTIF(L4:R4,"OC-EL")+COUNTIF(L4:R4,"BH-D"))*12.25+(COUNTIF(L4:R4,"N")+COUNTIF(L4:R4,"OC-N")+COUNTIF(L4:R4,"BH-N"))*12.25 -> 24.5 | AN4: =IF(AL4<AM4,"Short W1",IF(AM4<AL4,"Short W2","Balanced")) -> Short W2 | AO4: =(COUNTIF(E4:AF4,"BH-D")*CONFIG!$B$11*AG4*(CONFIG!$B$46-1)+COUNTIF(E4:AF4,"BH-N")*CONFIG!$B$12*AG4*(CONFIG!$B$46-1)) -> 0 | AP4: =AH4/4 -> 42.875 | AQ4: =IF(AP4>48,"⚠️ >48hr WTR BREACH",IF(AP4>44,"🟡 HIGH","✅ OK")) -> ✅ OK
A5: Bob Smith | B5: Day A | C5: EL | D5: 0.5 | E5: EL | F5: EL | G5: OFF | H5: OFF | I5: EL | J5: EL | K5: EL | L5: OFF | M5: OFF | N5: EL | O5: EL | P5: OFF | Q5: OFF | R5: OFF | S5: EL | T5: EL | U5: OFF | V5: OFF | W5: EL | X5: EL | Y5: EL | Z5: OFF | AA5: OFF | AB5: EL | AC5: EL | AD5: OFF | AE5: OFF | AF5: OFF | AG5: 11 | AH5: =(COUNTIF(E5:AF5,"E")*CONFIG!$B$9+COUNTIF(E5:AF5,"L")*CONFIG!$B$10+COUNTIF(E5:AF5,"EL")*CONFIG!$B$11+COUNTIF(E5:AF5,"N")*CONFIG!$B$12+COUNTIF(E5:AF5,"OC-E")*CONFIG!$B$9+COUNTIF(E5:AF5,"OC-L")*CONFIG!$B$10+COUNTIF(E5:AF5,"OC-EL")*CONFIG!$B$11+COUNTIF(E5:AF5,"OC-N")*CONFIG!$B$12+COUNTIF(E5:AF5,"ADM")*CONFIG!$B$9+COUNTIF(E5:AF5,"TRN")*CONFIG!$B$9+COUNTIF(E5:AF5,"BH-D")*CONFIG!$B$11+COUNTIF(E5:AF5,"BH-N")*CONFIG!$B$12) -> 171.5 | AI5: =AH5*AG5 -> 1886.5 | AJ5: =(COUNTIF(E5:AF5,"OC-E")*CONFIG!$B$9+COUNTIF(E5:AF5,"OC-L")*CONFIG!$B$10+COUNTIF(E5:AF5,"OC-EL")*CONFIG!$B$11+COUNTIF(E5:AF5,"OC-N")*CONFIG!$B$12+COUNTIF(E5:AF5,"OT")*CONFIG!$B$9) -> 0 | AK5: =AJ5*CONFIG!$B$28 -> 0 | AL5: =(COUNTIF(E5:K5,"E")+COUNTIF(E5:K5,"L")+COUNTIF(E5:K5,"OC-E")+COUNTIF(E5:K5,"OC-L"))*6+(COUNTIF(E5:K5,"EL")+COUNTIF(E5:K5,"OC-EL")+COUNTIF(E5:K5,"BH-D"))*12.25+(COUNTIF(E5:K5,"N")+COUNTIF(E5:K5,"OC-N")+COUNTIF(E5:K5,"BH-N"))*12.25 -> 61.25 | AM5: =(COUNTIF(L5:R5,"E")+COUNTIF(L5:R5,"L")+COUNTIF(L5:R5,"OC-E")+COUNTIF(L5:R5,"OC-L"))*6+(COUNTIF(L5:R5,"EL")+COUNTIF(L5:R5,"OC-EL")+COUNTIF(L5:R5,"BH-D"))*12.25+(COUNTIF(L5:R5,"N")+COUNTIF(L5:R5,"OC-N")+COUNTIF(L5:R5,"BH-N"))*12.25 -> 24.5 | AN5: =IF(AL5<AM5,"Short W1",IF(AM5<AL5,"Short W2","Balanced")) -> Short W2 | AO5: =(COUNTIF(E5:AF5,"BH-D")*CONFIG!$B$11*AG5*(CONFIG!$B$46-1)+COUNTIF(E5:AF5,"BH-N")*CONFIG!$B$12*AG5*(CONFIG!$B$46-1)) -> 0 | AP5: =AH5/4 -> 42.875 | AQ5: =IF(AP5>48,"⚠️ >48hr WTR BREACH",IF(AP5>44,"🟡 HIGH","✅ OK")) -> ✅ OK
A6: Carol Davis | B6: Day A | C6: EL | D6: 1 | E6: EL | F6: EL | G6: OFF | H6: OFF | I6: EL | J6: EL | K6: EL | L6: OFF | M6: OFF | N6: EL | O6: EL | P6: OFF | Q6: OFF | R6: OFF | S6: EL | T6: EL | U6: OFF | V6: OFF | W6: EL | X6: EL | Y6: EL | Z6: OFF | AA6: OFF | AB6: EL | AC6: EL | AD6: OFF | AE6: OFF | AF6: OFF | AG6: 12.5 | AH6: =(COUNTIF(E6:AF6,"E")*CONFIG!$B$9+COUNTIF(E6:AF6,"L")*CONFIG!$B$10+COUNTIF(E6:AF6,"EL")*CONFIG!$B$11+COUNTIF(E6:AF6,"N")*CONFIG!$B$12+COUNTIF(E6:AF6,"OC-E")*CONFIG!$B$9+COUNTIF(E6:AF6,"OC-L")*CONFIG!$B$10+COUNTIF(E6:AF6,"OC-EL")*CONFIG!$B$11+COUNTIF(E6:AF6,"OC-N")*CONFIG!$B$12+COUNTIF(E6:AF6,"ADM")*CONFIG!$B$9+COUNTIF(E6:AF6,"TRN")*CONFIG!$B$9+COUNTIF(E6:AF6,"BH-D")*CONFIG!$B$11+COUNTIF(E6:AF6,"BH-N")*CONFIG!$B$12) -> 171.5 | AI6: =AH6*AG6 -> 2143.75 | AJ6: =(COUNTIF(E6:AF6,"OC-E")*CONFIG!$B$9+COUNTIF(E6:AF6,"OC-L")*CONFIG!$B$10+COUNTIF(E6:AF6,"OC-EL")*CONFIG!$B$11+COUNTIF(E6:AF6,"OC-N")*CONFIG!$B$12+COUNTIF(E6:AF6,"OT")*CONFIG!$B$9) -> 0 | AK6: =AJ6*CONFIG!$B$28 -> 0 | AL6: =(COUNTIF(E6:K6,"E")+COUNTIF(E6:K6,"L")+COUNTIF(E6:K6,"OC-E")+COUNTIF(E6:K6,"OC-L"))*6+(COUNTIF(E6:K6,"EL")+COUNTIF(E6:K6,"OC-EL")+COUNTIF(E6:K6,"BH-D"))*12.25+(COUNTIF(E6:K6,"N")+COUNTIF(E6:K6,"OC-N")+COUNTIF(E6:K6,"BH-N"))*12.25 -> 61.25 | AM6: =(COUNTIF(L6:R6,"E")+COUNTIF(L6:R6,"L")+COUNTIF(L6:R6,"OC-E")+COUNTIF(L6:R6,"OC-L"))*6+(COUNTIF(L6:R6,"EL")+COUNTIF(L6:R6,"OC-EL")+COUNTIF(L6:R6,"BH-D"))*12.25+(COUNTIF(L6:R6,"N")+COUNTIF(L6:R6,"OC-N")+COUNTIF(L6:R6,"BH-N"))*12.25 -> 24.5 | AN6: =IF(AL6<AM6,"Short W1",IF(AM6<AL6,"Short W2","Balanced")) -> Short W2 | AO6: =(COUNTIF(E6:AF6,"BH-D")*CONFIG!$B$11*AG6*(CONFIG!$B$46-1)+COUNTIF(E6:AF6,"BH-N")*CONFIG!$B$12*AG6*(CONFIG!$B$46-1)) -> 0 | AP6: =AH6/4 -> 42.875 | AQ6: =IF(AP6>48,"⚠️ >48hr WTR BREACH",IF(AP6>44,"🟡 HIGH","✅ OK")) -> ✅ OK
A7: David Wilson | B7: Day A | C7: EL | D7: 0.5 | E7: EL | F7: EL | G7: OFF | H7: OFF | I7: EL | J7: EL | K7: EL | L7: OFF | M7: OFF | N7: EL | O7: EL | P7: OFF | Q7: OFF | R7: OFF | S7: EL | T7: EL | U7: OFF | V7: OFF | W7: EL | X7: EL | Y7: EL | Z7: OFF | AA7: OFF | AB7: EL | AC7: EL | AD7: OFF | AE7: OFF | AF7: OFF | AG7: 11 | AH7: =(COUNTIF(E7:AF7,"E")*CONFIG!$B$9+COUNTIF(E7:AF7,"L")*CONFIG!$B$10+COUNTIF(E7:AF7,"EL")*CONFIG!$B$11+COUNTIF(E7:AF7,"N")*CONFIG!$B$12+COUNTIF(E7:AF7,"OC-E")*CONFIG!$B$9+COUNTIF(E7:AF7,"OC-L")*CONFIG!$B$10+COUNTIF(E7:AF7,"OC-EL")*CONFIG!$B$11+COUNTIF(E7:AF7,"OC-N")*CONFIG!$B$12+COUNTIF(E7:AF7,"ADM")*CONFIG!$B$9+COUNTIF(E7:AF7,"TRN")*CONFIG!$B$9+COUNTIF(E7:AF7,"BH-D")*CONFIG!$B$11+COUNTIF(E7:AF7,"BH-N")*CONFIG!$B$12) -> 171.5 | AI7: =AH7*AG7 -> 1886.5 | AJ7: =(COUNTIF(E7:AF7,"OC-E")*CONFIG!$B$9+COUNTIF(E7:AF7,"OC-L")*CONFIG!$B$10+COUNTIF(E7:AF7,"OC-EL")*CONFIG!$B$11+COUNTIF(E7:AF7,"OC-N")*CONFIG!$B$12+COUNTIF(E7:AF7,"OT")*CONFIG!$B$9) -> 0 | AK7: =AJ7*CONFIG!$B$28 -> 0 | AL7: =(COUNTIF(E7:K7,"E")+COUNTIF(E7:K7,"L")+COUNTIF(E7:K7,"OC-E")+COUNTIF(E7:K7,"OC-L"))*6+(COUNTIF(E7:K7,"EL")+COUNTIF(E7:K7,"OC-EL")+COUNTIF(E7:K7,"BH-D"))*12.25+(COUNTIF(E7:K7,"N")+COUNTIF(E7:K7,"OC-N")+COUNTIF(E7:K7,"BH-N"))*12.25 -> 61.25 | AM7: =(COUNTIF(L7:R7,"E")+COUNTIF(L7:R7,"L")+COUNTIF(L7:R7,"OC-E")+COUNTIF(L7:R7,"OC-L"))*6+(COUNTIF(L7:R7,"EL")+COUNTIF(L7:R7,"OC-EL")+COUNTIF(L7:R7,"BH-D"))*12.25+(COUNTIF(L7:R7,"N")+COUNTIF(L7:R7,"OC-N")+COUNTIF(L7:R7,"BH-N"))*12.25 -> 24.5 | AN7: =IF(AL7<AM7,"Short W1",IF(AM7<AL7,"Short W2","Balanced")) -> Short W2 | AO7: =(COUNTIF(E7:AF7,"BH-D")*CONFIG!$B$11*AG7*(CONFIG!$B$46-1)+COUNTIF(E7:AF7,"BH-N")*CONFIG!$B$12*AG7*(CONFIG!$B$46-1)) -> 0 | AP7: =AH7/4 -> 42.875 | AQ7: =IF(AP7>48,"⚠️ >48hr WTR BREACH",IF(AP7>44,"🟡 HIGH","✅ OK")) -> ✅ OK
A8: Emma Brown | B8: Day A | C8: EL | D8: 1.5 | E8: EL | F8: EL | G8: OFF | H8: OFF | I8: EL | J8: EL | K8: EL | L8: OFF | M8: OFF | N8: EL | O8: EL | P8: OFF | Q8: OFF | R8: OFF | S8: EL | T8: EL | U8: OFF | V8: OFF | W8: EL | X8: EL | Y8: EL | Z8: OFF | AA8: OFF | AB8: EL | AC8: EL | AD8: OFF | AE8: OFF | AF8: OFF | AG8: 14 | AH8: =(COUNTIF(E8:AF8,"E")*CONFIG!$B$9+COUNTIF(E8:AF8,"L")*CONFIG!$B$10+COUNTIF(E8:AF8,"EL")*CONFIG!$B$11+COUNTIF(E8:AF8,"N")*CONFIG!$B$12+COUNTIF(E8:AF8,"OC-E")*CONFIG!$B$9+COUNTIF(E8:AF8,"OC-L")*CONFIG!$B$10+COUNTIF(E8:AF8,"OC-EL")*CONFIG!$B$11+COUNTIF(E8:AF8,"OC-N")*CONFIG!$B$12+COUNTIF(E8:AF8,"ADM")*CONFIG!$B$9+COUNTIF(E8:AF8,"TRN")*CONFIG!$B$9+COUNTIF(E8:AF8,"BH-D")*CONFIG!$B$11+COUNTIF(E8:AF8,"BH-N")*CONFIG!$B$12) -> 171.5 | AI8: =AH8*AG8 -> 2401 | AJ8: =(COUNTIF(E8:AF8,"OC-E")*CONFIG!$B$9+COUNTIF(E8:AF8,"OC-L")*CONFIG!$B$10+COUNTIF(E8:AF8,"OC-EL")*CONFIG!$B$11+COUNTIF(E8:AF8,"OC-N")*CONFIG!$B$12+COUNTIF(E8:AF8,"OT")*CONFIG!$B$9) -> 0 | AK8: =AJ8*CONFIG!$B$28 -> 0 | AL8: =(COUNTIF(E8:K8,"E")+COUNTIF(E8:K8,"L")+COUNTIF(E8:K8,"OC-E")+COUNTIF(E8:K8,"OC-L"))*6+(COUNTIF(E8:K8,"EL")+COUNTIF(E8:K8,"OC-EL")+COUNTIF(E8:K8,"BH-D"))*12.25+(COUNTIF(E8:K8,"N")+COUNTIF(E8:K8,"OC-N")+COUNTIF(E8:K8,"BH-N"))*12.25 -> 61.25 | AM8: =(COUNTIF(L8:R8,"E")+COUNTIF(L8:R8,"L")+COUNTIF(L8:R8,"OC-E")+COUNTIF(L8:R8,"OC-L"))*6+(COUNTIF(L8:R8,"EL")+COUNTIF(L8:R8,"OC-EL")+COUNTIF(L8:R8,"BH-D"))*12.25+(COUNTIF(L8:R8,"N")+COUNTIF(L8:R8,"OC-N")+COUNTIF(L8:R8,"BH-N"))*12.25 -> 24.5 | AN8: =IF(AL8<AM8,"Short W1",IF(AM8<AL8,"Short W2","Balanced")) -> Short W2 | AO8: =(COUNTIF(E8:AF8,"BH-D")*CONFIG!$B$11*AG8*(CONFIG!$B$46-1)+COUNTIF(E8:AF8,"BH-N")*CONFIG!$B$12*AG8*(CONFIG!$B$46-1)) -> 0 | AP8: =AH8/4 -> 42.875 | AQ8: =IF(AP8>48,"⚠️ >48hr WTR BREACH",IF(AP8>44,"🟡 HIGH","✅ OK")) -> ✅ OK
A9: Fiona Hart | B9: Day A | C9: EL | D9: 0.5 | E9: EL | F9: EL | G9: OFF | H9: OFF | I9: EL | J9: EL | K9: EL | L9: OFF | M9: OFF | N9: EL | O9: EL | P9: OFF | Q9: OFF | R9: OFF | S9: EL | T9: EL | U9: OFF | V9: OFF | W9: EL | X9: EL | Y9: EL | Z9: OFF | AA9: OFF | AB9: EL | AC9: EL | AD9: OFF | AE9: OFF | AF9: OFF | AG9: 11 | AH9: =(COUNTIF(E9:AF9,"E")*CONFIG!$B$9+COUNTIF(E9:AF9,"L")*CONFIG!$B$10+COUNTIF(E9:AF9,"EL")*CONFIG!$B$11+COUNTIF(E9:AF9,"N")*CONFIG!$B$12+COUNTIF(E9:AF9,"OC-E")*CONFIG!$B$9+COUNTIF(E9:AF9,"OC-L")*CONFIG!$B$10+COUNTIF(E9:AF9,"OC-EL")*CONFIG!$B$11+COUNTIF(E9:AF9,"OC-N")*CONFIG!$B$12+COUNTIF(E9:AF9,"ADM")*CONFIG!$B$9+COUNTIF(E9:AF9,"TRN")*CONFIG!$B$9+COUNTIF(E9:AF9,"BH-D")*CONFIG!$B$11+COUNTIF(E9:AF9,"BH-N")*CONFIG!$B$12) -> 171.5 | AI9: =AH9*AG9 -> 1886.5 | AJ9: =(COUNTIF(E9:AF9,"OC-E")*CONFIG!$B$9+COUNTIF(E9:AF9,"OC-L")*CONFIG!$B$10+COUNTIF(E9:AF9,"OC-EL")*CONFIG!$B$11+COUNTIF(E9:AF9,"OC-N")*CONFIG!$B$12+COUNTIF(E9:AF9,"OT")*CONFIG!$B$9) -> 0 | AK9: =AJ9*CONFIG!$B$28 -> 0 | AL9: =(COUNTIF(E9:K9,"E")+COUNTIF(E9:K9,"L")+COUNTIF(E9:K9,"OC-E")+COUNTIF(E9:K9,"OC-L"))*6+(COUNTIF(E9:K9,"EL")+COUNTIF(E9:K9,"OC-EL")+COUNTIF(E9:K9,"BH-D"))*12.25+(COUNTIF(E9:K9,"N")+COUNTIF(E9:K9,"OC-N")+COUNTIF(E9:K9,"BH-N"))*12.25 -> 61.25 | AM9: =(COUNTIF(L9:R9,"E")+COUNTIF(L9:R9,"L")+COUNTIF(L9:R9,"OC-E")+COUNTIF(L9:R9,"OC-L"))*6+(COUNTIF(L9:R9,"EL")+COUNTIF(L9:R9,"OC-EL")+COUNTIF(L9:R9,"BH-D"))*12.25+(COUNTIF(L9:R9,"N")+COUNTIF(L9:R9,"OC-N")+COUNTIF(L9:R9,"BH-N"))*12.25 -> 24.5 | AN9: =IF(AL9<AM9,"Short W1",IF(AM9<AL9,"Short W2","Balanced")) -> Short W2 | AO9: =(COUNTIF(E9:AF9,"BH-D")*CONFIG!$B$11*AG9*(CONFIG!$B$46-1)+COUNTIF(E9:AF9,"BH-N")*CONFIG!$B$12*AG9*(CONFIG!$B$46-1)) -> 0 | AP9: =AH9/4 -> 42.875 | AQ9: =IF(AP9>48,"⚠️ >48hr WTR BREACH",IF(AP9>44,"🟡 HIGH","✅ OK")) -> ✅ OK
A10: George King | B10: Day A | C10: EL | D10: 1 | E10: EL | F10: EL | G10: OFF | H10: OFF | I10: EL | J10: EL | K10: EL | L10: OFF | M10: OFF | N10: EL | O10: EL | P10: OFF | Q10: OFF | R10: OFF | S10: EL | T10: EL | U10: OFF | V10: OFF | W10: EL | X10: EL | Y10: EL | Z10: OFF | AA10: OFF | AB10: EL | AC10: EL | AD10: OFF | AE10: OFF | AF10: OFF | AG10: 12.5 | AH10: =(COUNTIF(E10:AF10,"E")*CONFIG!$B$9+COUNTIF(E10:AF10,"L")*CONFIG!$B$10+COUNTIF(E10:AF10,"EL")*CONFIG!$B$11+COUNTIF(E10:AF10,"N")*CONFIG!$B$12+COUNTIF(E10:AF10,"OC-E")*CONFIG!$B$9+COUNTIF(E10:AF10,"OC-L")*CONFIG!$B$10+COUNTIF(E10:AF10,"OC-EL")*CONFIG!$B$11+COUNTIF(E10:AF10,"OC-N")*CONFIG!$B$12+COUNTIF(E10:AF10,"ADM")*CONFIG!$B$9+COUNTIF(E10:AF10,"TRN")*CONFIG!$B$9+COUNTIF(E10:AF10,"BH-D")*CONFIG!$B$11+COUNTIF(E10:AF10,"BH-N")*CONFIG!$B$12) -> 171.5 | AI10: =AH10*AG10 -> 2143.75 | AJ10: =(COUNTIF(E10:AF10,"OC-E")*CONFIG!$B$9+COUNTIF(E10:AF10,"OC-L")*CONFIG!$B$10+COUNTIF(E10:AF10,"OC-EL")*CONFIG!$B$11+COUNTIF(E10:AF10,"OC-N")*CONFIG!$B$12+COUNTIF(E10:AF10,"OT")*CONFIG!$B$9) -> 0 | AK10: =AJ10*CONFIG!$B$28 -> 0 | AL10: =(COUNTIF(E10:K10,"E")+COUNTIF(E10:K10,"L")+COUNTIF(E10:K10,"OC-E")+COUNTIF(E10:K10,"OC-L"))*6+(COUNTIF(E10:K10,"EL")+COUNTIF(E10:K10,"OC-EL")+COUNTIF(E10:K10,"BH-D"))*12.25+(COUNTIF(E10:K10,"N")+COUNTIF(E10:K10,"OC-N")+COUNTIF(E10:K10,"BH-N"))*12.25 -> 61.25 | AM10: =(COUNTIF(L10:R10,"E")+COUNTIF(L10:R10,"L")+COUNTIF(L10:R10,"OC-E")+COUNTIF(L10:R10,"OC-L"))*6+(COUNTIF(L10:R10,"EL")+COUNTIF(L10:R10,"OC-EL")+COUNTIF(L10:R10,"BH-D"))*12.25+(COUNTIF(L10:R10,"N")+COUNTIF(L10:R10,"OC-N")+COUNTIF(L10:R10,"BH-N"))*12.25 -> 24.5 | AN10: =IF(AL10<AM10,"Short W1",IF(AM10<AL10,"Short W2","Balanced")) -> Short W2 | AO10: =(COUNTIF(E10:AF10,"BH-D")*CONFIG!$B$11*AG10*(CONFIG!$B$46-1)+COUNTIF(E10:AF10,"BH-N")*CONFIG!$B$12*AG10*(CONFIG!$B$46-1)) -> 0 | AP10: =AH10/4 -> 42.875 | AQ10: =IF(AP10>48,"⚠️ >48hr WTR BREACH",IF(AP10>44,"🟡 HIGH","✅ OK")) -> ✅ OK
A11: Hannah Lee | B11: Day B | C11: EL | D11: 1 | E11: OFF | F11: OFF | G11: EL | H11: EL | I11: OFF | J11: OFF | K11: OFF | L11: EL | M11: EL | N11: OFF | O11: OFF | P11: EL | Q11: EL | R11: EL | S11: OFF | T11: OFF | U11: EL | V11: EL | W11: OFF | X11: OFF | Y11: OFF | Z11: EL | AA11: EL | AB11: OFF | AC11: OFF | AD11: EL | AE11: EL | AF11: EL | AG11: 12.5 | AH11: =(COUNTIF(E11:AF11,"E")*CONFIG!$B$9+COUNTIF(E11:AF11,"L")*CONFIG!$B$10+COUNTIF(E11:AF11,"EL")*CONFIG!$B$11+COUNTIF(E11:AF11,"N")*CONFIG!$B$12+COUNTIF(E11:AF11,"OC-E")*CONFIG!$B$9+COUNTIF(E11:AF11,"OC-L")*CONFIG!$B$10+COUNTIF(E11:AF11,"OC-EL")*CONFIG!$B$11+COUNTIF(E11:AF11,"OC-N")*CONFIG!$B$12+COUNTIF(E11:AF11,"ADM")*CONFIG!$B$9+COUNTIF(E11:AF11,"TRN")*CONFIG!$B$9+COUNTIF(E11:AF11,"BH-D")*CONFIG!$B$11+COUNTIF(E11:AF11,"BH-N")*CONFIG!$B$12) -> 171.5 | AI11: =AH11*AG11 -> 2143.75 | AJ11: =(COUNTIF(E11:AF11,"OC-E")*CONFIG!$B$9+COUNTIF(E11:AF11,"OC-L")*CONFIG!$B$10+COUNTIF(E11:AF11,"OC-EL")*CONFIG!$B$11+COUNTIF(E11:AF11,"OC-N")*CONFIG!$B$12+COUNTIF(E11:AF11,"OT")*CONFIG!$B$9) -> 0 | AK11: =AJ11*CONFIG!$B$28 -> 0 | AL11: =(COUNTIF(E11:K11,"E")+COUNTIF(E11:K11,"L")+COUNTIF(E11:K11,"OC-E")+COUNTIF(E11:K11,"OC-L"))*6+(COUNTIF(E11:K11,"EL")+COUNTIF(E11:K11,"OC-EL")+COUNTIF(E11:K11,"BH-D"))*12.25+(COUNTIF(E11:K11,"N")+COUNTIF(E11:K11,"OC-N")+COUNTIF(E11:K11,"BH-N"))*12.25 -> 24.5 | AM11: =(COUNTIF(L11:R11,"E")+COUNTIF(L11:R11,"L")+COUNTIF(L11:R11,"OC-E")+COUNTIF(L11:R11,"OC-L"))*6+(COUNTIF(L11:R11,"EL")+COUNTIF(L11:R11,"OC-EL")+COUNTIF(L11:R11,"BH-D"))*12.25+(COUNTIF(L11:R11,"N")+COUNTIF(L11:R11,"OC-N")+COUNTIF(L11:R11,"BH-N"))*12.25 -> 61.25 | AN11: =IF(AL11<AM11,"Short W1",IF(AM11<AL11,"Short W2","Balanced")) -> Short W1 | AO11: =(COUNTIF(E11:AF11,"BH-D")*CONFIG!$B$11*AG11*(CONFIG!$B$46-1)+COUNTIF(E11:AF11,"BH-N")*CONFIG!$B$12*AG11*(CONFIG!$B$46-1)) -> 0 | AP11: =AH11/4 -> 42.875 | AQ11: =IF(AP11>48,"⚠️ >48hr WTR BREACH",IF(AP11>44,"🟡 HIGH","✅ OK")) -> ✅ OK
A12: Ian Clark | B12: Day B | C12: EL | D12: 0.5 | E12: OFF | F12: OFF | G12: EL | H12: EL | I12: OFF | J12: OFF | K12: OFF | L12: EL | M12: EL | N12: OFF | O12: OFF | P12: EL | Q12: EL | R12: EL | S12: OFF | T12: OFF | U12: EL | V12: EL | W12: OFF | X12: OFF | Y12: OFF | Z12: EL | AA12: EL | AB12: OFF | AC12: OFF | AD12: EL | AE12: EL | AF12: EL | AG12: 11 | AH12: =(COUNTIF(E12:AF12,"E")*CONFIG!$B$9+COUNTIF(E12:AF12,"L")*CONFIG!$B$10+COUNTIF(E12:AF12,"EL")*CONFIG!$B$11+COUNTIF(E12:AF12,"N")*CONFIG!$B$12+COUNTIF(E12:AF12,"OC-E")*CONFIG!$B$9+COUNTIF(E12:AF12,"OC-L")*CONFIG!$B$10+COUNTIF(E12:AF12,"OC-EL")*CONFIG!$B$11+COUNTIF(E12:AF12,"OC-N")*CONFIG!$B$12+COUNTIF(E12:AF12,"ADM")*CONFIG!$B$9+COUNTIF(E12:AF12,"TRN")*CONFIG!$B$9+COUNTIF(E12:AF12,"BH-D")*CONFIG!$B$11+COUNTIF(E12:AF12,"BH-N")*CONFIG!$B$12) -> 171.5 | AI12: =AH12*AG12 -> 1886.5 | AJ12: =(COUNTIF(E12:AF12,"OC-E")*CONFIG!$B$9+COUNTIF(E12:AF12,"OC-L")*CONFIG!$B$10+COUNTIF(E12:AF12,"OC-EL")*CONFIG!$B$11+COUNTIF(E12:AF12,"OC-N")*CONFIG!$B$12+COUNTIF(E12:AF12,"OT")*CONFIG!$B$9) -> 0 | AK12: =AJ12*CONFIG!$B$28 -> 0 | AL12: =(COUNTIF(E12:K12,"E")+COUNTIF(E12:K12,"L")+COUNTIF(E12:K12,"OC-E")+COUNTIF(E12:K12,"OC-L"))*6+(COUNTIF(E12:K12,"EL")+COUNTIF(E12:K12,"OC-EL")+COUNTIF(E12:K12,"BH-D"))*12.25+(COUNTIF(E12:K12,"N")+COUNTIF(E12:K12,"OC-N")+COUNTIF(E12:K12,"BH-N"))*12.25 -> 24.5 | AM12: =(COUNTIF(L12:R12,"E")+COUNTIF(L12:R12,"L")+COUNTIF(L12:R12,"OC-E")+COUNTIF(L12:R12,"OC-L"))*6+(COUNTIF(L12:R12,"EL")+COUNTIF(L12:R12,"OC-EL")+COUNTIF(L12:R12,"BH-D"))*12.25+(COUNTIF(L12:R12,"N")+COUNTIF(L12:R12,"OC-N")+COUNTIF(L12:R12,"BH-N"))*12.25 -> 61.25 | AN12: =IF(AL12<AM12,"Short W1",IF(AM12<AL12,"Short W2","Balanced")) -> Short W1 | AO12: =(COUNTIF(E12:AF12,"BH-D")*CONFIG!$B$11*AG12*(CONFIG!$B$46-1)+COUNTIF(E12:AF12,"BH-N")*CONFIG!$B$12*AG12*(CONFIG!$B$46-1)) -> 0 | AP12: =AH12/4 -> 42.875 | AQ12: =IF(AP12>48,"⚠️ >48hr WTR BREACH",IF(AP12>44,"🟡 HIGH","✅ OK")) -> ✅ OK
A13: Julia Martin | B13: Day B | C13: EL | D13: 1 | E13: OFF | F13: OFF | G13: EL | H13: EL | I13: OFF | J13: OFF | K13: OFF | L13: EL | M13: EL | N13: OFF | O13: OFF | P13: EL | Q13: EL | R13: EL | S13: OFF | T13: OFF | U13: EL | V13: EL | W13: OFF | X13: OFF | Y13: OFF | Z13: EL | AA13: EL | AB13: OFF | AC13: OFF | AD13: EL | AE13: EL | AF13: EL | AG13: 12.5 | AH13: =(COUNTIF(E13:AF13,"E")*CONFIG!$B$9+COUNTIF(E13:AF13,"L")*CONFIG!$B$10+COUNTIF(E13:AF13,"EL")*CONFIG!$B$11+COUNTIF(E13:AF13,"N")*CONFIG!$B$12+COUNTIF(E13:AF13,"OC-E")*CONFIG!$B$9+COUNTIF(E13:AF13,"OC-L")*CONFIG!$B$10+COUNTIF(E13:AF13,"OC-EL")*CONFIG!$B$11+COUNTIF(E13:AF13,"OC-N")*CONFIG!$B$12+COUNTIF(E13:AF13,"ADM")*CONFIG!$B$9+COUNTIF(E13:AF13,"TRN")*CONFIG!$B$9+COUNTIF(E13:AF13,"BH-D")*CONFIG!$B$11+COUNTIF(E13:AF13,"BH-N")*CONFIG!$B$12) -> 171.5 | AI13: =AH13*AG13 -> 2143.75 | AJ13: =(COUNTIF(E13:AF13,"OC-E")*CONFIG!$B$9+COUNTIF(E13:AF13,"OC-L")*CONFIG!$B$10+COUNTIF(E13:AF13,"OC-EL")*CONFIG!$B$11+COUNTIF(E13:AF13,"OC-N")*CONFIG!$B$12+COUNTIF(E13:AF13,"OT")*CONFIG!$B$9) -> 0 | AK13: =AJ13*CONFIG!$B$28 -> 0 | AL13: =(COUNTIF(E13:K13,"E")+COUNTIF(E13:K13,"L")+COUNTIF(E13:K13,"OC-E")+COUNTIF(E13:K13,"OC-L"))*6+(COUNTIF(E13:K13,"EL")+COUNTIF(E13:K13,"OC-EL")+COUNTIF(E13:K13,"BH-D"))*12.25+(COUNTIF(E13:K13,"N")+COUNTIF(E13:K13,"OC-N")+COUNTIF(E13:K13,"BH-N"))*12.25 -> 24.5 | AM13: =(COUNTIF(L13:R13,"E")+COUNTIF(L13:R13,"L")+COUNTIF(L13:R13,"OC-E")+COUNTIF(L13:R13,"OC-L"))*6+(COUNTIF(L13:R13,"EL")+COUNTIF(L13:R13,"OC-EL")+COUNTIF(L13:R13,"BH-D"))*12.25+(COUNTIF(L13:R13,"N")+COUNTIF(L13:R13,"OC-N")+COUNTIF(L13:R13,"BH-N"))*12.25 -> 61.25 | AN13: =IF(AL13<AM13,"Short W1",IF(AM13<AL13,"Short W2","Balanced")) -> Short W1 | AO13: =(COUNTIF(E13:AF13,"BH-D")*CONFIG!$B$11*AG13*(CONFIG!$B$46-1)+COUNTIF(E13:AF13,"BH-N")*CONFIG!$B$12*AG13*(CONFIG!$B$46-1)) -> 0 | AP13: =AH13/4 -> 42.875 | AQ13: =IF(AP13>48,"⚠️ >48hr WTR BREACH",IF(AP13>44,"🟡 HIGH","✅ OK")) -> ✅ OK
A14: Kevin White | B14: Day B | C14: EL | D14: 0.5 | E14: OFF | F14: OFF | G14: EL | H14: EL | I14: OFF | J14: OFF | K14: OFF | L14: EL | M14: EL | N14: OFF | O14: OFF | P14: EL | Q14: EL | R14: EL | S14: OFF | T14: OFF | U14: EL | V14: EL | W14: OFF | X14: OFF | Y14: OFF | Z14: EL | AA14: EL | AB14: OFF | AC14: OFF | AD14: EL | AE14: EL | AF14: EL | AG14: 11 | AH14: =(COUNTIF(E14:AF14,"E")*CONFIG!$B$9+COUNTIF(E14:AF14,"L")*CONFIG!$B$10+COUNTIF(E14:AF14,"EL")*CONFIG!$B$11+COUNTIF(E14:AF14,"N")*CONFIG!$B$12+COUNTIF(E14:AF14,"OC-E")*CONFIG!$B$9+COUNTIF(E14:AF14,"OC-L")*CONFIG!$B$10+COUNTIF(E14:AF14,"OC-EL")*CONFIG!$B$11+COUNTIF(E14:AF14,"OC-N")*CONFIG!$B$12+COUNTIF(E14:AF14,"ADM")*CONFIG!$B$9+COUNTIF(E14:AF14,"TRN")*CONFIG!$B$9+COUNTIF(E14:AF14,"BH-D")*CONFIG!$B$11+COUNTIF(E14:AF14,"BH-N")*CONFIG!$B$12) -> 171.5 | AI14: =AH14*AG14 -> 1886.5 | AJ14: =(COUNTIF(E14:AF14,"OC-E")*CONFIG!$B$9+COUNTIF(E14:AF14,"OC-L")*CONFIG!$B$10+COUNTIF(E14:AF14,"OC-EL")*CONFIG!$B$11+COUNTIF(E14:AF14,"OC-N")*CONFIG!$B$12+COUNTIF(E14:AF14,"OT")*CONFIG!$B$9) -> 0 | AK14: =AJ14*CONFIG!$B$28 -> 0 | AL14: =(COUNTIF(E14:K14,"E")+COUNTIF(E14:K14,"L")+COUNTIF(E14:K14,"OC-E")+COUNTIF(E14:K14,"OC-L"))*6+(COUNTIF(E14:K14,"EL")+COUNTIF(E14:K14,"OC-EL")+COUNTIF(E14:K14,"BH-D"))*12.25+(COUNTIF(E14:K14,"N")+COUNTIF(E14:K14,"OC-N")+COUNTIF(E14:K14,"BH-N"))*12.25 -> 24.5 | AM14: =(COUNTIF(L14:R14,"E")+COUNTIF(L14:R14,"L")+COUNTIF(L14:R14,"OC-E")+COUNTIF(L14:R14,"OC-L"))*6+(COUNTIF(L14:R14,"EL")+COUNTIF(L14:R14,"OC-EL")+COUNTIF(L14:R14,"BH-D"))*12.25+(COUNTIF(L14:R14,"N")+COUNTIF(L14:R14,"OC-N")+COUNTIF(L14:R14,"BH-N"))*12.25 -> 61.25 | AN14: =IF(AL14<AM14,"Short W1",IF(AM14<AL14,"Short W2","Balanced")) -> Short W1 | AO14: =(COUNTIF(E14:AF14,"BH-D")*CONFIG!$B$11*AG14*(CONFIG!$B$46-1)+COUNTIF(E14:AF14,"BH-N")*CONFIG!$B$12*AG14*(CONFIG!$B$46-1)) -> 0 | AP14: =AH14/4 -> 42.875 | AQ14: =IF(AP14>48,"⚠️ >48hr WTR BREACH",IF(AP14>44,"🟡 HIGH","✅ OK")) -> ✅ OK
A15: Laura Adams | B15: Day B | C15: EL | D15: 1.5 | E15: OFF | F15: OFF | G15: EL | H15: EL | I15: OFF | J15: OFF | K15: OFF | L15: EL | M15: EL | N15: OFF | O15: OFF | P15: EL | Q15: EL | R15: EL | S15: OFF | T15: OFF | U15: EL | V15: EL | W15: OFF | X15: OFF | Y15: OFF | Z15: EL | AA15: EL | AB15: OFF | AC15: OFF | AD15: EL | AE15: EL | AF15: EL | AG15: 14 | AH15: =(COUNTIF(E15:AF15,"E")*CONFIG!$B$9+COUNTIF(E15:AF15,"L")*CONFIG!$B$10+COUNTIF(E15:AF15,"EL")*CONFIG!$B$11+COUNTIF(E15:AF15,"N")*CONFIG!$B$12+COUNTIF(E15:AF15,"OC-E")*CONFIG!$B$9+COUNTIF(E15:AF15,"OC-L")*CONFIG!$B$10+COUNTIF(E15:AF15,"OC-EL")*CONFIG!$B$11+COUNTIF(E15:AF15,"OC-N")*CONFIG!$B$12+COUNTIF(E15:AF15,"ADM")*CONFIG!$B$9+COUNTIF(E15:AF15,"TRN")*CONFIG!$B$9+COUNTIF(E15:AF15,"BH-D")*CONFIG!$B$11+COUNTIF(E15:AF15,"BH-N")*CONFIG!$B$12) -> 171.5 | AI15: =AH15*AG15 -> 2401 | AJ15: =(COUNTIF(E15:AF15,"OC-E")*CONFIG!$B$9+COUNTIF(E15:AF15,"OC-L")*CONFIG!$B$10+COUNTIF(E15:AF15,"OC-EL")*CONFIG!$B$11+COUNTIF(E15:AF15,"OC-N")*CONFIG!$B$12+COUNTIF(E15:AF15,"OT")*CONFIG!$B$9) -> 0 | AK15: =AJ15*CONFIG!$B$28 -> 0 | AL15: =(COUNTIF(E15:K15,"E")+COUNTIF(E15:K15,"L")+COUNTIF(E15:K15,"OC-E")+COUNTIF(E15:K15,"OC-L"))*6+(COUNTIF(E15:K15,"EL")+COUNTIF(E15:K15,"OC-EL")+COUNTIF(E15:K15,"BH-D"))*12.25+(COUNTIF(E15:K15,"N")+COUNTIF(E15:K15,"OC-N")+COUNTIF(E15:K15,"BH-N"))*12.25 -> 24.5 | AM15: =(COUNTIF(L15:R15,"E")+COUNTIF(L15:R15,"L")+COUNTIF(L15:R15,"OC-E")+COUNTIF(L15:R15,"OC-L"))*6+(COUNTIF(L15:R15,"EL")+COUNTIF(L15:R15,"OC-EL")+COUNTIF(L15:R15,"BH-D"))*12.25+(COUNTIF(L15:R15,"N")+COUNTIF(L15:R15,"OC-N")+COUNTIF(L15:R15,"BH-N"))*12.25 -> 61.25 | AN15: =IF(AL15<AM15,"Short W1",IF(AM15<AL15,"Short W2","Balanced")) -> Short W1 | AO15: =(COUNTIF(E15:AF15,"BH-D")*CONFIG!$B$11*AG15*(CONFIG!$B$46-1)+COUNTIF(E15:AF15,"BH-N")*CONFIG!$B$12*AG15*(CONFIG!$B$46-1)) -> 0 | AP15: =AH15/4 -> 42.875 | AQ15: =IF(AP15>48,"⚠️ >48hr WTR BREACH",IF(AP15>44,"🟡 HIGH","✅ OK")) -> ✅ OK
... A28: Yasmin Reed | B28: Day B | C28: L | D28: 1 | E28: OFF | F28: OFF | G28: L | H28: L | I28: OFF | J28: OFF | K28: OFF | L28: L | M28: L | N28: OFF | O28: OFF | P28: L | Q28: L | R28: L | S28: OFF | T28: OFF | U28: L | V28: L | W28: OFF | X28: OFF | Y28: OFF | Z28: L | AA28: L | AB28: OFF | AC28: OFF | AD28: L | AE28: L | AF28: L | AG28: 12 | AH28: =(COUNTIF(E28:AF28,"E")*CONFIG!$B$9+COUNTIF(E28:AF28,"L")*CONFIG!$B$10+COUNTIF(E28:AF28,"EL")*CONFIG!$B$11+COUNTIF(E28:AF28,"N")*CONFIG!$B$12+COUNTIF(E28:AF28,"OC-E")*CONFIG!$B$9+COUNTIF(E28:AF28,"OC-L")*CONFIG!$B$10+COUNTIF(E28:AF28,"OC-EL")*CONFIG!$B$11+COUNTIF(E28:AF28,"OC-N")*CONFIG!$B$12+COUNTIF(E28:AF28,"ADM")*CONFIG!$B$9+COUNTIF(E28:AF28,"TRN")*CONFIG!$B$9+COUNTIF(E28:AF28,"BH-D")*CONFIG!$B$11+COUNTIF(E28:AF28,"BH-N")*CONFIG!$B$12) -> 84 | AI28: =AH28*AG28 -> 1008 | AJ28: =(COUNTIF(E28:AF28,"OC-E")*CONFIG!$B$9+COUNTIF(E28:AF28,"OC-L")*CONFIG!$B$10+COUNTIF(E28:AF28,"OC-EL")*CONFIG!$B$11+COUNTIF(E28:AF28,"OC-N")*CONFIG!$B$12+COUNTIF(E28:AF28,"OT")*CONFIG!$B$9) -> 0 | AK28: =AJ28*CONFIG!$B$28 -> 0 | AL28: =(COUNTIF(E28:K28,"E")+COUNTIF(E28:K28,"L")+COUNTIF(E28:K28,"OC-E")+COUNTIF(E28:K28,"OC-L"))*6+(COUNTIF(E28:K28,"EL")+COUNTIF(E28:K28,"OC-EL")+COUNTIF(E28:K28,"BH-D"))*12.25+(COUNTIF(E28:K28,"N")+COUNTIF(E28:K28,"OC-N")+COUNTIF(E28:K28,"BH-N"))*12.25 -> 12 | AM28: =(COUNTIF(L28:R28,"E")+COUNTIF(L28:R28,"L")+COUNTIF(L28:R28,"OC-E")+COUNTIF(L28:R28,"OC-L"))*6+(COUNTIF(L28:R28,"EL")+COUNTIF(L28:R28,"OC-EL")+COUNTIF(L28:R28,"BH-D"))*12.25+(COUNTIF(L28:R28,"N")+COUNTIF(L28:R28,"OC-N")+COUNTIF(L28:R28,"BH-N"))*12.25 -> 30 | AN28: =IF(AL28<AM28,"Short W1",IF(AM28<AL28,"Short W2","Balanced")) -> Short W1 | AO28: =(COUNTIF(E28:AF28,"BH-D")*CONFIG!$B$11*AG28*(CONFIG!$B$46-1)+COUNTIF(E28:AF28,"BH-N")*CONFIG!$B$12*AG28*(CONFIG!$B$46-1)) -> 0 | AP28: =AH28/4 -> 21 | AQ28: =IF(AP28>48,"⚠️ >48hr WTR BREACH",IF(AP28>44,"🟡 HIGH","✅ OK")) -> ✅ OK
A52: COVERAGE VALIDATION
A53: Early Count | E53: =COUNTIF(E$4:E$50,"E")+COUNTIF(E$4:E$50,"EL")+COUNTIF(E$4:E$50,"OC-E")+COUNTIF(E$4:E$50,"OC-EL")+COUNTIF(E$4:E$50,"BH-D")+COUNTIF(E$4:E$50,"AG-E") -> 8 | F53: =COUNTIF(F$4:F$50,"E")+COUNTIF(F$4:F$50,"EL")+COUNTIF(F$4:F$50,"OC-E")+COUNTIF(F$4:F$50,"OC-EL")+COUNTIF(F$4:F$50,"BH-D")+COUNTIF(F$4:F$50,"AG-E") -> 8 | G53: =COUNTIF(G$4:G$50,"E")+COUNTIF(G$4:G$50,"EL")+COUNTIF(G$4:G$50,"OC-E")+COUNTIF(G$4:G$50,"OC-EL")+COUNTIF(G$4:G$50,"BH-D")+COUNTIF(G$4:G$50,"AG-E") -> 7 | H53: =COUNTIF(H$4:H$50,"E")+COUNTIF(H$4:H$50,"EL")+COUNTIF(H$4:H$50,"OC-E")+COUNTIF(H$4:H$50,"OC-EL")+COUNTIF(H$4:H$50,"BH-D")+COUNTIF(H$4:H$50,"AG-E") -> 7 | I53: =COUNTIF(I$4:I$50,"E")+COUNTIF(I$4:I$50,"EL")+COUNTIF(I$4:I$50,"OC-E")+COUNTIF(I$4:I$50,"OC-EL")+COUNTIF(I$4:I$50,"BH-D")+COUNTIF(I$4:I$50,"AG-E") -> 8 | J53: =COUNTIF(J$4:J$50,"E")+COUNTIF(J$4:J$50,"EL")+COUNTIF(J$4:J$50,"OC-E")+COUNTIF(J$4:J$50,"OC-EL")+COUNTIF(J$4:J$50,"BH-D")+COUNTIF(J$4:J$50,"AG-E") -> 8 | K53: =COUNTIF(K$4:K$50,"E")+COUNTIF(K$4:K$50,"EL")+COUNTIF(K$4:K$50,"OC-E")+COUNTIF(K$4:K$50,"OC-EL")+COUNTIF(K$4:K$50,"BH-D")+COUNTIF(K$4:K$50,"AG-E") -> 8 | L53: =COUNTIF(L$4:L$50,"E")+COUNTIF(L$4:L$50,"EL")+COUNTIF(L$4:L$50,"OC-E")+COUNTIF(L$4:L$50,"OC-EL")+COUNTIF(L$4:L$50,"BH-D")+COUNTIF(L$4:L$50,"AG-E") -> 7 | ... AF53: =COUNTIF(AF$4:AF$50,"E")+COUNTIF(AF$4:AF$50,"EL")+COUNTIF(AF$4:AF$50,"OC-E")+COUNTIF(AF$4:AF$50,"OC-EL")+COUNTIF(AF$4:AF$50,"BH-D")+COUNTIF(AF$4:AF$50,"AG-E") -> 7
A54: Early Skill ⚡ | E54: =SUMPRODUCT(((E$4:E$50="E")+(E$4:E$50="EL")+(E$4:E$50="OC-E")+(E$4:E$50="OC-EL")+(E$4:E$50="BH-D"))*$D$4:$D$50)+COUNTIF(E$4:E$50,"AG-E")*1 -> 6.5 | F54: =SUMPRODUCT(((F$4:F$50="E")+(F$4:F$50="EL")+(F$4:F$50="OC-E")+(F$4:F$50="OC-EL")+(F$4:F$50="BH-D"))*$D$4:$D$50)+COUNTIF(F$4:F$50,"AG-E")*1 -> 6.5 | G54: =SUMPRODUCT(((G$4:G$50="E")+(G$4:G$50="EL")+(G$4:G$50="OC-E")+(G$4:G$50="OC-EL")+(G$4:G$50="BH-D"))*$D$4:$D$50)+COUNTIF(G$4:G$50,"AG-E")*1 -> 6 | H54: =SUMPRODUCT(((H$4:H$50="E")+(H$4:H$50="EL")+(H$4:H$50="OC-E")+(H$4:H$50="OC-EL")+(H$4:H$50="BH-D"))*$D$4:$D$50)+COUNTIF(H$4:H$50,"AG-E")*1 -> 6 | I54: =SUMPRODUCT(((I$4:I$50="E")+(I$4:I$50="EL")+(I$4:I$50="OC-E")+(I$4:I$50="OC-EL")+(I$4:I$50="BH-D"))*$D$4:$D$50)+COUNTIF(I$4:I$50,"AG-E")*1 -> 6.5 | J54: =SUMPRODUCT(((J$4:J$50="E")+(J$4:J$50="EL")+(J$4:J$50="OC-E")+(J$4:J$50="OC-EL")+(J$4:J$50="BH-D"))*$D$4:$D$50)+COUNTIF(J$4:J$50,"AG-E")*1 -> 6.5 | K54: =SUMPRODUCT(((K$4:K$50="E")+(K$4:K$50="EL")+(K$4:K$50="OC-E")+(K$4:K$50="OC-EL")+(K$4:K$50="BH-D"))*$D$4:$D$50)+COUNTIF(K$4:K$50,"AG-E")*1 -> 6.5 | L54: =SUMPRODUCT(((L$4:L$50="E")+(L$4:L$50="EL")+(L$4:L$50="OC-E")+(L$4:L$50="OC-EL")+(L$4:L$50="BH-D"))*$D$4:$D$50)+COUNTIF(L$4:L$50,"AG-E")*1 -> 6 | ... AF54: =SUMPRODUCT(((AF$4:AF$50="E")+(AF$4:AF$50="EL")+(AF$4:AF$50="OC-E")+(AF$4:AF$50="OC-EL")+(AF$4:AF$50="BH-D"))*$D$4:$D$50)+COUNTIF(AF$4:AF$50,"AG-E")*1 -> 6
A55: Late Count | E55: =COUNTIF(E$4:E$50,"L")+COUNTIF(E$4:E$50,"EL")+COUNTIF(E$4:E$50,"OC-L")+COUNTIF(E$4:E$50,"OC-EL")+COUNTIF(E$4:E$50,"BH-D")+COUNTIF(E$4:E$50,"AG-L") -> 7 | F55: =COUNTIF(F$4:F$50,"L")+COUNTIF(F$4:F$50,"EL")+COUNTIF(F$4:F$50,"OC-L")+COUNTIF(F$4:F$50,"OC-EL")+COUNTIF(F$4:F$50,"BH-D")+COUNTIF(F$4:F$50,"AG-L") -> 7 | G55: =COUNTIF(G$4:G$50,"L")+COUNTIF(G$4:G$50,"EL")+COUNTIF(G$4:G$50,"OC-L")+COUNTIF(G$4:G$50,"OC-EL")+COUNTIF(G$4:G$50,"BH-D")+COUNTIF(G$4:G$50,"AG-L") -> 8 | H55: =COUNTIF(H$4:H$50,"L")+COUNTIF(H$4:H$50,"EL")+COUNTIF(H$4:H$50,"OC-L")+COUNTIF(H$4:H$50,"OC-EL")+COUNTIF(H$4:H$50,"BH-D")+COUNTIF(H$4:H$50,"AG-L") -> 8 | I55: =COUNTIF(I$4:I$50,"L")+COUNTIF(I$4:I$50,"EL")+COUNTIF(I$4:I$50,"OC-L")+COUNTIF(I$4:I$50,"OC-EL")+COUNTIF(I$4:I$50,"BH-D")+COUNTIF(I$4:I$50,"AG-L") -> 7 | J55: =COUNTIF(J$4:J$50,"L")+COUNTIF(J$4:J$50,"EL")+COUNTIF(J$4:J$50,"OC-L")+COUNTIF(J$4:J$50,"OC-EL")+COUNTIF(J$4:J$50,"BH-D")+COUNTIF(J$4:J$50,"AG-L") -> 7 | K55: =COUNTIF(K$4:K$50,"L")+COUNTIF(K$4:K$50,"EL")+COUNTIF(K$4:K$50,"OC-L")+COUNTIF(K$4:K$50,"OC-EL")+COUNTIF(K$4:K$50,"BH-D")+COUNTIF(K$4:K$50,"AG-L") -> 7 | L55: =COUNTIF(L$4:L$50,"L")+COUNTIF(L$4:L$50,"EL")+COUNTIF(L$4:L$50,"OC-L")+COUNTIF(L$4:L$50,"OC-EL")+COUNTIF(L$4:L$50,"BH-D")+COUNTIF(L$4:L$50,"AG-L") -> 8 | ... AF55: =COUNTIF(AF$4:AF$50,"L")+COUNTIF(AF$4:AF$50,"EL")+COUNTIF(AF$4:AF$50,"OC-L")+COUNTIF(AF$4:AF$50,"OC-EL")+COUNTIF(AF$4:AF$50,"BH-D")+COUNTIF(AF$4:AF$50,"AG-L") -> 8
A56: Late Skill ⚡ | E56: =SUMPRODUCT(((E$4:E$50="L")+(E$4:E$50="EL")+(E$4:E$50="OC-L")+(E$4:E$50="OC-EL")+(E$4:E$50="BH-D"))*$D$4:$D$50)+COUNTIF(E$4:E$50,"AG-L")*1 -> 6 | F56: =SUMPRODUCT(((F$4:F$50="L")+(F$4:F$50="EL")+(F$4:F$50="OC-L")+(F$4:F$50="OC-EL")+(F$4:F$50="BH-D"))*$D$4:$D$50)+COUNTIF(F$4:F$50,"AG-L")*1 -> 6 | G56: =SUMPRODUCT(((G$4:G$50="L")+(G$4:G$50="EL")+(G$4:G$50="OC-L")+(G$4:G$50="OC-EL")+(G$4:G$50="BH-D"))*$D$4:$D$50)+COUNTIF(G$4:G$50,"AG-L")*1 -> 7 | H56: =SUMPRODUCT(((H$4:H$50="L")+(H$4:H$50="EL")+(H$4:H$50="OC-L")+(H$4:H$50="OC-EL")+(H$4:H$50="BH-D"))*$D$4:$D$50)+COUNTIF(H$4:H$50,"AG-L")*1 -> 7 | I56: =SUMPRODUCT(((I$4:I$50="L")+(I$4:I$50="EL")+(I$4:I$50="OC-L")+(I$4:I$50="OC-EL")+(I$4:I$50="BH-D"))*$D$4:$D$50)+COUNTIF(I$4:I$50,"AG-L")*1 -> 6 | J56: =SUMPRODUCT(((J$4:J$50="L")+(J$4:J$50="EL")+(J$4:J$50="OC-L")+(J$4:J$50="OC-EL")+(J$4:J$50="BH-D"))*$D$4:$D$50)+COUNTIF(J$4:J$50,"AG-L")*1 -> 6 | K56: =SUMPRODUCT(((K$4:K$50="L")+(K$4:K$50="EL")+(K$4:K$50="OC-L")+(K$4:K$50="OC-EL")+(K$4:K$50="BH-D"))*$D$4:$D$50)+COUNTIF(K$4:K$50,"AG-L")*1 -> 6 | L56: =SUMPRODUCT(((L$4:L$50="L")+(L$4:L$50="EL")+(L$4:L$50="OC-L")+(L$4:L$50="OC-EL")+(L$4:L$50="BH-D"))*$D$4:$D$50)+COUNTIF(L$4:L$50,"AG-L")*1 -> 7 | ... AF56: =SUMPRODUCT(((AF$4:AF$50="L")+(AF$4:AF$50="EL")+(AF$4:AF$50="OC-L")+(AF$4:AF$50="OC-EL")+(AF$4:AF$50="BH-D"))*$D$4:$D$50)+COUNTIF(AF$4:AF$50,"AG-L")*1 -> 7
A57: Night Count | E57: =COUNTIF(E$4:E$50,"N")+COUNTIF(E$4:E$50,"OC-N")+COUNTIF(E$4:E$50,"BH-N")+COUNTIF(E$4:E$50,"AG-N") -> 3 | F57: =COUNTIF(F$4:F$50,"N")+COUNTIF(F$4:F$50,"OC-N")+COUNTIF(F$4:F$50,"BH-N")+COUNTIF(F$4:F$50,"AG-N") -> 3 | G57: =COUNTIF(G$4:G$50,"N")+COUNTIF(G$4:G$50,"OC-N")+COUNTIF(G$4:G$50,"BH-N")+COUNTIF(G$4:G$50,"AG-N") -> 3 | H57: =COUNTIF(H$4:H$50,"N")+COUNTIF(H$4:H$50,"OC-N")+COUNTIF(H$4:H$50,"BH-N")+COUNTIF(H$4:H$50,"AG-N") -> 3 | I57: =COUNTIF(I$4:I$50,"N")+COUNTIF(I$4:I$50,"OC-N")+COUNTIF(I$4:I$50,"BH-N")+COUNTIF(I$4:I$50,"AG-N") -> 3 | J57: =COUNTIF(J$4:J$50,"N")+COUNTIF(J$4:J$50,"OC-N")+COUNTIF(J$4:J$50,"BH-N")+COUNTIF(J$4:J$50,"AG-N") -> 3 | K57: =COUNTIF(K$4:K$50,"N")+COUNTIF(K$4:K$50,"OC-N")+COUNTIF(K$4:K$50,"BH-N")+COUNTIF(K$4:K$50,"AG-N") -> 3 | L57: =COUNTIF(L$4:L$50,"N")+COUNTIF(L$4:L$50,"OC-N")+COUNTIF(L$4:L$50,"BH-N")+COUNTIF(L$4:L$50,"AG-N") -> 3 | ... AF57: =COUNTIF(AF$4:AF$50,"N")+COUNTIF(AF$4:AF$50,"OC-N")+COUNTIF(AF$4:AF$50,"BH-N")+COUNTIF(AF$4:AF$50,"AG-N") -> 3
A58: Night Skill ⚡ | E58: =SUMPRODUCT(((E$4:E$50="N")+(E$4:E$50="OC-N")+(E$4:E$50="BH-N"))*$D$4:$D$50)+COUNTIF(E$4:E$50,"AG-N")*1 -> 2 | F58: =SUMPRODUCT(((F$4:F$50="N")+(F$4:F$50="OC-N")+(F$4:F$50="BH-N"))*$D$4:$D$50)+COUNTIF(F$4:F$50,"AG-N")*1 -> 2 | G58: =SUMPRODUCT(((G$4:G$50="N")+(G$4:G$50="OC-N")+(G$4:G$50="BH-N"))*$D$4:$D$50)+COUNTIF(G$4:G$50,"AG-N")*1 -> 2 | H58: =SUMPRODUCT(((H$4:H$50="N")+(H$4:H$50="OC-N")+(H$4:H$50="BH-N"))*$D$4:$D$50)+COUNTIF(H$4:H$50,"AG-N")*1 -> 2 | I58: =SUMPRODUCT(((I$4:I$50="N")+(I$4:I$50="OC-N")+(I$4:I$50="BH-N"))*$D$4:$D$50)+COUNTIF(I$4:I$50,"AG-N")*1 -> 2 | J58: =SUMPRODUCT(((J$4:J$50="N")+(J$4:J$50="OC-N")+(J$4:J$50="BH-N"))*$D$4:$D$50)+COUNTIF(J$4:J$50,"AG-N")*1 -> 2 | K58: =SUMPRODUCT(((K$4:K$50="N")+(K$4:K$50="OC-N")+(K$4:K$50="BH-N"))*$D$4:$D$50)+COUNTIF(K$4:K$50,"AG-N")*1 -> 2 | L58: =SUMPRODUCT(((L$4:L$50="N")+(L$4:L$50="OC-N")+(L$4:L$50="BH-N"))*$D$4:$D$50)+COUNTIF(L$4:L$50,"AG-N")*1 -> 2 | ... AF58: =SUMPRODUCT(((AF$4:AF$50="N")+(AF$4:AF$50="OC-N")+(AF$4:AF$50="BH-N"))*$D$4:$D$50)+COUNTIF(AF$4:AF$50,"AG-N")*1 -> 2
A59: AL Count | E59: =COUNTIF(E$4:E$50,"AL") -> 0 | F59: =COUNTIF(F$4:F$50,"AL") -> 0 | G59: =COUNTIF(G$4:G$50,"AL") -> 0 | H59: =COUNTIF(H$4:H$50,"AL") -> 0 | I59: =COUNTIF(I$4:I$50,"AL") -> 0 | J59: =COUNTIF(J$4:J$50,"AL") -> 0 | K59: =COUNTIF(K$4:K$50,"AL") -> 0 | L59: =COUNTIF(L$4:L$50,"AL") -> 0 | ... AF59: =COUNTIF(AF$4:AF$50,"AL") -> 0
A60: Sick Count | E60: =COUNTIF(E$4:E$50,"SICK") -> 0 | F60: =COUNTIF(F$4:F$50,"SICK") -> 0 | G60: =COUNTIF(G$4:G$50,"SICK") -> 0 | H60: =COUNTIF(H$4:H$50,"SICK") -> 0 | I60: =COUNTIF(I$4:I$50,"SICK") -> 0 | J60: =COUNTIF(J$4:J$50,"SICK") -> 0 | K60: =COUNTIF(K$4:K$50,"SICK") -> 0 | L60: =COUNTIF(L$4:L$50,"SICK") -> 0 | ... AF60: =COUNTIF(AF$4:AF$50,"SICK") -> 0
A61: Agency Count | E61: =COUNTIF(E$4:E$50,"AG-E")+COUNTIF(E$4:E$50,"AG-L")+COUNTIF(E$4:E$50,"AG-N") -> 0 | F61: =COUNTIF(F$4:F$50,"AG-E")+COUNTIF(F$4:F$50,"AG-L")+COUNTIF(F$4:F$50,"AG-N") -> 0 | G61: =COUNTIF(G$4:G$50,"AG-E")+COUNTIF(G$4:G$50,"AG-L")+COUNTIF(G$4:G$50,"AG-N") -> 0 | H61: =COUNTIF(H$4:H$50,"AG-E")+COUNTIF(H$4:H$50,"AG-L")+COUNTIF(H$4:H$50,"AG-N") -> 0 | I61: =COUNTIF(I$4:I$50,"AG-E")+COUNTIF(I$4:I$50,"AG-L")+COUNTIF(I$4:I$50,"AG-N") -> 0 | J61: =COUNTIF(J$4:J$50,"AG-E")+COUNTIF(J$4:J$50,"AG-L")+COUNTIF(J$4:J$50,"AG-N") -> 0 | K61: =COUNTIF(K$4:K$50,"AG-E")+COUNTIF(K$4:K$50,"AG-L")+COUNTIF(K$4:K$50,"AG-N") -> 0 | L61: =COUNTIF(L$4:L$50,"AG-E")+COUNTIF(L$4:L$50,"AG-L")+COUNTIF(L$4:L$50,"AG-N") -> 0 | ... AF61: =COUNTIF(AF$4:AF$50,"AG-E")+COUNTIF(AF$4:AF$50,"AG-L")+COUNTIF(AF$4:AF$50,"AG-N") -> 0
A62: Day Status | E62: =IF(OR(E53<CONFIG!$B$20,E55<CONFIG!$B$22),"🔴 HEADS",IF(OR(E54<CONFIG!$B$21,E56<CONFIG!$B$23),"🟠 SKILL","✅ OK")) -> ✅ OK | F62: =IF(OR(F53<CONFIG!$B$20,F55<CONFIG!$B$22),"🔴 HEADS",IF(OR(F54<CONFIG!$B$21,F56<CONFIG!$B$23),"🟠 SKILL","✅ OK")) -> ✅ OK | G62: =IF(OR(G30<CONFIG!$B$20,G32<CONFIG!$B$22),"🔴 HEADS",IF(OR(G31<CONFIG!$B$21,G33<CONFIG!$B$23),"🟠 SKILL","✅ OK")) -> 🔴 HEADS | H62: =IF(OR(H30<CONFIG!$B$20,H32<CONFIG!$B$22),"🔴 HEADS",IF(OR(H31<CONFIG!$B$21,H33<CONFIG!$B$23),"🟠 SKILL","✅ OK")) -> 🔴 HEADS | I62: =IF(OR(I30<CONFIG!$B$20,I32<CONFIG!$B$22),"🔴 HEADS",IF(OR(I31<CONFIG!$B$21,I33<CONFIG!$B$23),"🟠 SKILL","✅ OK")) -> 🔴 HEADS | J62: =IF(OR(J30<CONFIG!$B$20,J32<CONFIG!$B$22),"🔴 HEADS",IF(OR(J31<CONFIG!$B$21,J33<CONFIG!$B$23),"🟠 SKILL","✅ OK")) -> 🔴 HEADS | K62: =IF(OR(K30<CONFIG!$B$20,K32<CONFIG!$B$22),"🔴 HEADS",IF(OR(K31<CONFIG!$B$21,K33<CONFIG!$B$23),"🟠 SKILL","✅ OK")) -> 🔴 HEADS | L62: =IF(OR(L30<CONFIG!$B$20,L32<CONFIG!$B$22),"🔴 HEADS",IF(OR(L31<CONFIG!$B$21,L33<CONFIG!$B$23),"🟠 SKILL","✅ OK")) -> 🔴 HEADS | M62: =IF(OR(M30<CONFIG!$B$20,M32<CONFIG!$B$22),"🔴 HEADS",IF(OR(M31<CONFIG!$B$21,M33<CONFIG!$B$23),"🟠 SKILL","✅ OK")) -> 🔴 HEADS | N62: =IF(OR(N30<CONFIG!$B$20,N32<CONFIG!$B$22),"🔴 HEADS",IF(OR(N31<CONFIG!$B$21,N33<CONFIG!$B$23),"🟠 SKILL","✅ OK")) -> 🔴 HEADS | ... AD62: =IF(OR(AD30<CONFIG!$B$20,AD32<CONFIG!$B$22),"🔴 HEADS",IF(OR(AD31<CONFIG!$B$21,AD33<CONFIG!$B$23),"🟠 SKILL","✅ OK")) -> 🔴 HEADS | AE62: =IF(OR(AE53<CONFIG!$B$20,AE55<CONFIG!$B$22),"🔴 HEADS",IF(OR(AE54<CONFIG!$B$21,AE56<CONFIG!$B$23),"🟠 SKILL","✅ OK")) -> ✅ OK | AF62: =IF(OR(AF53<CONFIG!$B$20,AF55<CONFIG!$B$22),"🔴 HEADS",IF(OR(AF54<CONFIG!$B$21,AF56<CONFIG!$B$23),"🟠 SKILL","✅ OK")) -> ✅ OK
A63: Night Status | E63: =IF(E57<CONFIG!$B$24,"🔴 HEADS",IF(E58<CONFIG!$B$25,"🟠 SKILL","✅ OK")) -> ✅ OK | F63: =IF(F57<CONFIG!$B$24,"🔴 HEADS",IF(F58<CONFIG!$B$25,"🟠 SKILL","✅ OK")) -> ✅ OK | G63: =IF(G34<CONFIG!$B$24,"🔴 HEADS",IF(G35<CONFIG!$B$25,"🟠 SKILL","✅ OK")) -> 🔴 HEADS | H63: =IF(H34<CONFIG!$B$24,"🔴 HEADS",IF(H35<CONFIG!$B$25,"🟠 SKILL","✅ OK")) -> 🔴 HEADS | I63: =IF(I34<CONFIG!$B$24,"🔴 HEADS",IF(I35<CONFIG!$B$25,"🟠 SKILL","✅ OK")) -> 🔴 HEADS | J63: =IF(J34<CONFIG!$B$24,"🔴 HEADS",IF(J35<CONFIG!$B$25,"🟠 SKILL","✅ OK")) -> 🔴 HEADS | K63: =IF(K34<CONFIG!$B$24,"🔴 HEADS",IF(K35<CONFIG!$B$25,"🟠 SKILL","✅ OK")) -> 🔴 HEADS | L63: =IF(L34<CONFIG!$B$24,"🔴 HEADS",IF(L35<CONFIG!$B$25,"🟠 SKILL","✅ OK")) -> 🔴 HEADS | M63: =IF(M34<CONFIG!$B$24,"🔴 HEADS",IF(M35<CONFIG!$B$25,"🟠 SKILL","✅ OK")) -> 🔴 HEADS | N63: =IF(N34<CONFIG!$B$24,"🔴 HEADS",IF(N35<CONFIG!$B$25,"🟠 SKILL","✅ OK")) -> 🔴 HEADS | ... AD63: =IF(AD34<CONFIG!$B$24,"🔴 HEADS",IF(AD35<CONFIG!$B$25,"🟠 SKILL","✅ OK")) -> 🔴 HEADS | AE63: =IF(AE57<CONFIG!$B$24,"🔴 HEADS",IF(AE58<CONFIG!$B$25,"🟠 SKILL","✅ OK")) -> ✅ OK | AF63: =IF(AF57<CONFIG!$B$24,"🔴 HEADS",IF(AF58<CONFIG!$B$25,"🟠 SKILL","✅ OK")) -> ✅ OK

Sheet DAILY_COSTS
A1: DAILY COST TRACKER (v7 — Adaptive)
A2: Day# | B2: Day | C2: Base £ (staff) | D2: OT Prem £ | E2: AG Day £ | F2: AG Night £ | G2: BH Prem £ | H2: TOTAL £ | I2: Cumul £
A3: 1 | B3: Mon | C3: =SUMPRODUCT(((ROSTER!E$4:E$50="E")*CONFIG!$B$9+(ROSTER!E$4:E$50="L")*CONFIG!$B$10+(ROSTER!E$4:E$50="EL")*CONFIG!$B$11+(ROSTER!E$4:E$50="N")*CONFIG!$B$12+(ROSTER!E$4:E$50="OC-E")*CONFIG!$B$9+(ROSTER!E$4:E$50="OC-L")*CONFIG!$B$10+(ROSTER!E$4:E$50="OC-EL")*CONFIG!$B$11+(ROSTER!E$4:E$50="OC-N")*CONFIG!$B$12+(ROSTER!E$4:E$50="ADM")*CONFIG!$B$9+(ROSTER!E$4:E$50="TRN")*CONFIG!$B$9+(ROSTER!E$4:E$50="BH-D")*CONFIG!$B$11+(ROSTER!E$4:E$50="BH-N")*CONFIG!$B$12)*ROSTER!$AG$4:$AG$50) -> 1539.125 | D3: =SUMPRODUCT(((ROSTER!E$4:E$50="OC-E")*CONFIG!$B$9+(ROSTER!E$4:E$50="OC-L")*CONFIG!$B$10+(ROSTER!E$4:E$50="OC-EL")*CONFIG!$B$11+(ROSTER!E$4:E$50="OC-N")*CONFIG!$B$12))*CONFIG!$B$28 -> 0 | E3: =(COUNTIF(ROSTER!E$4:E$50,"AG-E")*CONFIG!$B$9+COUNTIF(ROSTER!E$4:E$50,"AG-L")*CONFIG!$B$10)*CONFIG!$B$29 -> 0 | F3: =COUNTIF(ROSTER!E$4:E$50,"AG-N")*CONFIG!$B$12*CONFIG!$B$30 -> 0 | G3: =SUMPRODUCT((ROSTER!E$4:E$50="BH-D")*CONFIG!$B$11*ROSTER!$AG$4:$AG$50*(CONFIG!$B$46-1))+SUMPRODUCT((ROSTER!E$4:E$50="BH-N")*CONFIG!$B$12*ROSTER!$AG$4:$AG$50*(CONFIG!$B$46-1)) -> 0 | H3: =C3+D3+E3+F3+G3 -> 1539.125 | I3: =H3 -> 1539.125
A4: 2 | B4: Tue | C4: =SUMPRODUCT(((ROSTER!F$4:F$50="E")*CONFIG!$B$9+(ROSTER!F$4:F$50="L")*CONFIG!$B$10+(ROSTER!F$4:F$50="EL")*CONFIG!$B$11+(ROSTER!F$4:F$50="N")*CONFIG!$B$12+(ROSTER!F$4:F$50="OC-E")*CONFIG!$B$9+(ROSTER!F$4:F$50="OC-L")*CONFIG!$B$10+(ROSTER!F$4:F$50="OC-EL")*CONFIG!$B$11+(ROSTER!F$4:F$50="OC-N")*CONFIG!$B$12+(ROSTER!F$4:F$50="ADM")*CONFIG!$B$9+(ROSTER!F$4:F$50="TRN")*CONFIG!$B$9+(ROSTER!F$4:F$50="BH-D")*CONFIG!$B$11+(ROSTER!F$4:F$50="BH-N")*CONFIG!$B$12)*ROSTER!$AG$4:$AG$50) -> 1539.125 | D4: =SUMPRODUCT(((ROSTER!F$4:F$50="OC-E")*CONFIG!$B$9+(ROSTER!F$4:F$50="OC-L")*CONFIG!$B$10+(ROSTER!F$4:F$50="OC-EL")*CONFIG!$B$11+(ROSTER!F$4:F$50="OC-N")*CONFIG!$B$12))*CONFIG!$B$28 -> 0 | E4: =(COUNTIF(ROSTER!F$4:F$50,"AG-E")*CONFIG!$B$9+COUNTIF(ROSTER!F$4:F$50,"AG-L")*CONFIG!$B$10)*CONFIG!$B$29 -> 0 | F4: =COUNTIF(ROSTER!F$4:F$50,"AG-N")*CONFIG!$B$12*CONFIG!$B$30 -> 0 | G4: =SUMPRODUCT((ROSTER!F$4:F$50="BH-D")*CONFIG!$B$11*ROSTER!$AG$4:$AG$50*(CONFIG!$B$46-1))+SUMPRODUCT((ROSTER!F$4:F$50="BH-N")*CONFIG!$B$12*ROSTER!$AG$4:$AG$50*(CONFIG!$B$46-1)) -> 0 | H4: =C4+D4+E4+F4+G4 -> 1539.125 | I4: =I3+H4 -> 3078.25
A5: 3 | B5: Wed | C5: =SUMPRODUCT(((ROSTER!G$4:G$50="E")*CONFIG!$B$9+(ROSTER!G$4:G$50="L")*CONFIG!$B$10+(ROSTER!G$4:G$50="EL")*CONFIG!$B$11+(ROSTER!G$4:G$50="N")*CONFIG!$B$12+(ROSTER!G$4:G$50="OC-E")*CONFIG!$B$9+(ROSTER!G$4:G$50="OC-L")*CONFIG!$B$10+(ROSTER!G$4:G$50="OC-EL")*CONFIG!$B$11+(ROSTER!G$4:G$50="OC-N")*CONFIG!$B$12+(ROSTER!G$4:G$50="ADM")*CONFIG!$B$9+(ROSTER!G$4:G$50="TRN")*CONFIG!$B$9+(ROSTER!G$4:G$50="BH-D")*CONFIG!$B$11+(ROSTER!G$4:G$50="BH-N")*CONFIG!$B$12)*ROSTER!$AG$4:$AG$50) -> 1548.125 | D5: =SUMPRODUCT(((ROSTER!G$4:G$50="OC-E")*CONFIG!$B$9+(ROSTER!G$4:G$50="OC-L")*CONFIG!$B$10+(ROSTER!G$4:G$50="OC-EL")*CONFIG!$B$11+(ROSTER!G$4:G$50="OC-N")*CONFIG!$B$12))*CONFIG!$B$28 -> 0 | E5: =(COUNTIF(ROSTER!G$4:G$50,"AG-E")*CONFIG!$B$9+COUNTIF(ROSTER!G$4:G$50,"AG-L")*CONFIG!$B$10)*CONFIG!$B$29 -> 0 | F5: =COUNTIF(ROSTER!G$4:G$50,"AG-N")*CONFIG!$B$12*CONFIG!$B$30 -> 0 | G5: =SUMPRODUCT((ROSTER!G$4:G$50="BH-D")*CONFIG!$B$11*ROSTER!$AG$4:$AG$50*(CONFIG!$B$46-1))+SUMPRODUCT((ROSTER!G$4:G$50="BH-N")*CONFIG!$B$12*ROSTER!$AG$4:$AG$50*(CONFIG!$B$46-1)) -> 0 | H5: =C5+D5+E5+F5+G5 -> 1548.125 | I5: =I4+H5 -> 4626.375
A6: 4 | B6: Thu | C6: =SUMPRODUCT(((ROSTER!H$4:H$50="E")*CONFIG!$B$9+(ROSTER!H$4:H$50="L")*CONFIG!$B$10+(ROSTER!H$4:H$50="EL")*CONFIG!$B$11+(ROSTER!H$4:H$50="N")*CONFIG!$B$12+(ROSTER!H$4:H$50="OC-E")*CONFIG!$B$9+(ROSTER!H$4:H$50="OC-L")*CONFIG!$B$10+(ROSTER!H$4:H$50="OC-EL")*CONFIG!$B$11+(ROSTER!H$4:H$50="OC-N")*CONFIG!$B$12+(ROSTER!H$4:H$50="ADM")*CONFIG!$B$9+(ROSTER!H$4:H$50="TRN")*CONFIG!$B$9+(ROSTER!H$4:H$50="BH-D")*CONFIG!$B$11+(ROSTER!H$4:H$50="BH-N")*CONFIG!$B$12)*ROSTER!$AG$4:$AG$50) -> 1548.125 | D6: =SUMPRODUCT(((ROSTER!H$4:H$50="OC-E")*CONFIG!$B$9+(ROSTER!H$4:H$50="OC-L")*CONFIG!$B$10+(ROSTER!H$4:H$50="OC-EL")*CONFIG!$B$11+(ROSTER!H$4:H$50="OC-N")*CONFIG!$B$12))*CONFIG!$B$28 -> 0 | E6: =(COUNTIF(ROSTER!H$4:H$50,"AG-E")*CONFIG!$B$9+COUNTIF(ROSTER!H$4:H$50,"AG-L")*CONFIG!$B$10)*CONFIG!$B$29 -> 0 | F6: =COUNTIF(ROSTER!H$4:H$50,"AG-N")*CONFIG!$B$12*CONFIG!$B$30 -> 0 | G6: =SUMPRODUCT((ROSTER!H$4:H$50="BH-D")*CONFIG!$B$11*ROSTER!$AG$4:$AG$50*(CONFIG!$B$46-1))+SUMPRODUCT((ROSTER!H$4:H$50="BH-N")*CONFIG!$B$12*ROSTER!$AG$4:$AG$50*(CONFIG!$B$46-1)) -> 0 | H6: =C6+D6+E6+F6+G6 -> 1548.125 | I6: =I5+H6 -> 6174.5
A7: 5 | B7: Fri | C7: =SUMPRODUCT(((ROSTER!I$4:I$50="E")*CONFIG!$B$9+(ROSTER!I$4:I$50="L")*CONFIG!$B$10+(ROSTER!I$4:I$50="EL")*CONFIG!$B$11+(ROSTER!I$4:I$50="N")*CONFIG!$B$12+(ROSTER!I$4:I$50="OC-E")*CONFIG!$B$9+(ROSTER!I$4:I$50="OC-L")*CONFIG!$B$10+(ROSTER!I$4:I$50="OC-EL")*CONFIG!$B$11+(ROSTER!I$4:I$50="OC-N")*CONFIG!$B$12+(ROSTER!I$4:I$50="ADM")*CONFIG!$B$9+(ROSTER!I$4:I$50="TRN")*CONFIG!$B$9+(ROSTER!I$4:I$50="BH-D")*CONFIG!$B$11+(ROSTER!I$4:I$50="BH-N")*CONFIG!$B$12)*ROSTER!$AG$4:$AG$50) -> 1539.125 | D7: =SUMPRODUCT(((ROSTER!I$4:I$50="OC-E")*CONFIG!$B$9+(ROSTER!I$4:I$50="OC-L")*CONFIG!$B$10+(ROSTER!I$4:I$50="OC-EL")*CONFIG!$B$11+(ROSTER!I$4:I$50="OC-N")*CONFIG!$B$12))*CONFIG!$B$28 -> 0 | E7: =(COUNTIF(ROSTER!I$4:I$50,"AG-E")*CONFIG!$B$9+COUNTIF(ROSTER!I$4:I$50,"AG-L")*CONFIG!$B$10)*CONFIG!$B$29 -> 0 | F7: =COUNTIF(ROSTER!I$4:I$50,"AG-N")*CONFIG!$B$12*CONFIG!$B$30 -> 0 | G7: =SUMPRODUCT((ROSTER!I$4:I$50="BH-D")*CONFIG!$B$11*ROSTER!$AG$4:$AG$50*(CONFIG!$B$46-1))+SUMPRODUCT((ROSTER!I$4:I$50="BH-N")*CONFIG!$B$12*ROSTER!$AG$4:$AG$50*(CONFIG!$B$46-1)) -> 0 | H7: =C7+D7+E7+F7+G7 -> 1539.125 | I7: =I6+H7 -> 7713.625
A8: 6 | B8: Sat | C8: =SUMPRODUCT(((ROSTER!J$4:J$50="E")*CONFIG!$B$9+(ROSTER!J$4:J$50="L")*CONFIG!$B$10+(ROSTER!J$4:J$50="EL")*CONFIG!$B$11+(ROSTER!J$4:J$50="N")*CONFIG!$B$12+(ROSTER!J$4:J$50="OC-E")*CONFIG!$B$9+(ROSTER!J$4:J$50="OC-L")*CONFIG!$B$10+(ROSTER!J$4:J$50="OC-EL")*CONFIG!$B$11+(ROSTER!J$4:J$50="OC-N")*CONFIG!$B$12+(ROSTER!J$4:J$50="ADM")*CONFIG!$B$9+(ROSTER!J$4:J$50="TRN")*CONFIG!$B$9+(ROSTER!J$4:J$50="BH-D")*CONFIG!$B$11+(ROSTER!J$4:J$50="BH-N")*CONFIG!$B$12)*ROSTER!$AG$4:$AG$50) -> 1539.125 | D8: =SUMPRODUCT(((ROSTER!J$4:J$50="OC-E")*CONFIG!$B$9+(ROSTER!J$4:J$50="OC-L")*CONFIG!$B$10+(ROSTER!J$4:J$50="OC-EL")*CONFIG!$B$11+(ROSTER!J$4:J$50="OC-N")*CONFIG!$B$12))*CONFIG!$B$28 -> 0 | E8: =(COUNTIF(ROSTER!J$4:J$50,"AG-E")*CONFIG!$B$9+COUNTIF(ROSTER!J$4:J$50,"AG-L")*CONFIG!$B$10)*CONFIG!$B$29 -> 0 | F8: =COUNTIF(ROSTER!J$4:J$50,"AG-N")*CONFIG!$B$12*CONFIG!$B$30 -> 0 | G8: =SUMPRODUCT((ROSTER!J$4:J$50="BH-D")*CONFIG!$B$11*ROSTER!$AG$4:$AG$50*(CONFIG!$B$46-1))+SUMPRODUCT((ROSTER!J$4:J$50="BH-N")*CONFIG!$B$12*ROSTER!$AG$4:$AG$50*(CONFIG!$B$46-1)) -> 0 | H8: =C8+D8+E8+F8+G8 -> 1539.125 | I8: =I7+H8 -> 9252.75
A9: 7 | B9: Sun | C9: =SUMPRODUCT(((ROSTER!K$4:K$50="E")*CONFIG!$B$9+(ROSTER!K$4:K$50="L")*CONFIG!$B$10+(ROSTER!K$4:K$50="EL")*CONFIG!$B$11+(ROSTER!K$4:K$50="N")*CONFIG!$B$12+(ROSTER!K$4:K$50="OC-E")*CONFIG!$B$9+(ROSTER!K$4:K$50="OC-L")*CONFIG!$B$10+(ROSTER!K$4:K$50="OC-EL")*CONFIG!$B$11+(ROSTER!K$4:K$50="OC-N")*CONFIG!$B$12+(ROSTER!K$4:K$50="ADM")*CONFIG!$B$9+(ROSTER!K$4:K$50="TRN")*CONFIG!$B$9+(ROSTER!K$4:K$50="BH-D")*CONFIG!$B$11+(ROSTER!K$4:K$50="BH-N")*CONFIG!$B$12)*ROSTER!$AG$4:$AG$50) -> 1539.125 | D9: =SUMPRODUCT(((ROSTER!K$4:K$50="OC-E")*CONFIG!$B$9+(ROSTER!K$4:K$50="OC-L")*CONFIG!$B$10+(ROSTER!K$4:K$50="OC-EL")*CONFIG!$B$11+(ROSTER!K$4:K$50="OC-N")*CONFIG!$B$12))*CONFIG!$B$28 -> 0 | E9: =(COUNTIF(ROSTER!K$4:K$50,"AG-E")*CONFIG!$B$9+COUNTIF(ROSTER!K$4:K$50,"AG-L")*CONFIG!$B$10)*CONFIG!$B$29 -> 0 | F9: =COUNTIF(ROSTER!K$4:K$50,"AG-N")*CONFIG!$B$12*CONFIG!$B$30 -> 0 | G9: =SUMPRODUCT((ROSTER!K$4:K$50="BH-D")*CONFIG!$B$11*ROSTER!$AG$4:$AG$50*(CONFIG!$B$46-1))+SUMPRODUCT((ROSTER!K$4:K$50="BH-N")*CONFIG!$B$12*ROSTER!$AG$4:$AG$50*(CONFIG!$B$46-1)) -> 0 | H9: =C9+D9+E9+F9+G9 -> 1539.125 | I9: =I8+H9 -> 10791.875
A10: 8 | B10: Mon | C10: =SUMPRODUCT(((ROSTER!L$4:L$50="E")*CONFIG!$B$9+(ROSTER!L$4:L$50="L")*CONFIG!$B$10+(ROSTER!L$4:L$50="EL")*CONFIG!$B$11+(ROSTER!L$4:L$50="N")*CONFIG!$B$12+(ROSTER!L$4:L$50="OC-E")*CONFIG!$B$9+(ROSTER!L$4:L$50="OC-L")*CONFIG!$B$10+(ROSTER!L$4:L$50="OC-EL")*CONFIG!$B$11+(ROSTER!L$4:L$50="OC-N")*CONFIG!$B$12+(ROSTER!L$4:L$50="ADM")*CONFIG!$B$9+(ROSTER!L$4:L$50="TRN")*CONFIG!$B$9+(ROSTER!L$4:L$50="BH-D")*CONFIG!$B$11+(ROSTER!L$4:L$50="BH-N")*CONFIG!$B$12)*ROSTER!$AG$4:$AG$50) -> 1548.125 | D10: =SUMPRODUCT(((ROSTER!L$4:L$50="OC-E")*CONFIG!$B$9+(ROSTER!L$4:L$50="OC-L")*CONFIG!$B$10+(ROSTER!L$4:L$50="OC-EL")*CONFIG!$B$11+(ROSTER!L$4:L$50="OC-N")*CONFIG!$B$12))*CONFIG!$B$28 -> 0 | E10: =(COUNTIF(ROSTER!L$4:L$50,"AG-E")*CONFIG!$B$9+COUNTIF(ROSTER!L$4:L$50,"AG-L")*CONFIG!$B$10)*CONFIG!$B$29 -> 0 | F10: =COUNTIF(ROSTER!L$4:L$50,"AG-N")*CONFIG!$B$12*CONFIG!$B$30 -> 0 | G10: =SUMPRODUCT((ROSTER!L$4:L$50="BH-D")*CONFIG!$B$11*ROSTER!$AG$4:$AG$50*(CONFIG!$B$46-1))+SUMPRODUCT((ROSTER!L$4:L$50="BH-N")*CONFIG!$B$12*ROSTER!$AG$4:$AG$50*(CONFIG!$B$46-1)) -> 0 | H10: =C10+D10+E10+F10+G10 -> 1548.125 | I10: =I9+H10 -> 12340
A11: 9 | B11: Tue | C11: =SUMPRODUCT(((ROSTER!M$4:M$50="E")*CONFIG!$B$9+(ROSTER!M$4:M$50="L")*CONFIG!$B$10+(ROSTER!M$4:M$50="EL")*CONFIG!$B$11+(ROSTER!M$4:M$50="N")*CONFIG!$B$12+(ROSTER!M$4:M$50="OC-E")*CONFIG!$B$9+(ROSTER!M$4:M$50="OC-L")*CONFIG!$B$10+(ROSTER!M$4:M$50="OC-EL")*CONFIG!$B$11+(ROSTER!M$4:M$50="OC-N")*CONFIG!$B$12+(ROSTER!M$4:M$50="ADM")*CONFIG!$B$9+(ROSTER!M$4:M$50="TRN")*CONFIG!$B$9+(ROSTER!M$4:M$50="BH-D")*CONFIG!$B$11+(ROSTER!M$4:M$50="BH-N")*CONFIG!$B$12)*ROSTER!$AG$4:$AG$50) -> 1548.125 | D11: =SUMPRODUCT(((ROSTER!M$4:M$50="OC-E")*CONFIG!$B$9+(ROSTER!M$4:M$50="OC-L")*CONFIG!$B$10+(ROSTER!M$4:M$50="OC-EL")*CONFIG!$B$11+(ROSTER!M$4:M$50="OC-N")*CONFIG!$B$12))*CONFIG!$B$28 -> 0 | E11: =(COUNTIF(ROSTER!M$4:M$50,"AG-E")*CONFIG!$B$9+COUNTIF(ROSTER!M$4:M$50,"AG-L")*CONFIG!$B$10)*CONFIG!$B$29 -> 0 | F11: =COUNTIF(ROSTER!M$4:M$50,"AG-N")*CONFIG!$B$12*CONFIG!$B$30 -> 0 | G11: =SUMPRODUCT((ROSTER!M$4:M$50="BH-D")*CONFIG!$B$11*ROSTER!$AG$4:$AG$50*(CONFIG!$B$46-1))+SUMPRODUCT((ROSTER!M$4:M$50="BH-N")*CONFIG!$B$12*ROSTER!$AG$4:$AG$50*(CONFIG!$B$46-1)) -> 0 | H11: =C11+D11+E11+F11+G11 -> 1548.125 | I11: =I10+H11 -> 13888.125
A12: 10 | B12: Wed | C12: =SUMPRODUCT(((ROSTER!N$4:N$50="E")*CONFIG!$B$9+(ROSTER!N$4:N$50="L")*CONFIG!$B$10+(ROSTER!N$4:N$50="EL")*CONFIG!$B$11+(ROSTER!N$4:N$50="N")*CONFIG!$B$12+(ROSTER!N$4:N$50="OC-E")*CONFIG!$B$9+(ROSTER!N$4:N$50="OC-L")*CONFIG!$B$10+(ROSTER!N$4:N$50="OC-EL")*CONFIG!$B$11+(ROSTER!N$4:N$50="OC-N")*CONFIG!$B$12+(ROSTER!N$4:N$50="ADM")*CONFIG!$B$9+(ROSTER!N$4:N$50="TRN")*CONFIG!$B$9+(ROSTER!N$4:N$50="BH-D")*CONFIG!$B$11+(ROSTER!N$4:N$50="BH-N")*CONFIG!$B$12)*ROSTER!$AG$4:$AG$50) -> 1539.125 | D12: =SUMPRODUCT(((ROSTER!N$4:N$50="OC-E")*CONFIG!$B$9+(ROSTER!N$4:N$50="OC-L")*CONFIG!$B$10+(ROSTER!N$4:N$50="OC-EL")*CONFIG!$B$11+(ROSTER!N$4:N$50="OC-N")*CONFIG!$B$12))*CONFIG!$B$28 -> 0 | E12: =(COUNTIF(ROSTER!N$4:N$50,"AG-E")*CONFIG!$B$9+COUNTIF(ROSTER!N$4:N$50,"AG-L")*CONFIG!$B$10)*CONFIG!$B$29 -> 0 | F12: =COUNTIF(ROSTER!N$4:N$50,"AG-N")*CONFIG!$B$12*CONFIG!$B$30 -> 0 | G12: =SUMPRODUCT((ROSTER!N$4:N$50="BH-D")*CONFIG!$B$11*ROSTER!$AG$4:$AG$50*(CONFIG!$B$46-1))+SUMPRODUCT((ROSTER!N$4:N$50="BH-N")*CONFIG!$B$12*ROSTER!$AG$4:$AG$50*(CONFIG!$B$46-1)) -> 0 | H12: =C12+D12+E12+F12+G12 -> 1539.125 | I12: =I11+H12 -> 15427.25
A13: 11 | B13: Thu | C13: =SUMPRODUCT(((ROSTER!O$4:O$50="E")*CONFIG!$B$9+(ROSTER!O$4:O$50="L")*CONFIG!$B$10+(ROSTER!O$4:O$50="EL")*CONFIG!$B$11+(ROSTER!O$4:O$50="N")*CONFIG!$B$12+(ROSTER!O$4:O$50="OC-E")*CONFIG!$B$9+(ROSTER!O$4:O$50="OC-L")*CONFIG!$B$10+(ROSTER!O$4:O$50="OC-EL")*CONFIG!$B$11+(ROSTER!O$4:O$50="OC-N")*CONFIG!$B$12+(ROSTER!O$4:O$50="ADM")*CONFIG!$B$9+(ROSTER!O$4:O$50="TRN")*CONFIG!$B$9+(ROSTER!O$4:O$50="BH-D")*CONFIG!$B$11+(ROSTER!O$4:O$50="BH-N")*CONFIG!$B$12)*ROSTER!$AG$4:$AG$50) -> 1539.125 | D13: =SUMPRODUCT(((ROSTER!O$4:O$50="OC-E")*CONFIG!$B$9+(ROSTER!O$4:O$50="OC-L")*CONFIG!$B$10+(ROSTER!O$4:O$50="OC-EL")*CONFIG!$B$11+(ROSTER!O$4:O$50="OC-N")*CONFIG!$B$12))*CONFIG!$B$28 -> 0 | E13: =(COUNTIF(ROSTER!O$4:O$50,"AG-E")*CONFIG!$B$9+COUNTIF(ROSTER!O$4:O$50,"AG-L")*CONFIG!$B$10)*CONFIG!$B$29 -> 0 | F13: =COUNTIF(ROSTER!O$4:O$50,"AG-N")*CONFIG!$B$12*CONFIG!$B$30 -> 0 | G13: =SUMPRODUCT((ROSTER!O$4:O$50="BH-D")*CONFIG!$B$11*ROSTER!$AG$4:$AG$50*(CONFIG!$B$46-1))+SUMPRODUCT((ROSTER!O$4:O$50="BH-N")*CONFIG!$B$12*ROSTER!$AG$4:$AG$50*(CONFIG!$B$46-1)) -> 0 | H13: =C13+D13+E13+F13+G13 -> 1539.125 | I13: =I12+H13 -> 16966.375
A14: 12 | B14: Fri | C14: =SUMPRODUCT(((ROSTER!P$4:P$50="E")*CONFIG!$B$9+(ROSTER!P$4:P$50="L")*CONFIG!$B$10+(ROSTER!P$4:P$50="EL")*CONFIG!$B$11+(ROSTER!P$4:P$50="N")*CONFIG!$B$12+(ROSTER!P$4:P$50="OC-E")*CONFIG!$B$9+(ROSTER!P$4:P$50="OC-L")*CONFIG!$B$10+(ROSTER!P$4:P$50="OC-EL")*CONFIG!$B$11+(ROSTER!P$4:P$50="OC-N")*CONFIG!$B$12+(ROSTER!P$4:P$50="ADM")*CONFIG!$B$9+(ROSTER!P$4:P$50="TRN")*CONFIG!$B$9+(ROSTER!P$4:P$50="BH-D")*CONFIG!$B$11+(ROSTER!P$4:P$50="BH-N")*CONFIG!$B$12)*ROSTER!$AG$4:$AG$50) -> 1548.125 | D14: =SUMPRODUCT(((ROSTER!P$4:P$50="OC-E")*CONFIG!$B$9+(ROSTER!P$4:P$50="OC-L")*CONFIG!$B$10+(ROSTER!P$4:P$50="OC-EL")*CONFIG!$B$11+(ROSTER!P$4:P$50="OC-N")*CONFIG!$B$12))*CONFIG!$B$28 -> 0 | E14: =(COUNTIF(ROSTER!P$4:P$50,"AG-E")*CONFIG!$B$9+COUNTIF(ROSTER!P$4:P$50,"AG-L")*CONFIG!$B$10)*CONFIG!$B$29 -> 0 | F14: =COUNTIF(ROSTER!P$4:P$50,"AG-N")*CONFIG!$B$12*CONFIG!$B$30 -> 0 | G14: =SUMPRODUCT((ROSTER!P$4:P$50="BH-D")*CONFIG!$B$11*ROSTER!$AG$4:$AG$50*(CONFIG!$B$46-1))+SUMPRODUCT((ROSTER!P$4:P$50="BH-N")*CONFIG!$B$12*ROSTER!$AG$4:$AG$50*(CONFIG!$B$46-1)) -> 0 | H14: =C14+D14+E14+F14+G14 -> 1548.125 | I14: =I13+H14 -> 18514.5
A15: 13 | B15: Sat | C15: =SUMPRODUCT(((ROSTER!Q$4:Q$50="E")*CONFIG!$B$9+(ROSTER!Q$4:Q$50="L")*CONFIG!$B$10+(ROSTER!Q$4:Q$50="EL")*CONFIG!$B$11+(ROSTER!Q$4:Q$50="N")*CONFIG!$B$12+(ROSTER!Q$4:Q$50="OC-E")*CONFIG!$B$9+(ROSTER!Q$4:Q$50="OC-L")*CONFIG!$B$10+(ROSTER!Q$4:Q$50="OC-EL")*CONFIG!$B$11+(ROSTER!Q$4:Q$50="OC-N")*CONFIG!$B$12+(ROSTER!Q$4:Q$50="ADM")*CONFIG!$B$9+(ROSTER!Q$4:Q$50="TRN")*CONFIG!$B$9+(ROSTER!Q$4:Q$50="BH-D")*CONFIG!$B$11+(ROSTER!Q$4:Q$50="BH-N")*CONFIG!$B$12)*ROSTER!$AG$4:$AG$50) -> 1548.125 | D15: =SUMPRODUCT(((ROSTER!Q$4:Q$50="OC-E")*CONFIG!$B$9+(ROSTER!Q$4:Q$50="OC-L")*CONFIG!$B$10+(ROSTER!Q$4:Q$50="OC-EL")*CONFIG!$B$11+(ROSTER!Q$4:Q$50="OC-N")*CONFIG!$B$12))*CONFIG!$B$28 -> 0 | E15: =(COUNTIF(ROSTER!Q$4:Q$50,"AG-E")*CONFIG!$B$9+COUNTIF(ROSTER!Q$4:Q$50,"AG-L")*CONFIG!$B$10)*CONFIG!$B$29 -> 0 | F15: =COUNTIF(ROSTER!Q$4:Q$50,"AG-N")*CONFIG!$B$12*CONFIG!$B$30 -> 0 | G15: =SUMPRODUCT((ROSTER!Q$4:Q$50="BH-D")*CONFIG!$B$11*ROSTER!$AG$4:$AG$50*(CONFIG!$B$46-1))+SUMPRODUCT((ROSTER!Q$4:Q$50="BH-N")*CONFIG!$B$12*ROSTER!$AG$4:$AG$50*(CONFIG!$B$46-1)) -> 0 | H15: =C15+D15+E15+F15+G15 -> 1548.125 | I15: =I14+H15 -> 20062.625
A16: 14 | B16: Sun | C16: =SUMPRODUCT(((ROSTER!R$4:R$50="E")*CONFIG!$B$9+(ROSTER!R$4:R$50="L")*CONFIG!$B$10+(ROSTER!R$4:R$50="EL")*CONFIG!$B$11+(ROSTER!R$4:R$50="N")*CONFIG!$B$12+(ROSTER!R$4:R$50="OC-E")*CONFIG!$B$9+(ROSTER!R$4:R$50="OC-L")*CONFIG!$B$10+(ROSTER!R$4:R$50="OC-EL")*CONFIG!$B$11+(ROSTER!R$4:R$50="OC-N")*CONFIG!$B$12+(ROSTER!R$4:R$50="ADM")*CONFIG!$B$9+(ROSTER!R$4:R$50="TRN")*CONFIG!$B$9+(ROSTER!R$4:R$50="BH-D")*CONFIG!$B$11+(ROSTER!R$4:R$50="BH-N")*CONFIG!$B$12)*ROSTER!$AG$4:$AG$50) -> 1548.125 | D16: =SUMPRODUCT(((ROSTER!R$4:R$50="OC-E")*CONFIG!$B$9+(ROSTER!R$4:R$50="OC-L")*CONFIG!$B$10+(ROSTER!R$4:R$50="OC-EL")*CONFIG!$B$11+(ROSTER!R$4:R$50="OC-N")*CONFIG!$B$12))*CONFIG!$B$28 -> 0 | E16: =(COUNTIF(ROSTER!R$4:R$50,"AG-E")*CONFIG!$B$9+COUNTIF(ROSTER!R$4:R$50,"AG-L")*CONFIG!$B$10)*CONFIG!$B$29 -> 0 | F16: =COUNTIF(ROSTER!R$4:R$50,"AG-N")*CONFIG!$B$12*CONFIG!$B$30 -> 0 | G16: =SUMPRODUCT((ROSTER!R$4:R$50="BH-D")*CONFIG!$B$11*ROSTER!$AG$4:$AG$50*(CONFIG!$B$46-1))+SUMPRODUCT((ROSTER!R$4:R$50="BH-N")*CONFIG!$B$12*ROSTER!$AG$4:$AG$50*(CONFIG!$B$46-1)) -> 0 | H16: =C16+D16+E16+F16+G16 -> 1548.125 | I16: =I15+H16 -> 21610.75
A17: 15 | B17: Mon | C17: =SUMPRODUCT(((ROSTER!S$4:S$50="E")*CONFIG!$B$9+(ROSTER!S$4:S$50="L")*CONFIG!$B$10+(ROSTER!S$4:S$50="EL")*CONFIG!$B$11+(ROSTER!S$4:S$50="N")*CONFIG!$B$12+(ROSTER!S$4:S$50="OC-E")*CONFIG!$B$9+(ROSTER!S$4:S$50="OC-L")*CONFIG!$B$10+(ROSTER!S$4:S$50="OC-EL")*CONFIG!$B$11+(ROSTER!S$4:S$50="OC-N")*CONFIG!$B$12+(ROSTER!S$4:S$50="ADM")*CONFIG!$B$9+(ROSTER!S$4:S$50="TRN")*CONFIG!$B$9+(ROSTER!S$4:S$50="BH-D")*CONFIG!$B$11+(ROSTER!S$4:S$50="BH-N")*CONFIG!$B$12)*ROSTER!$AG$4:$AG$50) -> 1539.125 | D17: =SUMPRODUCT(((ROSTER!S$4:S$50="OC-E")*CONFIG!$B$9+(ROSTER!S$4:S$50="OC-L")*CONFIG!$B$10+(ROSTER!S$4:S$50="OC-EL")*CONFIG!$B$11+(ROSTER!S$4:S$50="OC-N")*CONFIG!$B$12))*CONFIG!$B$28 -> 0 | E17: =(COUNTIF(ROSTER!S$4:S$50,"AG-E")*CONFIG!$B$9+COUNTIF(ROSTER!S$4:S$50,"AG-L")*CONFIG!$B$10)*CONFIG!$B$29 -> 0 | F17: =COUNTIF(ROSTER!S$4:S$50,"AG-N")*CONFIG!$B$12*CONFIG!$B$30 -> 0 | G17: =SUMPRODUCT((ROSTER!S$4:S$50="BH-D")*CONFIG!$B$11*ROSTER!$AG$4:$AG$50*(CONFIG!$B$46-1))+SUMPRODUCT((ROSTER!S$4:S$50="BH-N")*CONFIG!$B$12*ROSTER!$AG$4:$AG$50*(CONFIG!$B$46-1)) -> 0 | H17: =C17+D17+E17+F17+G17 -> 1539.125 | I17: =I16+H17 -> 23149.875
A18: 16 | B18: Tue | C18: =SUMPRODUCT(((ROSTER!T$4:T$50="E")*CONFIG!$B$9+(ROSTER!T$4:T$50="L")*CONFIG!$B$10+(ROSTER!T$4:T$50="EL")*CONFIG!$B$11+(ROSTER!T$4:T$50="N")*CONFIG!$B$12+(ROSTER!T$4:T$50="OC-E")*CONFIG!$B$9+(ROSTER!T$4:T$50="OC-L")*CONFIG!$B$10+(ROSTER!T$4:T$50="OC-EL")*CONFIG!$B$11+(ROSTER!T$4:T$50="OC-N")*CONFIG!$B$12+(ROSTER!T$4:T$50="ADM")*CONFIG!$B$9+(ROSTER!T$4:T$50="TRN")*CONFIG!$B$9+(ROSTER!T$4:T$50="BH-D")*CONFIG!$B$11+(ROSTER!T$4:T$50="BH-N")*CONFIG!$B$12)*ROSTER!$AG$4:$AG$50) -> 1539.125 | D18: =SUMPRODUCT(((ROSTER!T$4:T$50="OC-E")*CONFIG!$B$9+(ROSTER!T$4:T$50="OC-L")*CONFIG!$B$10+(ROSTER!T$4:T$50="OC-EL")*CONFIG!$B$11+(ROSTER!T$4:T$50="OC-N")*CONFIG!$B$12))*CONFIG!$B$28 -> 0 | E18: =(COUNTIF(ROSTER!T$4:T$50,"AG-E")*CONFIG!$B$9+COUNTIF(ROSTER!T$4:T$50,"AG-L")*CONFIG!$B$10)*CONFIG!$B$29 -> 0 | F18: =COUNTIF(ROSTER!T$4:T$50,"AG-N")*CONFIG!$B$12*CONFIG!$B$30 -> 0 | G18: =SUMPRODUCT((ROSTER!T$4:T$50="BH-D")*CONFIG!$B$11*ROSTER!$AG$4:$AG$50*(CONFIG!$B$46-1))+SUMPRODUCT((ROSTER!T$4:T$50="BH-N")*CONFIG!$B$12*ROSTER!$AG$4:$AG$50*(CONFIG!$B$46-1)) -> 0 | H18: =C18+D18+E18+F18+G18 -> 1539.125 | I18: =I17+H18 -> 24689
A19: 17 | B19: Wed | C19: =SUMPRODUCT(((ROSTER!U$4:U$50="E")*CONFIG!$B$9+(ROSTER!U$4:U$50="L")*CONFIG!$B$10+(ROSTER!U$4:U$50="EL")*CONFIG!$B$11+(ROSTER!U$4:U$50="N")*CONFIG!$B$12+(ROSTER!U$4:U$50="OC-E")*CONFIG!$B$9+(ROSTER!U$4:U$50="OC-L")*CONFIG!$B$10+(ROSTER!U$4:U$50="OC-EL")*CONFIG!$B$11+(ROSTER!U$4:U$50="OC-N")*CONFIG!$B$12+(ROSTER!U$4:U$50="ADM")*CONFIG!$B$9+(ROSTER!U$4:U$50="TRN")*CONFIG!$B$9+(ROSTER!U$4:U$50="BH-D")*CONFIG!$B$11+(ROSTER!U$4:U$50="BH-N")*CONFIG!$B$12)*ROSTER!$AG$4:$AG$50) -> 1548.125 | D19: =SUMPRODUCT(((ROSTER!U$4:U$50="OC-E")*CONFIG!$B$9+(ROSTER!U$4:U$50="OC-L")*CONFIG!$B$10+(ROSTER!U$4:U$50="OC-EL")*CONFIG!$B$11+(ROSTER!U$4:U$50="OC-N")*CONFIG!$B$12))*CONFIG!$B$28 -> 0 | E19: =(COUNTIF(ROSTER!U$4:U$50,"AG-E")*CONFIG!$B$9+COUNTIF(ROSTER!U$4:U$50,"AG-L")*CONFIG!$B$10)*CONFIG!$B$29 -> 0 | F19: =COUNTIF(ROSTER!U$4:U$50,"AG-N")*CONFIG!$B$12*CONFIG!$B$30 -> 0 | G19: =SUMPRODUCT((ROSTER!U$4:U$50="BH-D")*CONFIG!$B$11*ROSTER!$AG$4:$AG$50*(CONFIG!$B$46-1))+SUMPRODUCT((ROSTER!U$4:U$50="BH-N")*CONFIG!$B$12*ROSTER!$AG$4:$AG$50*(CONFIG!$B$46-1)) -> 0 | H19: =C19+D19+E19+F19+G19 -> 1548.125 | I19: =I18+H19 -> 26237.125
A20: 18 | B20: Thu | C20: =SUMPRODUCT(((ROSTER!V$4:V$50="E")*CONFIG!$B$9+(ROSTER!V$4:V$50="L")*CONFIG!$B$10+(ROSTER!V$4:V$50="EL")*CONFIG!$B$11+(ROSTER!V$4:V$50="N")*CONFIG!$B$12+(ROSTER!V$4:V$50="OC-E")*CONFIG!$B$9+(ROSTER!V$4:V$50="OC-L")*CONFIG!$B$10+(ROSTER!V$4:V$50="OC-EL")*CONFIG!$B$11+(ROSTER!V$4:V$50="OC-N")*CONFIG!$B$12+(ROSTER!V$4:V$50="ADM")*CONFIG!$B$9+(ROSTER!V$4:V$50="TRN")*CONFIG!$B$9+(ROSTER!V$4:V$50="BH-D")*CONFIG!$B$11+(ROSTER!V$4:V$50="BH-N")*CONFIG!$B$12)*ROSTER!$AG$4:$AG$50) -> 1548.125 | D20: =SUMPRODUCT(((ROSTER!V$4:V$50="OC-E")*CONFIG!$B$9+(ROSTER!V$4:V$50="OC-L")*CONFIG!$B$10+(ROSTER!V$4:V$50="OC-EL")*CONFIG!$B$11+(ROSTER!V$4:V$50="OC-N")*CONFIG!$B$12))*CONFIG!$B$28 -> 0 | E20: =(COUNTIF(ROSTER!V$4:V$50,"AG-E")*CONFIG!$B$9+COUNTIF(ROSTER!V$4:V$50,"AG-L")*CONFIG!$B$10)*CONFIG!$B$29 -> 0 | F20: =COUNTIF(ROSTER!V$4:V$50,"AG-N")*CONFIG!$B$12*CONFIG!$B$30 -> 0 | G20: =SUMPRODUCT((ROSTER!V$4:V$50="BH-D")*CONFIG!$B$11*ROSTER!$AG$4:$AG$50*(CONFIG!$B$46-1))+SUMPRODUCT((ROSTER!V$4:V$50="BH-N")*CONFIG!$B$12*ROSTER!$AG$4:$AG$50*(CONFIG!$B$46-1)) -> 0 | H20: =C20+D20+E20+F20+G20 -> 1548.125 | I20: =I19+H20 -> 27785.25
A21: 19 | B21: Fri | C21: =SUMPRODUCT(((ROSTER!W$4:W$50="E")*CONFIG!$B$9+(ROSTER!W$4:W$50="L")*CONFIG!$B$10+(ROSTER!W$4:W$50="EL")*CONFIG!$B$11+(ROSTER!W$4:W$50="N")*CONFIG!$B$12+(ROSTER!W$4:W$50="OC-E")*CONFIG!$B$9+(ROSTER!W$4:W$50="OC-L")*CONFIG!$B$10+(ROSTER!W$4:W$50="OC-EL")*CONFIG!$B$11+(ROSTER!W$4:W$50="OC-N")*CONFIG!$B$12+(ROSTER!W$4:W$50="ADM")*CONFIG!$B$9+(ROSTER!W$4:W$50="TRN")*CONFIG!$B$9+(ROSTER!W$4:W$50="BH-D")*CONFIG!$B$11+(ROSTER!W$4:W$50="BH-N")*CONFIG!$B$12)*ROSTER!$AG$4:$AG$50) -> 1539.125 | D21: =SUMPRODUCT(((ROSTER!W$4:W$50="OC-E")*CONFIG!$B$9+(ROSTER!W$4:W$50="OC-L")*CONFIG!$B$10+(ROSTER!W$4:W$50="OC-EL")*CONFIG!$B$11+(ROSTER!W$4:W$50="OC-N")*CONFIG!$B$12))*CONFIG!$B$28 -> 0 | E21: =(COUNTIF(ROSTER!W$4:W$50,"AG-E")*CONFIG!$B$9+COUNTIF(ROSTER!W$4:W$50,"AG-L")*CONFIG!$B$10)*CONFIG!$B$29 -> 0 | F21: =COUNTIF(ROSTER!W$4:W$50,"AG-N")*CONFIG!$B$12*CONFIG!$B$30 -> 0 | G21: =SUMPRODUCT((ROSTER!W$4:W$50="BH-D")*CONFIG!$B$11*ROSTER!$AG$4:$AG$50*(CONFIG!$B$46-1))+SUMPRODUCT((ROSTER!W$4:W$50="BH-N")*CONFIG!$B$12*ROSTER!$AG$4:$AG$50*(CONFIG!$B$46-1)) -> 0 | H21: =C21+D21+E21+F21+G21 -> 1539.125 | I21: =I20+H21 -> 29324.375
A22: 20 | B22: Sat | C22: =SUMPRODUCT(((ROSTER!X$4:X$50="E")*CONFIG!$B$9+(ROSTER!X$4:X$50="L")*CONFIG!$B$10+(ROSTER!X$4:X$50="EL")*CONFIG!$B$11+(ROSTER!X$4:X$50="N")*CONFIG!$B$12+(ROSTER!X$4:X$50="OC-E")*CONFIG!$B$9+(ROSTER!X$4:X$50="OC-L")*CONFIG!$B$10+(ROSTER!X$4:X$50="OC-EL")*CONFIG!$B$11+(ROSTER!X$4:X$50="OC-N")*CONFIG!$B$12+(ROSTER!X$4:X$50="ADM")*CONFIG!$B$9+(ROSTER!X$4:X$50="TRN")*CONFIG!$B$9+(ROSTER!X$4:X$50="BH-D")*CONFIG!$B$11+(ROSTER!X$4:X$50="BH-N")*CONFIG!$B$12)*ROSTER!$AG$4:$AG$50) -> 1539.125 | D22: =SUMPRODUCT(((ROSTER!X$4:X$50="OC-E")*CONFIG!$B$9+(ROSTER!X$4:X$50="OC-L")*CONFIG!$B$10+(ROSTER!X$4:X$50="OC-EL")*CONFIG!$B$11+(ROSTER!X$4:X$50="OC-N")*CONFIG!$B$12))*CONFIG!$B$28 -> 0 | E22: =(COUNTIF(ROSTER!X$4:X$50,"AG-E")*CONFIG!$B$9+COUNTIF(ROSTER!X$4:X$50,"AG-L")*CONFIG!$B$10)*CONFIG!$B$29 -> 0 | F22: =COUNTIF(ROSTER!X$4:X$50,"AG-N")*CONFIG!$B$12*CONFIG!$B$30 -> 0 | G22: =SUMPRODUCT((ROSTER!X$4:X$50="BH-D")*CONFIG!$B$11*ROSTER!$AG$4:$AG$50*(CONFIG!$B$46-1))+SUMPRODUCT((ROSTER!X$4:X$50="BH-N")*CONFIG!$B$12*ROSTER!$AG$4:$AG$50*(CONFIG!$B$46-1)) -> 0 | H22: =C22+D22+E22+F22+G22 -> 1539.125 | I22: =I21+H22 -> 30863.5
A23: 21 | B23: Sun | C23: =SUMPRODUCT(((ROSTER!Y$4:Y$50="E")*CONFIG!$B$9+(ROSTER!Y$4:Y$50="L")*CONFIG!$B$10+(ROSTER!Y$4:Y$50="EL")*CONFIG!$B$11+(ROSTER!Y$4:Y$50="N")*CONFIG!$B$12+(ROSTER!Y$4:Y$50="OC-E")*CONFIG!$B$9+(ROSTER!Y$4:Y$50="OC-L")*CONFIG!$B$10+(ROSTER!Y$4:Y$50="OC-EL")*CONFIG!$B$11+(ROSTER!Y$4:Y$50="OC-N")*CONFIG!$B$12+(ROSTER!Y$4:Y$50="ADM")*CONFIG!$B$9+(ROSTER!Y$4:Y$50="TRN")*CONFIG!$B$9+(ROSTER!Y$4:Y$50="BH-D")*CONFIG!$B$11+(ROSTER!Y$4:Y$50="BH-N")*CONFIG!$B$12)*ROSTER!$AG$4:$AG$50) -> 1539.125 | D23: =SUMPRODUCT(((ROSTER!Y$4:Y$50="OC-E")*CONFIG!$B$9+(ROSTER!Y$4:Y$50="OC-L")*CONFIG!$B$10+(ROSTER!Y$4:Y$50="OC-EL")*CONFIG!$B$11+(ROSTER!Y$4:Y$50="OC-N")*CONFIG!$B$12))*CONFIG!$B$28 -> 0 | E23: =(COUNTIF(ROSTER!Y$4:Y$50,"AG-E")*CONFIG!$B$9+COUNTIF(ROSTER!Y$4:Y$50,"AG-L")*CONFIG!$B$10)*CONFIG!$B$29 -> 0 | F23: =COUNTIF(ROSTER!Y$4:Y$50,"AG-N")*CONFIG!$B$12*CONFIG!$B$30 -> 0 | G23: =SUMPRODUCT((ROSTER!Y$4:Y$50="BH-D")*CONFIG!$B$11*ROSTER!$AG$4:$AG$50*(CONFIG!$B$46-1))+SUMPRODUCT((ROSTER!Y$4:Y$50="BH-N")*CONFIG!$B$12*ROSTER!$AG$4:$AG$50*(CONFIG!$B$46-1)) -> 0 | H23: =C23+D23+E23+F23+G23 -> 1539.125 | I23: =I22+H23 -> 32402.625
A24: 22 | B24: Mon | C24: =SUMPRODUCT(((ROSTER!Z$4:Z$50="E")*CONFIG!$B$9+(ROSTER!Z$4:Z$50="L")*CONFIG!$B$10+(ROSTER!Z$4:Z$50="EL")*CONFIG!$B$11+(ROSTER!Z$4:Z$50="N")*CONFIG!$B$12+(ROSTER!Z$4:Z$50="OC-E")*CONFIG!$B$9+(ROSTER!Z$4:Z$50="OC-L")*CONFIG!$B$10+(ROSTER!Z$4:Z$50="OC-EL")*CONFIG!$B$11+(ROSTER!Z$4:Z$50="OC-N")*CONFIG!$B$12+(ROSTER!Z$4:Z$50="ADM")*CONFIG!$B$9+(ROSTER!Z$4:Z$50="TRN")*CONFIG!$B$9+(ROSTER!Z$4:Z$50="BH-D")*CONFIG!$B$11+(ROSTER!Z$4:Z$50="BH-N")*CONFIG!$B$12)*ROSTER!$AG$4:$AG$50) -> 1548.125 | D24: =SUMPRODUCT(((ROSTER!Z$4:Z$50="OC-E")*CONFIG!$B$9+(ROSTER!Z$4:Z$50="OC-L")*CONFIG!$B$10+(ROSTER!Z$4:Z$50="OC-EL")*CONFIG!$B$11+(ROSTER!Z$4:Z$50="OC-N")*CONFIG!$B$12))*CONFIG!$B$28 -> 0 | E24: =(COUNTIF(ROSTER!Z$4:Z$50,"AG-E")*CONFIG!$B$9+COUNTIF(ROSTER!Z$4:Z$50,"AG-L")*CONFIG!$B$10)*CONFIG!$B$29 -> 0 | F24: =COUNTIF(ROSTER!Z$4:Z$50,"AG-N")*CONFIG!$B$12*CONFIG!$B$30 -> 0 | G24: =SUMPRODUCT((ROSTER!Z$4:Z$50="BH-D")*CONFIG!$B$11*ROSTER!$AG$4:$AG$50*(CONFIG!$B$46-1))+SUMPRODUCT((ROSTER!Z$4:Z$50="BH-N")*CONFIG!$B$12*ROSTER!$AG$4:$AG$50*(CONFIG!$B$46-1)) -> 0 | H24: =C24+D24+E24+F24+G24 -> 1548.125 | I24: =I23+H24 -> 33950.75
A25: 23 | B25: Tue | C25: =SUMPRODUCT(((ROSTER!AA$4:AA$50="E")*CONFIG!$B$9+(ROSTER!AA$4:AA$50="L")*CONFIG!$B$10+(ROSTER!AA$4:AA$50="EL")*CONFIG!$B$11+(ROSTER!AA$4:AA$50="N")*CONFIG!$B$12+(ROSTER!AA$4:AA$50="OC-E")*CONFIG!$B$9+(ROSTER!AA$4:AA$50="OC-L")*CONFIG!$B$10+(ROSTER!AA$4:AA$50="OC-EL")*CONFIG!$B$11+(ROSTER!AA$4:AA$50="OC-N")*CONFIG!$B$12+(ROSTER!AA$4:AA$50="ADM")*CONFIG!$B$9+(ROSTER!AA$4:AA$50="TRN")*CONFIG!$B$9+(ROSTER!AA$4:AA$50="BH-D")*CONFIG!$B$11+(ROSTER!AA$4:AA$50="BH-N")*CONFIG!$B$12)*ROSTER!$AG$4:$AG$50) -> 1548.125 | D25: =SUMPRODUCT(((ROSTER!AA$4:AA$50="OC-E")*CONFIG!$B$9+(ROSTER!AA$4:AA$50="OC-L")*CONFIG!$B$10+(ROSTER!AA$4:AA$50="OC-EL")*CONFIG!$B$11+(ROSTER!AA$4:AA$50="OC-N")*CONFIG!$B$12))*CONFIG!$B$28 -> 0 | E25: =(COUNTIF(ROSTER!AA$4:AA$50,"AG-E")*CONFIG!$B$9+COUNTIF(ROSTER!AA$4:AA$50,"AG-L")*CONFIG!$B$10)*CONFIG!$B$29 -> 0 | F25: =COUNTIF(ROSTER!AA$4:AA$50,"AG-N")*CONFIG!$B$12*CONFIG!$B$30 -> 0 | G25: =SUMPRODUCT((ROSTER!AA$4:AA$50="BH-D")*CONFIG!$B$11*ROSTER!$AG$4:$AG$50*(CONFIG!$B$46-1))+SUMPRODUCT((ROSTER!AA$4:AA$50="BH-N")*CONFIG!$B$12*ROSTER!$AG$4:$AG$50*(CONFIG!$B$46-1)) -> 0 | H25: =C25+D25+E25+F25+G25 -> 1548.125 | I25: =I24+H25 -> 35498.875
A26: 24 | B26: Wed | C26: =SUMPRODUCT(((ROSTER!AB$4:AB$50="E")*CONFIG!$B$9+(ROSTER!AB$4:AB$50="L")*CONFIG!$B$10+(ROSTER!AB$4:AB$50="EL")*CONFIG!$B$11+(ROSTER!AB$4:AB$50="N")*CONFIG!$B$12+(ROSTER!AB$4:AB$50="OC-E")*CONFIG!$B$9+(ROSTER!AB$4:AB$50="OC-L")*CONFIG!$B$10+(ROSTER!AB$4:AB$50="OC-EL")*CONFIG!$B$11+(ROSTER!AB$4:AB$50="OC-N")*CONFIG!$B$12+(ROSTER!AB$4:AB$50="ADM")*CONFIG!$B$9+(ROSTER!AB$4:AB$50="TRN")*CONFIG!$B$9+(ROSTER!AB$4:AB$50="BH-D")*CONFIG!$B$11+(ROSTER!AB$4:AB$50="BH-N")*CONFIG!$B$12)*ROSTER!$AG$4:$AG$50) -> 1539.125 | D26: =SUMPRODUCT(((ROSTER!AB$4:AB$50="OC-E")*CONFIG!$B$9+(ROSTER!AB$4:AB$50="OC-L")*CONFIG!$B$10+(ROSTER!AB$4:AB$50="OC-EL")*CONFIG!$B$11+(ROSTER!AB$4:AB$50="OC-N")*CONFIG!$B$12))*CONFIG!$B$28 -> 0 | E26: =(COUNTIF(ROSTER!AB$4:AB$50,"AG-E")*CONFIG!$B$9+COUNTIF(ROSTER!AB$4:AB$50,"AG-L")*CONFIG!$B$10)*CONFIG!$B$29 -> 0 | F26: =COUNTIF(ROSTER!AB$4:AB$50,"AG-N")*CONFIG!$B$12*CONFIG!$B$30 -> 0 | G26: =SUMPRODUCT((ROSTER!AB$4:AB$50="BH-D")*CONFIG!$B$11*ROSTER!$AG$4:$AG$50*(CONFIG!$B$46-1))+SUMPRODUCT((ROSTER!AB$4:AB$50="BH-N")*CONFIG!$B$12*ROSTER!$AG$4:$AG$50*(CONFIG!$B$46-1)) -> 0 | H26: =C26+D26+E26+F26+G26 -> 1539.125 | I26: =I25+H26 -> 37038
A27: 25 | B27: Thu | C27: =SUMPRODUCT(((ROSTER!AC$4:AC$50="E")*CONFIG!$B$9+(ROSTER!AC$4:AC$50="L")*CONFIG!$B$10+(ROSTER!AC$4:AC$50="EL")*CONFIG!$B$11+(ROSTER!AC$4:AC$50="N")*CONFIG!$B$12+(ROSTER!AC$4:AC$50="OC-E")*CONFIG!$B$9+(ROSTER!AC$4:AC$50="OC-L")*CONFIG!$B$10+(ROSTER!AC$4:AC$50="OC-EL")*CONFIG!$B$11+(ROSTER!AC$4:AC$50="OC-N")*CONFIG!$B$12+(ROSTER!AC$4:AC$50="ADM")*CONFIG!$B$9+(ROSTER!AC$4:AC$50="TRN")*CONFIG!$B$9+(ROSTER!AC$4:AC$50="BH-D")*CONFIG!$B$11+(ROSTER!AC$4:AC$50="BH-N")*CONFIG!$B$12)*ROSTER!$AG$4:$AG$50) -> 1539.125 | D27: =SUMPRODUCT(((ROSTER!AC$4:AC$50="OC-E")*CONFIG!$B$9+(ROSTER!AC$4:AC$50="OC-L")*CONFIG!$B$10+(ROSTER!AC$4:AC$50="OC-EL")*CONFIG!$B$11+(ROSTER!AC$4:AC$50="OC-N")*CONFIG!$B$12))*CONFIG!$B$28 -> 0 | E27: =(COUNTIF(ROSTER!AC$4:AC$50,"AG-E")*CONFIG!$B$9+COUNTIF(ROSTER!AC$4:AC$50,"AG-L")*CONFIG!$B$10)*CONFIG!$B$29 -> 0 | F27: =COUNTIF(ROSTER!AC$4:AC$50,"AG-N")*CONFIG!$B$12*CONFIG!$B$30 -> 0 | G27: =SUMPRODUCT((ROSTER!AC$4:AC$50="BH-D")*CONFIG!$B$11*ROSTER!$AG$4:$AG$50*(CONFIG!$B$46-1))+SUMPRODUCT((ROSTER!AC$4:AC$50="BH-N")*CONFIG!$B$12*ROSTER!$AG$4:$AG$50*(CONFIG!$B$46-1)) -> 0 | H27: =C27+D27+E27+F27+G27 -> 1539.125 | I27: =I26+H27 -> 38577.125
A28: 26 | B28: Fri | C28: =SUMPRODUCT(((ROSTER!AD$4:AD$50="E")*CONFIG!$B$9+(ROSTER!AD$4:AD$50="L")*CONFIG!$B$10+(ROSTER!AD$4:AD$50="EL")*CONFIG!$B$11+(ROSTER!AD$4:AD$50="N")*CONFIG!$B$12+(ROSTER!AD$4:AD$50="OC-E")*CONFIG!$B$9+(ROSTER!AD$4:AD$50="OC-L")*CONFIG!$B$10+(ROSTER!AD$4:AD$50="OC-EL")*CONFIG!$B$11+(ROSTER!AD$4:AD$50="OC-N")*CONFIG!$B$12+(ROSTER!AD$4:AD$50="ADM")*CONFIG!$B$9+(ROSTER!AD$4:AD$50="TRN")*CONFIG!$B$9+(ROSTER!AD$4:AD$50="BH-D")*CONFIG!$B$11+(ROSTER!AD$4:AD$50="BH-N")*CONFIG!$B$12)*ROSTER!$AG$4:$AG$50) -> 1548.125 | D28: =SUMPRODUCT(((ROSTER!AD$4:AD$50="OC-E")*CONFIG!$B$9+(ROSTER!AD$4:AD$50="OC-L")*CONFIG!$B$10+(ROSTER!AD$4:AD$50="OC-EL")*CONFIG!$B$11+(ROSTER!AD$4:AD$50="OC-N")*CONFIG!$B$12))*CONFIG!$B$28 -> 0 | E28: =(COUNTIF(ROSTER!AD$4:AD$50,"AG-E")*CONFIG!$B$9+COUNTIF(ROSTER!AD$4:AD$50,"AG-L")*CONFIG!$B$10)*CONFIG!$B$29 -> 0 | F28: =COUNTIF(ROSTER!AD$4:AD$50,"AG-N")*CONFIG!$B$12*CONFIG!$B$30 -> 0 | G28: =SUMPRODUCT((ROSTER!AD$4:AD$50="BH-D")*CONFIG!$B$11*ROSTER!$AG$4:$AG$50*(CONFIG!$B$46-1))+SUMPRODUCT((ROSTER!AD$4:AD$50="BH-N")*CONFIG!$B$12*ROSTER!$AG$4:$AG$50*(CONFIG!$B$46-1)) -> 0 | H28: =C28+D28+E28+F28+G28 -> 1548.125 | I28: =I27+H28 -> 40125.25
A29: 27 | B29: Sat | C29: =SUMPRODUCT(((ROSTER!AE$4:AE$50="E")*CONFIG!$B$9+(ROSTER!AE$4:AE$50="L")*CONFIG!$B$10+(ROSTER!AE$4:AE$50="EL")*CONFIG!$B$11+(ROSTER!AE$4:AE$50="N")*CONFIG!$B$12+(ROSTER!AE$4:AE$50="OC-E")*CONFIG!$B$9+(ROSTER!AE$4:AE$50="OC-L")*CONFIG!$B$10+(ROSTER!AE$4:AE$50="OC-EL")*CONFIG!$B$11+(ROSTER!AE$4:AE$50="OC-N")*CONFIG!$B$12+(ROSTER!AE$4:AE$50="ADM")*CONFIG!$B$9+(ROSTER!AE$4:AE$50="TRN")*CONFIG!$B$9+(ROSTER!AE$4:AE$50="BH-D")*CONFIG!$B$11+(ROSTER!AE$4:AE$50="BH-N")*CONFIG!$B$12)*ROSTER!$AG$4:$AG$50) -> 1548.125 | D29: =SUMPRODUCT(((ROSTER!AE$4:AE$50="OC-E")*CONFIG!$B$9+(ROSTER!AE$4:AE$50="OC-L")*CONFIG!$B$10+(ROSTER!AE$4:AE$50="OC-EL")*CONFIG!$B$11+(ROSTER!AE$4:AE$50="OC-N")*CONFIG!$B$12))*CONFIG!$B$28 -> 0 | E29: =(COUNTIF(ROSTER!AE$4:AE$50,"AG-E")*CONFIG!$B$9+COUNTIF(ROSTER!AE$4:AE$50,"AG-L")*CONFIG!$B$10)*CONFIG!$B$29 -> 0 | F29: =COUNTIF(ROSTER!AE$4:AE$50,"AG-N")*CONFIG!$B$12*CONFIG!$B$30 -> 0 | G29: =SUMPRODUCT((ROSTER!AE$4:AE$50="BH-D")*CONFIG!$B$11*ROSTER!$AG$4:$AG$50*(CONFIG!$B$46-1))+SUMPRODUCT((ROSTER!AE$4:AE$50="BH-N")*CONFIG!$B$12*ROSTER!$AG$4:$AG$50*(CONFIG!$B$46-1)) -> 0 | H29: =C29+D29+E29+F29+G29 -> 1548.125 | I29: =I28+H29 -> 41673.375
A30: 28 | B30: Sun | C30: =SUMPRODUCT(((ROSTER!AF$4:AF$50="E")*CONFIG!$B$9+(ROSTER!AF$4:AF$50="L")*CONFIG!$B$10+(ROSTER!AF$4:AF$50="EL")*CONFIG!$B$11+(ROSTER!AF$4:AF$50="N")*CONFIG!$B$12+(ROSTER!AF$4:AF$50="OC-E")*CONFIG!$B$9+(ROSTER!AF$4:AF$50="OC-L")*CONFIG!$B$10+(ROSTER!AF$4:AF$50="OC-EL")*CONFIG!$B$11+(ROSTER!AF$4:AF$50="OC-N")*CONFIG!$B$12+(ROSTER!AF$4:AF$50="ADM")*CONFIG!$B$9+(ROSTER!AF$4:AF$50="TRN")*CONFIG!$B$9+(ROSTER!AF$4:AF$50="BH-D")*CONFIG!$B$11+(ROSTER!AF$4:AF$50="BH-N")*CONFIG!$B$12)*ROSTER!$AG$4:$AG$50) -> 1548.125 | D30: =SUMPRODUCT(((ROSTER!AF$4:AF$50="OC-E")*CONFIG!$B$9+(ROSTER!AF$4:AF$50="OC-L")*CONFIG!$B$10+(ROSTER!AF$4:AF$50="OC-EL")*CONFIG!$B$11+(ROSTER!AF$4:AF$50="OC-N")*CONFIG!$B$12))*CONFIG!$B$28 -> 0 | E30: =(COUNTIF(ROSTER!AF$4:AF$50,"AG-E")*CONFIG!$B$9+COUNTIF(ROSTER!AF$4:AF$50,"AG-L")*CONFIG!$B$10)*CONFIG!$B$29 -> 0 | F30: =COUNTIF(ROSTER!AF$4:AF$50,"AG-N")*CONFIG!$B$12*CONFIG!$B$30 -> 0 | G30: =SUMPRODUCT((ROSTER!AF$4:AF$50="BH-D")*CONFIG!$B$11*ROSTER!$AG$4:$AG$50*(CONFIG!$B$46-1))+SUMPRODUCT((ROSTER!AF$4:AF$50="BH-N")*CONFIG!$B$12*ROSTER!$AG$4:$AG$50*(CONFIG!$B$46-1)) -> 0 | H30: =C30+D30+E30+F30+G30 -> 1548.125 | I30: =I29+H30 -> 43221.5
A31: 28-DAY TOTALS | C31: =SUM(C3:C30) -> 43221.5 | D31: =SUM(D3:D30) -> 0 | E31: =SUM(E3:E30) -> 0 | F31: =SUM(F3:F30) -> 0 | G31: =SUM(G3:G30) -> 0 | H31: =SUM(H3:H30) -> 43221.5
A33: COST BREAKDOWN
A34: Internal Staff (base) | B34: =C31 -> 43221.5
A35: OT Premium | B35: =D31 -> 0
A36: Agency Day | B36: =E31 -> 0
A37: Agency Night | B37: =F31 -> 0
A38: Bank Holiday Premium | B38: =G31 -> 0
A39: TOTAL 28-DAY | B39: =H31 -> 43221.5
A40: Agency % of Total | B40: =IF(H31>0,(E31+F31)/H31*100,0) -> 0

Sheet SCENARIO_MODEL
A1: STAFFING COST SCENARIOS (v7 — Fully Adaptive)
A2: All rates, counts, and costs dynamically linked to ROSTER, CONFIG, STAFF_DB, and DAILY_COSTS
A4: ASSUMPTIONS
A5: Total Active Staff | B5: =STAFF_DB!B38 -> 25 | D5: Adaptive: STAFF_DB
A6: Days in Period | B6: 28 | D6: 4-week rota cycle
A7: Day Shift Hours | B7: =CONFIG!B11 -> 12.25 | C7: hrs | D7: Adaptive: CONFIG
A8: Night Shift Hours | B8: =CONFIG!B12 -> 12.25 | C8: hrs | D8: Adaptive: CONFIG
A9: Avg Day Staff Rate | B9: =IFERROR(SUMPRODUCT((ROSTER!$AG$4:$AG$50)*(ROSTER!$C$4:$C$50<>"N")*(ROSTER!$B$4:$B$50<>"Float"))/COUNTIFS(ROSTER!$C$4:$C$50,"<>N",ROSTER!$B$4:$B$50,"<>Float"),0) -> 5.0394737 | C9: £/hr | D9: Adaptive: ROSTER rates
A10: Avg Night Staff Rate | B10: =IFERROR(SUMPRODUCT((ROSTER!$AG$4:$AG$50)*(ROSTER!$C$4:$C$50="N"))/COUNTIF(ROSTER!$C$4:$C$50,"N"),0) -> 12 | C10: £/hr | D10: Adaptive: ROSTER rates
A11: OT Premium | B11: =CONFIG!B28 -> 2 | C11: £/hr | D11: Adaptive: CONFIG
A12: Agency Day Rate | B12: =CONFIG!B29 -> 22 | C12: £/hr | D12: Adaptive: CONFIG
A13: Agency Night Rate | B13: =CONFIG!B30 -> 28 | C13: £/hr | D13: Adaptive: CONFIG
A14: Rostered Day Heads/day | B14: =IFERROR(SUMPRODUCT((ROSTER!$B$4:$B$50<>"Float")*(ROSTER!$C$4:$C$50<>"N")*(ROSTER!$B$4:$B$50<>""))/2,0) -> 8 | D14: Adaptive: ÷2 for Panama rotation
A15: Rostered Night Heads/day | B15: =IFERROR(SUMPRODUCT((ROSTER!$C$4:$C$50="N")*(ROSTER!$B$4:$B$50<>""))/2,0) -> 3 | D15: Adaptive: ÷2 for Panama rotation
A16: Float Pool Size | B16: =COUNTIF(ROSTER!$B$4:$B$50,"Float") -> 3 | D16: Adaptive: ROSTER
A17: Short-Week OT Pool | B17: 4 | D17: Input: max rested staff/day for OT
A18: Night Gap % (of total) | B18: =CONFIG!B52 -> 0.3 | C18: % | D18: Adaptive: CONFIG
A19: Float Deploy Rate | B19: =IFERROR(SUMPRODUCT((ROSTER!$AG$4:$AG$50)*(ROSTER!$B$4:$B$50="Float"))/COUNTIF(ROSTER!$B$4:$B$50,"Float"),0) -> 12 | C19: £/hr | D19: Adaptive: avg float rate
A22: SCENARIO | B22: Sick /day | C22: AL /day | D22: Total Gaps | E22: Float Fills | F22: OT Fills | G22: AG Day Fills | H22: AG Night Fills | I22: Base Staff £ (28d) | J22: Float Deploy £ (28d) | K22: OT Prem £ (28d) | L22: AG Day £ (28d) | M22: AG Night £ (28d) | N22: BH Prem £ (28d) | O22: TOTAL 28-DAY £ | P22: Monthly £ | Q22: ANNUAL £
A23: CLEAN (Zero disruption) | B23: 0 | C23: 0 | D23: =B23+C23 -> 0 | E23: =MIN(D23,$B$16) -> 0 | F23: =MIN(MAX(D23-E23,0),$B$17) -> 0 | G23: =ROUND(MAX(D23-E23-F23,0)*(1-$B$18),0) -> 0 | H23: =MAX(D23-E23-F23,0)-G23 -> 0 | I23: =DAILY_COSTS!C31 -> 43221.5 | J23: =E23*$B$7*$B$19*$B$6 -> 0 | K23: =F23*$B$7*$B$11*$B$6 -> 0 | L23: =G23*$B$7*$B$12*$B$6 -> 0 | M23: =H23*$B$8*$B$13*$B$6 -> 0 | N23: =DAILY_COSTS!G31 -> 0 | O23: =I23+J23+K23+L23+M23+N23 -> 43221.5 | P23: =O23/28*30.44 -> 46987.945 | Q23: =O23/28*365 -> 563423.12
A24: TYPICAL WEEK | B24: 1 | C24: 1 | D24: =B24+C24 -> 2 | E24: =MIN(D24,$B$16) -> 2 | F24: =MIN(MAX(D24-E24,0),$B$17) -> 0 | G24: =ROUND(MAX(D24-E24-F24,0)*(1-$B$18),0) -> 0 | H24: =MAX(D24-E24-F24,0)-G24 -> 0 | I24: =DAILY_COSTS!C31 -> 43221.5 | J24: =E24*$B$7*$B$19*$B$6 -> 8232 | K24: =F24*$B$7*$B$11*$B$6 -> 0 | L24: =G24*$B$7*$B$12*$B$6 -> 0 | M24: =H24*$B$8*$B$13*$B$6 -> 0 | N24: =DAILY_COSTS!G31 -> 0 | O24: =I24+J24+K24+L24+M24+N24 -> 51453.5 | P24: =O24/28*30.44 -> 55937.305 | Q24: =O24/28*365 -> 670733.12
A25: BAD WEEK | B25: 2 | C25: 2 | D25: =B25+C25 -> 4 | E25: =MIN(D25,$B$16) -> 3 | F25: =MIN(MAX(D25-E25,0),$B$17) -> 1 | G25: =ROUND(MAX(D25-E25-F25,0)*(1-$B$18),0) -> 0 | H25: =MAX(D25-E25-F25,0)-G25 -> 0 | I25: =DAILY_COSTS!C31 -> 43221.5 | J25: =E25*$B$7*$B$19*$B$6 -> 12348 | K25: =F25*$B$7*$B$11*$B$6 -> 686 | L25: =G25*$B$7*$B$12*$B$6 -> 0 | M25: =H25*$B$8*$B$13*$B$6 -> 0 | N25: =DAILY_COSTS!G31 -> 0 | O25: =I25+J25+K25+L25+M25+N25 -> 56255.5 | P25: =O25/28*30.44 -> 61157.765 | Q25: =O25/28*365 -> 733330.62
A26: CRISIS WEEK | B26: 3 | C26: 2 | D26: =B26+C26 -> 5 | E26: =MIN(D26,$B$16) -> 3 | F26: =MIN(MAX(D26-E26,0),$B$17) -> 2 | G26: =ROUND(MAX(D26-E26-F26,0)*(1-$B$18),0) -> 0 | H26: =MAX(D26-E26-F26,0)-G26 -> 0 | I26: =DAILY_COSTS!C31 -> 43221.5 | J26: =E26*$B$7*$B$19*$B$6 -> 12348 | K26: =F26*$B$7*$B$11*$B$6 -> 1372 | L26: =G26*$B$7*$B$12*$B$6 -> 0 | M26: =H26*$B$8*$B$13*$B$6 -> 0 | N26: =DAILY_COSTS!G31 -> 0 | O26: =I26+J26+K26+L26+M26+N26 -> 56941.5 | P26: =O26/28*30.44 -> 61903.545 | Q26: =O26/28*365 -> 742273.12
A27: WORST CASE (Winter/Flu) | B27: 4 | C27: 2 | D27: =B27+C27 -> 6 | E27: =MIN(D27,$B$16) -> 3 | F27: =MIN(MAX(D27-E27,0),$B$17) -> 3 | G27: =ROUND(MAX(D27-E27-F27,0)*(1-$B$18),0) -> 0 | H27: =MAX(D27-E27-F27,0)-G27 -> 0 | I27: =DAILY_COSTS!C31 -> 43221.5 | J27: =E27*$B$7*$B$19*$B$6 -> 12348 | K27: =F27*$B$7*$B$11*$B$6 -> 2058 | L27: =G27*$B$7*$B$12*$B$6 -> 0 | M27: =H27*$B$8*$B$13*$B$6 -> 0 | N27: =DAILY_COSTS!G31 -> 0 | O27: =I27+J27+K27+L27+M27+N27 -> 57627.5 | P27: =O27/28*30.44 -> 62649.325 | Q27: =O27/28*365 -> 751215.62
A28: PANDEMIC / NOROVIRUS | B28: 6 | C28: 2 | D28: =B28+C28 -> 8 | E28: =MIN(D28,$B$16) -> 3 | F28: =MIN(MAX(D28-E28,0),$B$17) -> 4 | G28: =ROUND(MAX(D28-E28-F28,0)*(1-$B$18),0) -> 1 | H28: =MAX(D28-E28-F28,0)-G28 -> 0 | I28: =DAILY_COSTS!C31 -> 43221.5 | J28: =E28*$B$7*$B$19*$B$6 -> 12348 | K28: =F28*$B$7*$B$11*$B$6 -> 2744 | L28: =G28*$B$7*$B$12*$B$6 -> 7546 | M28: =H28*$B$8*$B$13*$B$6 -> 0 | N28: =DAILY_COSTS!G31 -> 0 | O28: =I28+J28+K28+L28+M28+N28 -> 65859.5 | P28: =O28/28*30.44 -> 71598.685 | Q28: =O28/28*365 -> 858525.62
A30: AGENCY KILL IMPACT
A31: WITHOUT Agency Kill (all gaps → agency day + night split) | B31: =I24+D24*(1-$B$18)*$B$7*$B$12*$B$6+D24*$B$18*$B$8*$B$13*$B$6 -> 59548.3 | C31: 28-day | D31: =B31/28*365 -> 776254.62 | E31: /year
A32: WITH Agency Kill (float → OT → agency last) | B32: =O24 -> 51453.5 | C32: 28-day | D32: =B32/28*365 -> 670733.12
A34: ANNUAL SAVING PER HOME | B34: =D31-D32 -> 105521.5
A35: Across 10 homes | B35: =B34*10 -> 1055215
A36: Across 30 homes | B36: =B34*30 -> 3165645
A40: WINTER SCENARIOS (Weekly OT Cap)
A42: Scenario | B42: Gaps/d | C42: ×7 | D42: Float/wk | E42: OT/wk cap | F42: Agency/wk | G42: Ag £/wk
A43: WINTER TYPICAL | B43: 3 | C43: =B43*7 -> 21 | D43: =MIN(C43,15) -> 15 | E43: =MIN(MAX(C43-D43,0),CONFIG!$B$59) -> 6 | F43: =MAX(C43-D43-E43,0) -> 0 | G43: =(F43*0.7*12.25*CONFIG!$B$29+F43*0.3*12.25*CONFIG!$B$30) -> 0
A44: WINTER BAD | B44: 5 | C44: =B44*7 -> 35 | D44: =MIN(C44,15) -> 15 | E44: =MIN(MAX(C44-D44,0),CONFIG!$B$59) -> 8 | F44: =MAX(C44-D44-E44,0) -> 12 | G44: =(F44*0.7*12.25*CONFIG!$B$29+F44*0.3*12.25*CONFIG!$B$30) -> 3498.6
A45: WINTER CRISIS | B45: 7 | C45: =B45*7 -> 49 | D45: =MIN(C45,15) -> 15 | E45: =MIN(MAX(C45-D45,0),CONFIG!$B$59) -> 8 | F45: =MAX(C45-D45-E45,0) -> 26 | G45: =(F45*0.7*12.25*CONFIG!$B$29+F45*0.3*12.25*CONFIG!$B$30) -> 7580.3
A46: WINTER WORST | B46: 9 | C46: =B46*7 -> 63 | D46: =MIN(C46,15) -> 15 | E46: =MIN(MAX(C46-D46,0),CONFIG!$B$59) -> 8 | F46: =MAX(C46-D46-E46,0) -> 40 | G46: =(F46*0.7*12.25*CONFIG!$B$29+F46*0.3*12.25*CONFIG!$B$30) -> 11662
A47: NOROVIRUS PEAK | B47: 9 | C47: =B47*7 -> 63 | D47: =MIN(C47,15) -> 15 | E47: =MIN(MAX(C47-D47,0),CONFIG!$B$59) -> 8 | F47: =MAX(C47-D47-E47,0) -> 40 | G47: =(F47*0.7*12.25*CONFIG!$B$29+F47*0.3*12.25*CONFIG!$B$30) -> 11662

Sheet BEFORE_VS_AFTER
A1: BEFORE vs AFTER: THE ACQUISITION BUSINESS CASE
A2: Drop in real numbers from target home. Use in pitch deck and seller meetings.
A4: CURRENT STATE (Seller's Operation)
A5: Total Beds | B5: 40 | D5: Blue = editable input
A6: Occupancy Rate | B6: 0.85 | C6: %
A7: Private Pay Mix | B7: 0.15 | C7: %
A8: Council Weekly Fee | B8: 750 | C8: £/wk | D8: Local authority funded
A9: Private Weekly Fee | B9: 1100 | C9: £/wk | D9: Self-funder rate
A10: Agency Dependency | B10: 0.25 | C10: % | D10: % of shifts filled by agency
A11: Avg Shifts Needing Cover/day | B11: 2.5 | D11: Sick + AL + vacancies
A12: Avg Staff Rate | B12: 11.86 | C12: £/hr
A13: Agency Rate (Day) | B13: =CONFIG!B29 -> 22 | C13: £/hr
A14: Shift Length (Day) | B14: =CONFIG!B11 -> 12.25 | C14: hrs
A15: Agency Rate (Night) | B15: =CONFIG!B30 -> 28 | C15: £/hr
A16: Night Shift Length | B16: =CONFIG!B12 -> 12.25 | C16: hrs
A17: Occupied Beds | B17: =B5*B6 -> 34
A18: Council Beds | B18: =B17*(1-B7) -> 28.9
A19: Private Beds | B19: =B17*B7 -> 5.1
A20: Annual Revenue | B20: =(B18*B8+B19*B9)*52 -> 1418820
A21: Annual Agency Spend | B21: =B11*B10*((1-CONFIG!B52)*B13*B14+CONFIG!B52*B15*B16)*365 -> 66509.844
A22: Annual Base Staff Cost | B22: =DAILY_COSTS!C31/28*365 -> 563423.12
A23: Total Annual Staff Cost | B23: =B21+B22 -> 629932.97
A24: Est. Annual EBITDA | B24: =B20*0.18 -> 255387.6
A25: EBITDA Margin | B25: =B24/B20 -> 0.18
A28: PROJECTED STATE (12 Months Under Our Management)
A29: Total Beds | B29: =B5 -> 40 | D29: Same facility
A30: Occupancy Rate | B30: 0.92 | C30: % | D30: Marketing funnel impact
A31: Private Pay Mix | B31: 0.35 | C31: % | D31: Lead magnet + ads + funnel
A32: Council Weekly Fee | B32: =B8 -> 750 | C32: £/wk | D32: Same rates
A33: Private Weekly Fee | B33: 1200 | C33: £/wk | D33: Premium positioning
A34: Agency Dependency | B34: 0.05 | C34: % | D34: Panama + Agency Kill
A35: Avg Shifts Needing Cover/day | B35: 1.5 | D35: Better retention = fewer gaps
A36: Avg Staff Rate | B36: 12.2 | C36: £/hr | D36: Slight increase for retention
A37: Agency Rate (Day) | B37: =B13 -> 22 | C37: £/hr | D37: Same market rate
A38: Shift Length (Day) | B38: =B14 -> 12.25 | C38: hrs
A39: Agency Rate (Night) | B39: =B15 -> 28 | C39: £/hr
A40: Night Shift Length | B40: =B16 -> 12.25 | C40: hrs
A41: Occupied Beds | B41: =B29*B30 -> 36.8
A42: CALCULATED METRICS | B42: =B41*(1-B31) -> 23.92
A43: Occupied Beds | B43: =B29*B30 -> 36.8
A44: Council Beds | B44: =B43*(1-B31) -> 23.92
A45: Private Beds | B45: =B43*B31 -> 12.88
A46: Annual Revenue | B46: =(B44*B32+B45*B33)*52 -> 1736592
A47: Annual Agency Spend | B47: =B35*B34*((1-CONFIG!B52)*B37*B38+CONFIG!B52*B39*B40)*365 -> 7981.1812
A48: Annual Base Staff Cost | B48: =B22*(1+(B36-B12)/B12) -> 579575.22
A49: Total Annual Staff Cost | B49: =B47+B48 -> 587556.4
A50: Est. Annual EBITDA | B50: =B46*0.28 -> 486245.76
A51: EBITDA Margin | B51: =B50/B46 -> 0.28
A52: VALUE CREATION SUMMARY
A53: Revenue Uplift | B53: =B44-B20 -> -1418796.1
A54: VALUE CREATION SUMMARY | B54: =B48-B24 -> 324187.62
A55: Revenue Uplift | B55: =B46-B20 -> 317772
A56: EBITDA Uplift | B56: =B50-B24 -> 230858.16
A57: Agency Cost Reduction | B57: =B21-B47 -> 58528.662
A58: Agency Dependency Reduction | B58: =B10-B34 -> 0.2
A60: ENTERPRISE VALUE IMPACT
A61: EBITDA Multiple | B61: 6 | C61: x (editable)
A62: Before EV | B62: =B24*B61 -> 1532325.6 | C62: x (editable)
A63: After EV | B63: =B50*B61 -> 2917474.6
A64: VALUE CREATED PER HOME | B64: =B63-B62 -> 1385149
A65: VALUE CREATED PER HOME | B65: =B64-B63 -> -1532325.6
A66: Value across 10 homes | B66: =B64*10 -> 13851490
A67: Value across 30 homes | B67: =B64*30 -> 41554469
A68: Value across 30 homes | B68: =B65*30 -> -45969768

Sheet AGENCY_KILL_GUIDE
A1: THE "AGENCY KILLER" PROTOCOL
A3: SHIFT TIMES (with 15-min Paid Handover)
A4: Day Shift: 07:45-20:00 (12.25 paid hours)
A5: Night Shift: 19:45-08:00 (12.25 paid hours)
A6: Morning Handover: 07:45-08:00 (15 mins overlap)
A7: Evening Handover: 19:45-20:00 (15 mins overlap)
A8: Breaks: PAID (no deduction)
A10: CORE CONCEPT
A11: The Panama 2-2-3 rotation creates natural "short weeks" for each team.
A12: During a short week, staff work only 2 days (24.5 hours) instead of 5 days (61.25 hours).
A13: These staff are RESTED and UNDER-HOURS. They are your Agency Kill targets.
A15: THE PATTERN (14-day cycle)
B16: Mon | C16: Tue | D16: Wed | E16: Thu | F16: Fri | G16: Sat | H16: Sun
A17: Week 1 - Day A | B17: ON | C17: ON | D17: off | E17: off | F17: ON | G17: ON | H17: ON
A18: Week 1 - Day B | B18: off | C18: off | D18: ON | E18: ON | F18: off | G18: off | H18: off
A19: Week 2 - Day A | B19: off | C19: off | D19: ON | E19: ON | F19: off | G19: off | H19: off
A20: Week 2 - Day B | B20: ON | C20: ON | D20: off | E20: off | F20: ON | G20: ON | H20: ON
A21: (Night teams follow same pattern)
A23: WEEKLY HOURS BREAKDOWN
A24: Long Week (5 days × 12.25hrs): 61.25 hours
A25: Short Week (2 days × 12.25hrs): 24.5 hours
A26: Average per week: 42.875 hours (full-time)
A28: AGENCY KILL TARGETS
A29: Week 1: Day B staff are on short week (only Wed-Thu) → Target them for gaps Mon/Tue/Fri-Sun
A30: Week 2: Day A staff are on short week (only Wed-Thu) → Target them for gaps Mon/Tue/Fri-Sun
A32: GOLD SQUARES IN ROSTER
A33: Any "OFF" cell highlighted in GOLD = This person is:
A34: • On their short week (rested)
A35: • Under their normal hours (hungry for money)
... A73: Both teams are PAID for the 15-min handover overlap.

Sheet FATIGUE_TRACKER
A1: FATIGUE MONITOR (v7 — Float-Aware)
A2: Counts consecutive WORKING days. Float AVL = rest. Float deployed (any work code) = working.
A3: Name | B3: Team | C3: D1 | D3: D2 | E3: D3 | F3: D4 | G3: D5 | H3: D6 | I3: D7 | J3: D8 | K3: D9 | L3: D10 | M3: D11 | N3: D12 | O3: D13 | P3: D14 | Q3: D15 | R3: D16 | S3: D17 | T3: D18 | U3: D19 | V3: D20 | W3: D21 | X3: D22 | Y3: D23 | Z3: D24 | AA3: D25 | AB3: D26 | AC3: D27 | AD3: D28 | AE3: Max Run | AF3: Status | AG3: Wk Avg | AH3: WTR
A4: =ROSTER!A4 -> Alice Johnson | B4: =ROSTER!B4 -> Day A | C4: =IF(OR(ROSTER!E4="OFF",ROSTER!E4="AL",ROSTER!E4="SICK",ROSTER!E4="AVL",ROSTER!E4=""),0,1) -> 1 | D4: =IF(OR(ROSTER!F4="OFF",ROSTER!F4="AL",ROSTER!F4="SICK",ROSTER!F4="AVL",ROSTER!F4=""),0,C4+1) -> 2 | E4: =IF(OR(ROSTER!G4="OFF",ROSTER!G4="AL",ROSTER!G4="SICK",ROSTER!G4="AVL",ROSTER!G4=""),0,D4+1) -> 0 | F4: =IF(OR(ROSTER!H4="OFF",ROSTER!H4="AL",ROSTER!H4="SICK",ROSTER!H4="AVL",ROSTER!H4=""),0,E4+1) -> 0 | G4: =IF(OR(ROSTER!I4="OFF",ROSTER!I4="AL",ROSTER!I4="SICK",ROSTER!I4="AVL",ROSTER!I4=""),0,F4+1) -> 1 | H4: =IF(OR(ROSTER!J4="OFF",ROSTER!J4="AL",ROSTER!J4="SICK",ROSTER!J4="AVL",ROSTER!J4=""),0,G4+1) -> 2 | I4: =IF(OR(ROSTER!K4="OFF",ROSTER!K4="AL",ROSTER!K4="SICK",ROSTER!K4="AVL",ROSTER!K4=""),0,H4+1) -> 3 | J4: =IF(OR(ROSTER!L4="OFF",ROSTER!L4="AL",ROSTER!L4="SICK",ROSTER!L4="AVL",ROSTER!L4=""),0,I4+1) -> 0 | K4: =IF(OR(ROSTER!M4="OFF",ROSTER!M4="AL",ROSTER!M4="SICK",ROSTER!M4="AVL",ROSTER!M4=""),0,J4+1) -> 0 | ... AD4: =IF(OR(ROSTER!AF4="OFF",ROSTER!AF4="AL",ROSTER!AF4="SICK",ROSTER!AF4="AVL",ROSTER!AF4=""),0,AC4+1) -> 0 | AE4: =MAX(C4:AD4) -> 3 | AF4: =IF(AE4>=CONFIG!$B$33,"🟣 BLOCK OT",IF(AE4>=4,"⚠️ MONITOR","✅ OK")) -> ✅ OK | AG4: =ROSTER!AP4 -> 42.875 | AH4: =ROSTER!AQ4 -> ✅ OK
A5: =ROSTER!A5 -> Bob Smith | B5: =ROSTER!B5 -> Day A | C5: =IF(OR(ROSTER!E5="OFF",ROSTER!E5="AL",ROSTER!E5="SICK",ROSTER!E5="AVL",ROSTER!E5=""),0,1) -> 1 | D5: =IF(OR(ROSTER!F5="OFF",ROSTER!F5="AL",ROSTER!F5="SICK",ROSTER!F5="AVL",ROSTER!F5=""),0,C5+1) -> 2 | E5: =IF(OR(ROSTER!G5="OFF",ROSTER!G5="AL",ROSTER!G5="SICK",ROSTER!G5="AVL",ROSTER!G5=""),0,D5+1) -> 0 | F5: =IF(OR(ROSTER!H5="OFF",ROSTER!H5="AL",ROSTER!H5="SICK",ROSTER!H5="AVL",ROSTER!H5=""),0,E5+1) -> 0 | G5: =IF(OR(ROSTER!I5="OFF",ROSTER!I5="AL",ROSTER!I5="SICK",ROSTER!I5="AVL",ROSTER!I5=""),0,F5+1) -> 1 | H5: =IF(OR(ROSTER!J5="OFF",ROSTER!J5="AL",ROSTER!J5="SICK",ROSTER!J5="AVL",ROSTER!J5=""),0,G5+1) -> 2 | I5: =IF(OR(ROSTER!K5="OFF",ROSTER!K5="AL",ROSTER!K5="SICK",ROSTER!K5="AVL",ROSTER!K5=""),0,H5+1) -> 3 | J5: =IF(OR(ROSTER!L5="OFF",ROSTER!L5="AL",ROSTER!L5="SICK",ROSTER!L5="AVL",ROSTER!L5=""),0,I5+1) -> 0 | K5: =IF(OR(ROSTER!M5="OFF",ROSTER!M5="AL",ROSTER!M5="SICK",ROSTER!M5="AVL",ROSTER!M5=""),0,J5+1) -> 0 | ... AD5: =IF(OR(ROSTER!AF5="OFF",ROSTER!AF5="AL",ROSTER!AF5="SICK",ROSTER!AF5="AVL",ROSTER!AF5=""),0,AC5+1) -> 0 | AE5: =MAX(C5:AD5) -> 3 | AF5: =IF(AE5>=CONFIG!$B$33,"🟣 BLOCK OT",IF(AE5>=4,"⚠️ MONITOR","✅ OK")) -> ✅ OK | AG5: =ROSTER!AP5 -> 42.875 | AH5: =ROSTER!AQ5 -> ✅ OK
A6: =ROSTER!A6 -> Carol Davis | B6: =ROSTER!B6 -> Day A | C6: =IF(OR(ROSTER!E6="OFF",ROSTER!E6="AL",ROSTER!E6="SICK",ROSTER!E6="AVL",ROSTER!E6=""),0,1) -> 1 | D6: =IF(OR(ROSTER!F6="OFF",ROSTER!F6="AL",ROSTER!F6="SICK",ROSTER!F6="AVL",ROSTER!F6=""),0,C6+1) -> 2 | E6: =IF(OR(ROSTER!G6="OFF",ROSTER!G6="AL",ROSTER!G6="SICK",ROSTER!G6="AVL",ROSTER!G6=""),0,D6+1) -> 0 | F6: =IF(OR(ROSTER!H6="OFF",ROSTER!H6="AL",ROSTER!H6="SICK",ROSTER!H6="AVL",ROSTER!H6=""),0,E6+1) -> 0 | G6: =IF(OR(ROSTER!I6="OFF",ROSTER!I6="AL",ROSTER!I6="SICK",ROSTER!I6="AVL",ROSTER!I6=""),0,F6+1) -> 1 | H6: =IF(OR(ROSTER!J6="OFF",ROSTER!J6="AL",ROSTER!J6="SICK",ROSTER!J6="AVL",ROSTER!J6=""),0,G6+1) -> 2 | I6: =IF(OR(ROSTER!K6="OFF",ROSTER!K6="AL",ROSTER!K6="SICK",ROSTER!K6="AVL",ROSTER!K6=""),0,H6+1) -> 3 | J6: =IF(OR(ROSTER!L6="OFF",ROSTER!L6="AL",ROSTER!L6="SICK",ROSTER!L6="AVL",ROSTER!L6=""),0,I6+1) -> 0 | K6: =IF(OR(ROSTER!M6="OFF",ROSTER!M6="AL",ROSTER!M6="SICK",ROSTER!M6="AVL",ROSTER!M6=""),0,J6+1) -> 0 | ... AD6: =IF(OR(ROSTER!AF6="OFF",ROSTER!AF6="AL",ROSTER!AF6="SICK",ROSTER!AF6="AVL",ROSTER!AF6=""),0,AC6+1) -> 0 | AE6: =MAX(C6:AD6) -> 3 | AF6: =IF(AE6>=CONFIG!$B$33,"🟣 BLOCK OT",IF(AE6>=4,"⚠️ MONITOR","✅ OK")) -> ✅ OK | AG6: =ROSTER!AP6 -> 42.875 | AH6: =ROSTER!AQ6 -> ✅ OK
A7: =ROSTER!A7 -> David Wilson | B7: =ROSTER!B7 -> Day A | C7: =IF(OR(ROSTER!E7="OFF",ROSTER!E7="AL",ROSTER!E7="SICK",ROSTER!E7="AVL",ROSTER!E7=""),0,1) -> 1 | D7: =IF(OR(ROSTER!F7="OFF",ROSTER!F7="AL",ROSTER!F7="SICK",ROSTER!F7="AVL",ROSTER!F7=""),0,C7+1) -> 2 | E7: =IF(OR(ROSTER!G7="OFF",ROSTER!G7="AL",ROSTER!G7="SICK",ROSTER!G7="AVL",ROSTER!G7=""),0,D7+1) -> 0 | F7: =IF(OR(ROSTER!H7="OFF",ROSTER!H7="AL",ROSTER!H7="SICK",ROSTER!H7="AVL",ROSTER!H7=""),0,E7+1) -> 0 | G7: =IF(OR(ROSTER!I7="OFF",ROSTER!I7="AL",ROSTER!I7="SICK",ROSTER!I7="AVL",ROSTER!I7=""),0,F7+1) -> 1 | H7: =IF(OR(ROSTER!J7="OFF",ROSTER!J7="AL",ROSTER!J7="SICK",ROSTER!J7="AVL",ROSTER!J7=""),0,G7+1) -> 2 | I7: =IF(OR(ROSTER!K7="OFF",ROSTER!K7="AL",ROSTER!K7="SICK",ROSTER!K7="AVL",ROSTER!K7=""),0,H7+1) -> 3 | J7: =IF(OR(ROSTER!L7="OFF",ROSTER!L7="AL",ROSTER!L7="SICK",ROSTER!L7="AVL",ROSTER!L7=""),0,I7+1) -> 0 | K7: =IF(OR(ROSTER!M7="OFF",ROSTER!M7="AL",ROSTER!M7="SICK",ROSTER!M7="AVL",ROSTER!M7=""),0,J7+1) -> 0 | ... AD7: =IF(OR(ROSTER!AF7="OFF",ROSTER!AF7="AL",ROSTER!AF7="SICK",ROSTER!AF7="AVL",ROSTER!AF7=""),0,AC7+1) -> 0 | AE7: =MAX(C7:AD7) -> 3 | AF7: =IF(AE7>=CONFIG!$B$33,"🟣 BLOCK OT",IF(AE7>=4,"⚠️ MONITOR","✅ OK")) -> ✅ OK | AG7: =ROSTER!AP7 -> 42.875 | AH7: =ROSTER!AQ7 -> ✅ OK
A8: =ROSTER!A8 -> Emma Brown | B8: =ROSTER!B8 -> Day A | C8: =IF(OR(ROSTER!E8="OFF",ROSTER!E8="AL",ROSTER!E8="SICK",ROSTER!E8="AVL",ROSTER!E8=""),0,1) -> 1 | D8: =IF(OR(ROSTER!F8="OFF",ROSTER!F8="AL",ROSTER!F8="SICK",ROSTER!F8="AVL",ROSTER!F8=""),0,C8+1) -> 2 | E8: =IF(OR(ROSTER!G8="OFF",ROSTER!G8="AL",ROSTER!G8="SICK",ROSTER!G8="AVL",ROSTER!G8=""),0,D8+1) -> 0 | F8: =IF(OR(ROSTER!H8="OFF",ROSTER!H8="AL",ROSTER!H8="SICK",ROSTER!H8="AVL",ROSTER!H8=""),0,E8+1) -> 0 | G8: =IF(OR(ROSTER!I8="OFF",ROSTER!I8="AL",ROSTER!I8="SICK",ROSTER!I8="AVL",ROSTER!I8=""),0,F8+1) -> 1 | H8: =IF(OR(ROSTER!J8="OFF",ROSTER!J8="AL",ROSTER!J8="SICK",ROSTER!J8="AVL",ROSTER!J8=""),0,G8+1) -> 2 | I8: =IF(OR(ROSTER!K8="OFF",ROSTER!K8="AL",ROSTER!K8="SICK",ROSTER!K8="AVL",ROSTER!K8=""),0,H8+1) -> 3 | J8: =IF(OR(ROSTER!L8="OFF",ROSTER!L8="AL",ROSTER!L8="SICK",ROSTER!L8="AVL",ROSTER!L8=""),0,I8+1) -> 0 | K8: =IF(OR(ROSTER!M8="OFF",ROSTER!M8="AL",ROSTER!M8="SICK",ROSTER!M8="AVL",ROSTER!M8=""),0,J8+1) -> 0 | ... AD8: =IF(OR(ROSTER!AF8="OFF",ROSTER!AF8="AL",ROSTER!AF8="SICK",ROSTER!AF8="AVL",ROSTER!AF8=""),0,AC8+1) -> 0 | AE8: =MAX(C8:AD8) -> 3 | AF8: =IF(AE8>=CONFIG!$B$33,"🟣 BLOCK OT",IF(AE8>=4,"⚠️ MONITOR","✅ OK")) -> ✅ OK | AG8: =ROSTER!AP8 -> 42.875 | AH8: =ROSTER!AQ8 -> ✅ OK
A9: =ROSTER!A9 -> Fiona Hart | B9: =ROSTER!B9 -> Day A | C9: =IF(OR(ROSTER!E9="OFF",ROSTER!E9="AL",ROSTER!E9="SICK",ROSTER!E9="AVL",ROSTER!E9=""),0,1) -> 1 | D9: =IF(OR(ROSTER!F9="OFF",ROSTER!F9="AL",ROSTER!F9="SICK",ROSTER!F9="AVL",ROSTER!F9=""),0,C9+1) -> 2 | E9: =IF(OR(ROSTER!G9="OFF",ROSTER!G9="AL",ROSTER!G9="SICK",ROSTER!G9="AVL",ROSTER!G9=""),0,D9+1) -> 0 | F9: =IF(OR(ROSTER!H9="OFF",ROSTER!H9="AL",ROSTER!H9="SICK",ROSTER!H9="AVL",ROSTER!H9=""),0,E9+1) -> 0 | G9: =IF(OR(ROSTER!I9="OFF",ROSTER!I9="AL",ROSTER!I9="SICK",ROSTER!I9="AVL",ROSTER!I9=""),0,F9+1) -> 1 | H9: =IF(OR(ROSTER!J9="OFF",ROSTER!J9="AL",ROSTER!J9="SICK",ROSTER!J9="AVL",ROSTER!J9=""),0,G9+1) -> 2 | I9: =IF(OR(ROSTER!K9="OFF",ROSTER!K9="AL",ROSTER!K9="SICK",ROSTER!K9="AVL",ROSTER!K9=""),0,H9+1) -> 3 | J9: =IF(OR(ROSTER!L9="OFF",ROSTER!L9="AL",ROSTER!L9="SICK",ROSTER!L9="AVL",ROSTER!L9=""),0,I9+1) -> 0 | K9: =IF(OR(ROSTER!M9="OFF",ROSTER!M9="AL",ROSTER!M9="SICK",ROSTER!M9="AVL",ROSTER!M9=""),0,J9+1) -> 0 | ... AD9: =IF(OR(ROSTER!AF9="OFF",ROSTER!AF9="AL",ROSTER!AF9="SICK",ROSTER!AF9="AVL",ROSTER!AF9=""),0,AC9+1) -> 0 | AE9: =MAX(C9:AD9) -> 3 | AF9: =IF(AE9>=CONFIG!$B$33,"🟣 BLOCK OT",IF(AE9>=4,"⚠️ MONITOR","✅ OK")) -> ✅ OK | AG9: =ROSTER!AP9 -> 42.875 | AH9: =ROSTER!AQ9 -> ✅ OK
A10: =ROSTER!A10 -> George King | B10: =ROSTER!B10 -> Day A | C10: =IF(OR(ROSTER!E10="OFF",ROSTER!E10="AL",ROSTER!E10="SICK",ROSTER!E10="AVL",ROSTER!E10=""),0,1) -> 1 | D10: =IF(OR(ROSTER!F10="OFF",ROSTER!F10="AL",ROSTER!F10="SICK",ROSTER!F10="AVL",ROSTER!F10=""),0,C10+1) -> 2 | E10: =IF(OR(ROSTER!G10="OFF",ROSTER!G10="AL",ROSTER!G10="SICK",ROSTER!G10="AVL",ROSTER!G10=""),0,D10+1) -> 0 | F10: =IF(OR(ROSTER!H10="OFF",ROSTER!H10="AL",ROSTER!H10="SICK",ROSTER!H10="AVL",ROSTER!H10=""),0,E10+1) -> 0 | G10: =IF(OR(ROSTER!I10="OFF",ROSTER!I10="AL",ROSTER!I10="SICK",ROSTER!I10="AVL",ROSTER!I10=""),0,F10+1) -> 1 | H10: =IF(OR(ROSTER!J10="OFF",ROSTER!J10="AL",ROSTER!J10="SICK",ROSTER!J10="AVL",ROSTER!J10=""),0,G10+1) -> 2 | I10: =IF(OR(ROSTER!K10="OFF",ROSTER!K10="AL",ROSTER!K10="SICK",ROSTER!K10="AVL",ROSTER!K10=""),0,H10+1) -> 3 | J10: =IF(OR(ROSTER!L10="OFF",ROSTER!L10="AL",ROSTER!L10="SICK",ROSTER!L10="AVL",ROSTER!L10=""),0,I10+1) -> 0 | K10: =IF(OR(ROSTER!M10="OFF",ROSTER!M10="AL",ROSTER!M10="SICK",ROSTER!M10="AVL",ROSTER!M10=""),0,J10+1) -> 0 | ... AD10: =IF(OR(ROSTER!AF10="OFF",ROSTER!AF10="AL",ROSTER!AF10="SICK",ROSTER!AF10="AVL",ROSTER!AF10=""),0,AC10+1) -> 0 | AE10: =MAX(C10:AD10) -> 3 | AF10: =IF(AE10>=CONFIG!$B$33,"🟣 BLOCK OT",IF(AE10>=4,"⚠️ MONITOR","✅ OK")) -> ✅ OK | AG10: =ROSTER!AP10 -> 42.875 | AH10: =ROSTER!AQ10 -> ✅ OK
A11: =ROSTER!A11 -> Hannah Lee | B11: =ROSTER!B11 -> Day B | C11: =IF(OR(ROSTER!E11="OFF",ROSTER!E11="AL",ROSTER!E11="SICK",ROSTER!E11="AVL",ROSTER!E11=""),0,1) -> 0 | D11: =IF(OR(ROSTER!F11="OFF",ROSTER!F11="AL",ROSTER!F11="SICK",ROSTER!F11="AVL",ROSTER!F11=""),0,C11+1) -> 0 | E11: =IF(OR(ROSTER!G11="OFF",ROSTER!G11="AL",ROSTER!G11="SICK",ROSTER!G11="AVL",ROSTER!G11=""),0,D11+1) -> 1 | F11: =IF(OR(ROSTER!H11="OFF",ROSTER!H11="AL",ROSTER!H11="SICK",ROSTER!H11="AVL",ROSTER!H11=""),0,E11+1) -> 2 | G11: =IF(OR(ROSTER!I11="OFF",ROSTER!I11="AL",ROSTER!I11="SICK",ROSTER!I11="AVL",ROSTER!I11=""),0,F11+1) -> 0 | H11: =IF(OR(ROSTER!J11="OFF",ROSTER!J11="AL",ROSTER!J11="SICK",ROSTER!J11="AVL",ROSTER!J11=""),0,G11+1) -> 0 | I11: =IF(OR(ROSTER!K11="OFF",ROSTER!K11="AL",ROSTER!K11="SICK",ROSTER!K11="AVL",ROSTER!K11=""),0,H11+1) -> 0 | J11: =IF(OR(ROSTER!L11="OFF",ROSTER!L11="AL",ROSTER!L11="SICK",ROSTER!L11="AVL",ROSTER!L11=""),0,I11+1) -> 1 | K11: =IF(OR(ROSTER!M11="OFF",ROSTER!M11="AL",ROSTER!M11="SICK",ROSTER!M11="AVL",ROSTER!M11=""),0,J11+1) -> 2 | ... AD11: =IF(OR(ROSTER!AF11="OFF",ROSTER!AF11="AL",ROSTER!AF11="SICK",ROSTER!AF11="AVL",ROSTER!AF11=""),0,AC11+1) -> 3 | AE11: =MAX(C11:AD11) -> 3 | AF11: =IF(AE11>=CONFIG!$B$33,"🟣 BLOCK OT",IF(AE11>=4,"⚠️ MONITOR","✅ OK")) -> ✅ OK | AG11: =ROSTER!AP11 -> 42.875 | AH11: =ROSTER!AQ11 -> ✅ OK
A12: =ROSTER!A12 -> Ian Clark | B12: =ROSTER!B12 -> Day B | C12: =IF(OR(ROSTER!E12="OFF",ROSTER!E12="AL",ROSTER!E12="SICK",ROSTER!E12="AVL",ROSTER!E12=""),0,1) -> 0 | D12: =IF(OR(ROSTER!F12="OFF",ROSTER!F12="AL",ROSTER!F12="SICK",ROSTER!F12="AVL",ROSTER!F12=""),0,C12+1) -> 0 | E12: =IF(OR(ROSTER!G12="OFF",ROSTER!G12="AL",ROSTER!G12="SICK",ROSTER!G12="AVL",ROSTER!G12=""),0,D12+1) -> 1 | F12: =IF(OR(ROSTER!H12="OFF",ROSTER!H12="AL",ROSTER!H12="SICK",ROSTER!H12="AVL",ROSTER!H12=""),0,E12+1) -> 2 | G12: =IF(OR(ROSTER!I12="OFF",ROSTER!I12="AL",ROSTER!I12="SICK",ROSTER!I12="AVL",ROSTER!I12=""),0,F12+1) -> 0 | H12: =IF(OR(ROSTER!J12="OFF",ROSTER!J12="AL",ROSTER!J12="SICK",ROSTER!J12="AVL",ROSTER!J12=""),0,G12+1) -> 0 | I12: =IF(OR(ROSTER!K12="OFF",ROSTER!K12="AL",ROSTER!K12="SICK",ROSTER!K12="AVL",ROSTER!K12=""),0,H12+1) -> 0 | J12: =IF(OR(ROSTER!L12="OFF",ROSTER!L12="AL",ROSTER!L12="SICK",ROSTER!L12="AVL",ROSTER!L12=""),0,I12+1) -> 1 | K12: =IF(OR(ROSTER!M12="OFF",ROSTER!M12="AL",ROSTER!M12="SICK",ROSTER!M12="AVL",ROSTER!M12=""),0,J12+1) -> 2 | ... AD12: =IF(OR(ROSTER!AF12="OFF",ROSTER!AF12="AL",ROSTER!AF12="SICK",ROSTER!AF12="AVL",ROSTER!AF12=""),0,AC12+1) -> 3 | AE12: =MAX(C12:AD12) -> 3 | AF12: =IF(AE12>=CONFIG!$B$33,"🟣 BLOCK OT",IF(AE12>=4,"⚠️ MONITOR","✅ OK")) -> ✅ OK | AG12: =ROSTER!AP12 -> 42.875 | AH12: =ROSTER!AQ12 -> ✅ OK
A13: =ROSTER!A13 -> Julia Martin | B13: =ROSTER!B13 -> Day B | C13: =IF(OR(ROSTER!E13="OFF",ROSTER!E13="AL",ROSTER!E13="SICK",ROSTER!E13="AVL",ROSTER!E13=""),0,1) -> 0 | D13: =IF(OR(ROSTER!F13="OFF",ROSTER!F13="AL",ROSTER!F13="SICK",ROSTER!F13="AVL",ROSTER!F13=""),0,C13+1) -> 0 | E13: =IF(OR(ROSTER!G13="OFF",ROSTER!G13="AL",ROSTER!G13="SICK",ROSTER!G13="AVL",ROSTER!G13=""),0,D13+1) -> 1 | F13: =IF(OR(ROSTER!H13="OFF",ROSTER!H13="AL",ROSTER!H13="SICK",ROSTER!H13="AVL",ROSTER!H13=""),0,E13+1) -> 2 | G13: =IF(OR(ROSTER!I13="OFF",ROSTER!I13="AL",ROSTER!I13="SICK",ROSTER!I13="AVL",ROSTER!I13=""),0,F13+1) -> 0 | H13: =IF(OR(ROSTER!J13="OFF",ROSTER!J13="AL",ROSTER!J13="SICK",ROSTER!J13="AVL",ROSTER!J13=""),0,G13+1) -> 0 | I13: =IF(OR(ROSTER!K13="OFF",ROSTER!K13="AL",ROSTER!K13="SICK",ROSTER!K13="AVL",ROSTER!K13=""),0,H13+1) -> 0 | J13: =IF(OR(ROSTER!L13="OFF",ROSTER!L13="AL",ROSTER!L13="SICK",ROSTER!L13="AVL",ROSTER!L13=""),0,I13+1) -> 1 | K13: =IF(OR(ROSTER!M13="OFF",ROSTER!M13="AL",ROSTER!M13="SICK",ROSTER!M13="AVL",ROSTER!M13=""),0,J13+1) -> 2 | ... AD13: =IF(OR(ROSTER!AF13="OFF",ROSTER!AF13="AL",ROSTER!AF13="SICK",ROSTER!AF13="AVL",ROSTER!AF13=""),0,AC13+1) -> 3 | AE13: =MAX(C13:AD13) -> 3 | AF13: =IF(AE13>=CONFIG!$B$33,"🟣 BLOCK OT",IF(AE13>=4,"⚠️ MONITOR","✅ OK")) -> ✅ OK | AG13: =ROSTER!AP13 -> 42.875 | AH13: =ROSTER!AQ13 -> ✅ OK
A14: =ROSTER!A14 -> Kevin White | B14: =ROSTER!B14 -> Day B | C14: =IF(OR(ROSTER!E14="OFF",ROSTER!E14="AL",ROSTER!E14="SICK",ROSTER!E14="AVL",ROSTER!E14=""),0,1) -> 0 | D14: =IF(OR(ROSTER!F14="OFF",ROSTER!F14="AL",ROSTER!F14="SICK",ROSTER!F14="AVL",ROSTER!F14=""),0,C14+1) -> 0 | E14: =IF(OR(ROSTER!G14="OFF",ROSTER!G14="AL",ROSTER!G14="SICK",ROSTER!G14="AVL",ROSTER!G14=""),0,D14+1) -> 1 | F14: =IF(OR(ROSTER!H14="OFF",ROSTER!H14="AL",ROSTER!H14="SICK",ROSTER!H14="AVL",ROSTER!H14=""),0,E14+1) -> 2 | G14: =IF(OR(ROSTER!I14="OFF",ROSTER!I14="AL",ROSTER!I14="SICK",ROSTER!I14="AVL",ROSTER!I14=""),0,F14+1) -> 0 | H14: =IF(OR(ROSTER!J14="OFF",ROSTER!J14="AL",ROSTER!J14="SICK",ROSTER!J14="AVL",ROSTER!J14=""),0,G14+1) -> 0 | I14: =IF(OR(ROSTER!K14="OFF",ROSTER!K14="AL",ROSTER!K14="SICK",ROSTER!K14="AVL",ROSTER!K14=""),0,H14+1) -> 0 | J14: =IF(OR(ROSTER!L14="OFF",ROSTER!L14="AL",ROSTER!L14="SICK",ROSTER!L14="AVL",ROSTER!L14=""),0,I14+1) -> 1 | K14: =IF(OR(ROSTER!M14="OFF",ROSTER!M14="AL",ROSTER!M14="SICK",ROSTER!M14="AVL",ROSTER!M14=""),0,J14+1) -> 2 | ... AD14: =IF(OR(ROSTER!AF14="OFF",ROSTER!AF14="AL",ROSTER!AF14="SICK",ROSTER!AF14="AVL",ROSTER!AF14=""),0,AC14+1) -> 3 | AE14: =MAX(C14:AD14) -> 3 | AF14: =IF(AE14>=CONFIG!$B$33,"🟣 BLOCK OT",IF(AE14>=4,"⚠️ MONITOR","✅ OK")) -> ✅ OK | AG14: =ROSTER!AP14 -> 42.875 | AH14: =ROSTER!AQ14 -> ✅ OK
A15: =ROSTER!A15 -> Laura Adams | B15: =ROSTER!B15 -> Day B | C15: =IF(OR(ROSTER!E15="OFF",ROSTER!E15="AL",ROSTER!E15="SICK",ROSTER!E15="AVL",ROSTER!E15=""),0,1) -> 0 | D15: =IF(OR(ROSTER!F15="OFF",ROSTER!F15="AL",ROSTER!F15="SICK",ROSTER!F15="AVL",ROSTER!F15=""),0,C15+1) -> 0 | E15: =IF(OR(ROSTER!G15="OFF",ROSTER!G15="AL",ROSTER!G15="SICK",ROSTER!G15="AVL",ROSTER!G15=""),0,D15+1) -> 1 | F15: =IF(OR(ROSTER!H15="OFF",ROSTER!H15="AL",ROSTER!H15="SICK",ROSTER!H15="AVL",ROSTER!H15=""),0,E15+1) -> 2 | G15: =IF(OR(ROSTER!I15="OFF",ROSTER!I15="AL",ROSTER!I15="SICK",ROSTER!I15="AVL",ROSTER!I15=""),0,F15+1) -> 0 | H15: =IF(OR(ROSTER!J15="OFF",ROSTER!J15="AL",ROSTER!J15="SICK",ROSTER!J15="AVL",ROSTER!J15=""),0,G15+1) -> 0 | I15: =IF(OR(ROSTER!K15="OFF",ROSTER!K15="AL",ROSTER!K15="SICK",ROSTER!K15="AVL",ROSTER!K15=""),0,H15+1) -> 0 | J15: =IF(OR(ROSTER!L15="OFF",ROSTER!L15="AL",ROSTER!L15="SICK",ROSTER!L15="AVL",ROSTER!L15=""),0,I15+1) -> 1 | K15: =IF(OR(ROSTER!M15="OFF",ROSTER!M15="AL",ROSTER!M15="SICK",ROSTER!M15="AVL",ROSTER!M15=""),0,J15+1) -> 2 | ... AD15: =IF(OR(ROSTER!AF15="OFF",ROSTER!AF15="AL",ROSTER!AF15="SICK",ROSTER!AF15="AVL",ROSTER!AF15=""),0,AC15+1) -> 3 | AE15: =MAX(C15:AD15) -> 3 | AF15: =IF(AE15>=CONFIG!$B$33,"🟣 BLOCK OT",IF(AE15>=4,"⚠️ MONITOR","✅ OK")) -> ✅ OK | AG15: =ROSTER!AP15 -> 42.875 | AH15: =ROSTER!AQ15 -> ✅ OK
... A28: =ROSTER!A28 -> Yasmin Reed | B28: =ROSTER!B28 -> Day B | C28: =IF(OR(ROSTER!E28="OFF",ROSTER!E28="AL",ROSTER!E28="SICK",ROSTER!E28="AVL",ROSTER!E28=""),0,1) -> 0 | D28: =IF(OR(ROSTER!F28="OFF",ROSTER!F28="AL",ROSTER!F28="SICK",ROSTER!F28="AVL",ROSTER!F28=""),0,C28+1) -> 0 | E28: =IF(OR(ROSTER!G28="OFF",ROSTER!G28="AL",ROSTER!G28="SICK",ROSTER!G28="AVL",ROSTER!G28=""),0,D28+1) -> 1 | F28: =IF(OR(ROSTER!H28="OFF",ROSTER!H28="AL",ROSTER!H28="SICK",ROSTER!H28="AVL",ROSTER!H28=""),0,E28+1) -> 2 | G28: =IF(OR(ROSTER!I28="OFF",ROSTER!I28="AL",ROSTER!I28="SICK",ROSTER!I28="AVL",ROSTER!I28=""),0,F28+1) -> 0 | H28: =IF(OR(ROSTER!J28="OFF",ROSTER!J28="AL",ROSTER!J28="SICK",ROSTER!J28="AVL",ROSTER!J28=""),0,G28+1) -> 0 | I28: =IF(OR(ROSTER!K28="OFF",ROSTER!K28="AL",ROSTER!K28="SICK",ROSTER!K28="AVL",ROSTER!K28=""),0,H28+1) -> 0 | J28: =IF(OR(ROSTER!L28="OFF",ROSTER!L28="AL",ROSTER!L28="SICK",ROSTER!L28="AVL",ROSTER!L28=""),0,I28+1) -> 1 | K28: =IF(OR(ROSTER!M28="OFF",ROSTER!M28="AL",ROSTER!M28="SICK",ROSTER!M28="AVL",ROSTER!M28=""),0,J28+1) -> 2 | ... AD28: =IF(OR(ROSTER!AF28="OFF",ROSTER!AF28="AL",ROSTER!AF28="SICK",ROSTER!AF28="AVL",ROSTER!AF28=""),0,AC28+1) -> 3 | AE28: =MAX(C28:AD28) -> 3 | AF28: =IF(AE28>=CONFIG!$B$33,"🟣 BLOCK OT",IF(AE28>=4,"⚠️ MONITOR","✅ OK")) -> ✅ OK | AG28: =ROSTER!AP28 -> 21 | AH28: =ROSTER!AQ28 -> ✅ OK

Sheet DASHBOARD
A1: STAFFING DASHBOARD (v7)
A3: 28-DAY METRICS | E3: SHIFT CODES
A4: Total Hours Worked | B4: =SUM(ROSTER!AH4:AH50) -> 3598 | E4: E | F4: Early 6hrs | G4: 08:00-14:00
A5: Base Wage Cost | B5: =DAILY_COSTS!C31 -> 43221.5 | E5: L | F5: Late 6hrs | G5: 14:00-20:00
A6: OT Premium Paid | B6: =DAILY_COSTS!D31 -> 0 | E6: EL | F6: Full Day 12hrs | G6: 08:00-20:00
A7: Agency Day Cost | B7: =DAILY_COSTS!E31 -> 0 | E7: N | F7: Night 12hrs | G7: 19:30-08:30
A8: Agency Night Cost | B8: =DAILY_COSTS!F31 -> 0 | E8: OFF | F8: Day Off
A9: Bank Holiday Premium | B9: =DAILY_COSTS!G31 -> 0 | E9: AL | F9: Annual Leave
A10: TOTAL 28-DAY COST | B10: =DAILY_COSTS!H31 -> 43221.5 | E10: SICK | F10: Sickness
A11: Agency % of Total | B11: =IF(DAILY_COSTS!H31>0,(DAILY_COSTS!E31+DAILY_COSTS!F31)/DAILY_COSTS!H31*100,0) -> 0 | C11: % | E11: ADM | F11: Admin | G11: Float base
A12: Avg Daily Cost | B12: =DAILY_COSTS!H31/28 -> 1543.625 | E12: TRN | F12: Training
E13: AVL | F13: Available | G13: Float standby
A14: STAFF DEPLOYMENT | E14: OC-E | F14: On-Call Early | G14: +£2/hr (6hrs)
A15: Day A | B15: =COUNTIFS(ROSTER!$B$4:$B$50,"Day A") -> 8 | E15: OC-L | F15: On-Call Late | G15: +£2/hr (6hrs)
A16: Day B | B16: =COUNTIFS(ROSTER!$B$4:$B$50,"Day B") -> 8 | E16: OC-EL | F16: On-Call Full | G16: +£2/hr (12hrs)
A17: Night A | B17: =COUNTIFS(ROSTER!$B$4:$B$50,"Night A") -> 3 | E17: OC-N | F17: On-Call Night | G17: +£2/hr (12hrs)
A18: Night B | B18: =COUNTIFS(ROSTER!$B$4:$B$50,"Night B") -> 3 | E18: AG-E | F18: Agency Early | G18: £22/hr
A19: Float | B19: =COUNTIFS(ROSTER!$B$4:$B$50,"Float") -> 3 | E19: AG-L | F19: Agency Late | G19: £22/hr
A20: TOTAL | B20: =SUM(B15:B19) -> 25 | E20: AG-N | F20: Agency Night | G20: £28/hr
A22: SCENARIO PROJECTIONS (Annual) | E22: BH-D | F22: Bank Holiday Day | G22: rate x 1.5
A23: =SCENARIO_MODEL!A23 -> CLEAN (Zero disruption) | B23: =SCENARIO_MODEL!Q23 -> 563423.12 | E23: BH-N | F23: Bank Holiday Night | G23: rate x 1.5
A24: =SCENARIO_MODEL!A24 -> TYPICAL WEEK | B24: =SCENARIO_MODEL!Q24 -> 670733.12
A25: =SCENARIO_MODEL!A25 -> BAD WEEK | B25: =SCENARIO_MODEL!Q25 -> 733330.62
A26: =SCENARIO_MODEL!A26 -> CRISIS WEEK | B26: =SCENARIO_MODEL!Q26 -> 742273.12
A27: =SCENARIO_MODEL!A27 -> WORST CASE (Winter/Flu) | B27: =SCENARIO_MODEL!Q27 -> 751215.62
A28: =SCENARIO_MODEL!A28 -> PANDEMIC / NOROVIRUS | B28: =SCENARIO_MODEL!Q28 -> 858525.62
A30: AGENCY KILL ANNUAL SAVING | B30: =SCENARIO_MODEL!B34 -> 105521.5
A33: SHIFT CODE REFERENCE
A34: E | B34: Early (6hr)
A35: L | B35: Late (6hr)
A36: EL | B36: Full Day (12.25hr)
A37: N | B37: Night (12.25hr)
A38: OFF | B38: Day Off
A39: AL | B39: Annual Leave
A40: SICK | B40: Sick Leave
A41: ADM | B41: Admin
A42: TRN | B42: Training
A43: AVL | B43: Float Available
A44: OC-E/L/EL/N | B44: On-Call (OT prem)
A45: AG-E/L/N | B45: Agency Cover
A46: BH-D/BH-N | B46: Bank Holiday

Sheet FULL_P_AND_L
A1: FULL P&L — ACQUISITION BUSINESS CASE
B4: BEFORE | C4: YEAR 1 | D4: YEAR 2
A6: REVENUE
A7: Beds | B7: 40 | C7: 40 | D7: 40
A8: Occupancy | B8: 0.82 | C8: 0.88 | D8: 0.9
A9: Occupied | B9: =B7*B8 -> 32.8 | C9: =C7*C8 -> 35.2 | D9: =D7*D8 -> 36
A10: Council £/wk | B10: 880 | C10: 930 | D10: 970
A11: Private £/wk | B11: 1100 | C11: 1250 | D11: 1350
A12: Private Mix | B12: 0.25 | C12: 0.3 | D12: 0.35
A13: Council Beds | B13: =B9*(1-B12) -> 24.6 | C13: =C9*(1-C12) -> 24.64 | D13: =D9*(1-D12) -> 23.4
A14: Private Beds | B14: =B9*B12 -> 8.2 | C14: =C9*C12 -> 10.56 | D14: =D9*D12 -> 12.6
A15: TOTAL REVENUE | B15: =(B13*B10+B14*B11)*52 -> 1594736 | C15: =(C13*C10+C14*C11)*52 -> 1877990.4 | D15: =(D13*D10+D14*D11)*52 -> 2064816
A17: COSTS
A18: Direct Care Wages | B18: =DAILY_COSTS!C31/28*365 -> 563423.12 | C18: =IF(B8=0,0,B18*(1+0.067)*(C8/B8)) -> 645160.7 | D18: =IF(C8=0,0,C18*(1+0.05)*(D8/C8)) -> 692814.62 | E18: Model +5% NLW +3% Yr2
A19: Agency Spend | B19: =B18*0.106 -> 59722.851 | C19: =C18*0.03 -> 19354.821 | D19: =D18*0.015 -> 10392.219
A20: OT Premiums | B20: =B18*0.01 -> 5634.2312 | C20: =C18*0.035 -> 22580.625 | D20: =D18*0.025 -> 17320.365
A21: DIRECT CARE TOTAL | B21: =SUM(B18:B20) -> 628780.21 | C21: =SUM(C18:C20) -> 687096.15 | D21: =SUM(D18:D20) -> 720527.2
A23: Non-Care Staff
A24: Reg Manager | B24: 45000 | C24: =B24*1.04 -> 46800 | D24: =C24*1.04 -> 48672
A25: Deputy | B25: 32000 | C25: =B25*1.04 -> 33280 | D25: =C25*1.04 -> 34611.2
A26: Admin | B26: 22000 | C26: =B26*1.05 -> 23100 | D26: =C26*1.05 -> 24255
A27: Kitchen ×2 | B27: 44000 | C27: =IF(B8=0,B27,B27*(0.7+0.3*C8/B8)*1.067) -> 47978.566 | D27: =IF(C8=0,C27,C27*(0.7+0.3*D8/C8)*1.05) -> 50720.977
A28: Domestic ×2.5 | B28: 40000 | C28: =IF(B8=0,B28,B28*(0.5+0.5*C8/B8)*1.067) -> 44241.463 | D28: =IF(C8=0,C28,C28*(0.5+0.5*D8/C8)*1.05) -> 46981.418
A29: Maintenance | B29: 12000 | C29: =B29*1.03 -> 12360 | D29: =C29*1.03 -> 12730.8
A30: NON-CARE TOTAL | B30: =SUM(B24:B29) -> 195000 | C30: =SUM(C24:C29) -> 207760.03 | D30: =SUM(D24:D29) -> 217971.39
A32: Employer NI 15% (2025/26) | B32: =MAX((B21+B30)-33*5000,0)*0.15-10500 -> 88317.031 | C32: =MAX((C21+C30)-33*5000,0)*0.15-10500 -> 98978.427 | D32: =MAX((D21+D30)-33*5000,0)*0.15-10500 -> 105524.79 | E32: 13.8% after £9,100/employee threshold (33 staff)
A33: Pension 3% | B33: =(B21+B30)*0.03 -> 24713.406 | C33: =(C21+C30)*0.03 -> 26845.685 | D33: =(D21+D30)*0.03 -> 28154.958
A34: Recruitment & Training | B34: 12000 | C34: 20000 | D34: 10000
A35: ON-COSTS TOTAL | B35: =SUM(B32:B34) -> 125030.44 | C35: =SUM(C32:C34) -> 145824.11 | D35: =SUM(D32:D34) -> 143679.75
A37: ALL-IN STAFF COST | B37: =B21+B30+B35 -> 948810.64 | C37: =C21+C30+C35 -> 1040680.3 | D37: =D21+D30+D35 -> 1082178.3
A38: Staff % Revenue | B38: =IF(B15=0,0,B37/B15) -> 0.59496408 | C38: =IF(C15=0,0,C37/C15) -> 0.55414569 | D38: =IF(D15=0,0,D37/D15) -> 0.52410401 | E38: Industry: 59-60%. Target: 52-56%
A40: Property & Ops
A41: Food & Catering | B41: 65000 | C41: 68000 | D41: 72000
A42: Utilities | B42: 42000 | C42: 40000 | D42: 38000
A43: Insurance | B43: 30000 | C43: 31000 | D43: 32000
A44: Maintenance | B44: 25000 | C44: 30000 | D44: 25000
A45: CQC & Compliance | B45: 7000 | C45: 7500 | D45: 8000
A46: IT & Systems | B46: 8000 | C46: 12000 | D46: 10000
A47: Marketing | B47: 5000 | C47: 18000 | D47: 12000
A48: Sundries | B48: 15000 | C48: 16000 | D48: 17000
A49: Winter Prep Fund | B49: 0 | C49: 12000 | D49: 10000
A50: OPS TOTAL | B50: =SUM(B41:B49) -> 197000 | C50: =SUM(C41:C49) -> 234500 | D50: =SUM(D41:D49) -> 224000
A52: TOTAL COSTS | B52: =B37+B50 -> 1145810.6 | C52: =C37+C50 -> 1275180.3 | D52: =D37+D50 -> 1306178.3
A54: EBITDA | B54: =B15-B52 -> 448925.36 | C54: =C15-C52 -> 602810.11 | D54: =D15-D52 -> 758637.65
A55: EBITDA Margin | B55: =IF(B15=0,0,B54/B15) -> 0.2815045 | C55: =IF(C15=0,0,C54/C15) -> 0.32098679 | D55: =IF(D15=0,0,D54/D15) -> 0.36741175 | E55: Industry: 7-17%. Target: 15-22%
A57: EBITDA Multiple | B57: 6 | C57: 6 | D57: 6
A58: Enterprise Value | B58: =B54*B57 -> 2693552.1 | C58: =C54*C57 -> 3616860.7 | D58: =D54*D57 -> 4551825.9
A59: VALUE CREATED | B59: — | C59: =C58-B58 -> 923308.52 | D59: =D58-B58 -> 1858273.8
A61: ×10 homes | C61: =C59*10 -> 9233085.2 | D61: =D59*10 -> 18582738
A62: ×30 homes | C62: =C59*30 -> 27699256 | D62: =D59*30 -> 55748214
